Workbook

Sheet Summary
A1: Description | B1: Value | C1: Actual Load KVA
B2: As per the Sanction Letter | C2: Usage measured on 1of every month
A3: Utility Sanction Load KVA | B3: 14000 KVA | C3: 7760 KVA
A4: Utility Minimum Demand % | B4: 75
A6: Capacity Installed | B6: Transformer kW | C6: No of TX | D6: Catcher TX kW | E6: No. Of catcher | F6: Actual Load kW | G6: Generator kW | H6: No of DG | I6: Catcher DG kW | J6: No. Of catcher | K6: UPS kW | L6: UPS Config | M6: IT capacity Installed kW | N6: IT Power Sold in kW ( concidering unity as PF) | O6: Allocated IT Power to customer ( Taking 50% as divercity factor for rated power customer ) | P6: IT kW Usage | Q6: Avaialble IT kW Design-Used | R6: Available IT kW Design-Sold | S6: Available IT kW Design-Sold ( Allocated capacity) | T6: MAX Rack Capacity | U6: Racks which can be placed on floor | V6: Rack losss ( Cage+ non standard rack+ path) | W6: Available space | X6: Designed White Space ( in SQ FT) | Y6: Used White Space( in SQ FT) | Z6: Avaialble White Space ( in SQ FT)
B7: Mention the design kW capacity of Transformer | G7: Mention the design kW capacity of Generator | K7: Mention the design N capacity in kw in a N+N Configuration | M7: Installed including interfloor shared capacity | N7: Customer subscribed IT kW | O7: Allocated power | P7: Measured on 1st of every month | Q7: Measured on 1st of every month | R7: Measured on 1st of every month | S7: Measured on 1st of every month
A8: L1 | B8: =2750*0.9 -> 2475 | C8: 1 | D8: =2750*0.9 -> 2475 | E8: 1 | F8: 1046 | G8: =3000*0.8 -> 2400 | H8: 1 | I8: =3000*0.8 -> 2400 | J8: 1 | K8: 2160 | L8: Bank A ( 1250 KVA* 2) & Bank B (600 KVA *4 ) | M8: 2160 | N8: 2160 | O8: 2160 | P8: ='Noida-01'!U168 -> 954.80061 | Q8: =M8-P8 -> 1205.1994 | R8: =M8-N8 -> 0 | S8: =M8-O8 -> 0 | T8: 220 | U8: 220 | V8: 0 | W8: 0 | X8: 7384 | Y8: 7384 | Z8: =X8-Y8 -> 0
A9: L2 | B9: =2750*0.9 -> 2475 | C9: 1 | F9: 860 | G9: =3000*0.8 -> 2400 | H9: 1 | K9: 2160 | L9: Bank A ( 1250 KVA* 2) & Bank B (600 KVA *4 ) | M9: 2160 | N9: 2160 | O9: 2160 | P9: ='Noida-01'!U169 -> 737.80376 | Q9: =M9-P9 -> 1422.1962 | R9: =M9-N9 -> 0 | S9: =M9-O9 -> 0 | T9: 220 | U9: 220 | V9: 0 | W9: 0 | X9: 7384 | Y9: 7384 | Z9: =X9-Y9 -> 0
A10: L3 | B10: =2750*0.9 -> 2475 | C10: 1 | F10: 837 | G10: =3000*0.8 -> 2400 | H10: 1 | K10: 2160 | L10: Bank A ( 1250 KVA* 2) & Bank B (600 KVA *4 ) | M10: 2160 | N10: 2160 | O10: 2160 | P10: ='Noida-01'!U170 -> 914.58874 | Q10: =M10-P10 -> 1245.4113 | R10: =M10-N10 -> 0 | S10: =M10-O10 -> 0 | T10: 220 | U10: 220 | V10: 0 | W10: 0 | X10: 7384 | Y10: 7384 | Z10: =X10-Y10 -> 0
A11: L4 | B11: =2250*0.9 -> 2025 | C11: 1 | D11: =2500*0.9 -> 2250 | E11: 1 | F11: 1048 | G11: =2000*0.8 -> 1600 | H11: 1 | I11: =2500*0.8 -> 2000 | J11: 1 | K11: 1440 | L11: Bank A ( 400 KVA* 4) & Bank B (400 KVA *4 ) | M11: =1600*0.9 -> 1440 | N11: ='Noida-01'!T120 -> 1484.18 | O11: ='Noida-01'!Y120 -> #REF! | P11: ='Noida-01'!Z120 -> 614.16729 | Q11: =M11-P11 -> 825.83271 | R11: =M11-N11 -> -44.18 | S11: =M11-O11 -> #REF! | T11: 392 | U11: ='Noida-01'!L124 -> 313.95238 | V11: =69 -> 69 | W11: =T11-(U11+V11) -> 9.047619 | X11: 7300 | Y11: 7300 | Z11: =X11-Y11 -> 0
A12: L5 | B12: =2250*0.9 -> 2025 | C12: 1 | F12: 1062 | G12: =2250*0.8 -> 1800 | H12: 1 | K12: 1440 | L12: Bank A ( 400 KVA* 4) & Bank B (400 KVA *4 ) | M12: =800*0.9+100 -> 820 | N12: ='Noida-01'!T70 -> 933.87 | O12: ='Noida-01'!Y70 -> #REF! | P12: ='Noida-01'!Z70 -> 589.69917 | Q12: =M12-P12 -> 230.30083 | R12: =M12-N12 -> -113.87 | S12: =M12-O12 -> #REF! | T12: 353 | U12: ='Noida-01'!L74 -> 286.14286 | V12: 50 | W12: =T12-(U12+V12) -> 16.857143 | X12: 9200 | Y12: 9200 | Z12: =X12-Y12 -> 0
A13: L6 | M13: =720-100 -> 620 | N13: ='Noida-01'!T158 -> 1080.49 | O13: ='Noida-01'!Y158 -> #REF! | P13: ='Noida-01'!Z158 -> 500.87619 | Q13: =M13-P13 -> 119.12381 | R13: =M13-N13 -> -460.49 | S13: =M13-O13 -> #REF! | T13: 258 | U13: ='Noida-01'!L162 -> 244.71429 | V13: =34 -> 34 | W13: =T13-(U13+V13) -> -20.714286 | X13: 6000 | Y13: 6000 | Z13: =X13-Y13 -> 0
A14: L7 | B14: =2500*0.9 -> 2250 | C14: 1 | F14: 193 | G14: =2250*0.8 -> 1800 | H14: 1 | K14: 1700 | L14: Bank A ( 450 KVA* 4) & Bank B (450 KVA *4 ) | M14: 1400 | N14: ='Noida-01'!T226 -> 1436.8 | O14: ='Noida-01'!Y226 -> #REF! | P14: ='Noida-01'!Z226 -> 563.71504 | Q14: =M14-P14 -> 836.28496 | R14: =M14-N14 -> -36.8 | S14: =M14-O14 -> #REF! | T14: 261 | U14: ='Noida-01'!L231 -> 251.71429 | V14: 13 | W14: =T14-(U14+V14) -> -3.7142857 | X14: 6850 | Y14: 6850 | Z14: =X14-Y14 -> 0 | AA14: From L7 To L6 & l5 =150 KVA L6+ 120 KVA L5
A15: Total | K15: =SUM(K8:K14) -> 11060 | M15: =SUM(M8:M14) -> 10760 | N15: =SUM(N8:N14) -> 11415.34 | O15: =SUM(O8:O14) -> #REF! | P15: =SUM(P8:P14) -> 4875.6508 | Q15: =SUM(Q8:Q14) -> 5884.3492 | T15: =SUM(T8:T14) -> 1924 | U15: =SUM(U8:U14) -> 1756.5238 | V15: =SUM(V8:V14) -> 166
T17: =T15 -> 1924 | U17: =U15+V15 -> 1922.5238

Sheet Terminated
S1: Divisification | U1: 0.5 | V1: Rated to Consumed | X1: =#REF! -> #REF! | Z1: Actual PUE | AA1: 2.21 | AB1: Actual Unit Rate: | AC1: 10.35 | AD1: =+AA1*(AC1*(30.5*24-AF1)+AF1*20) -> 18246.92 | AE1: Genset Hr/Mo | AF1: 70.5
D2: Billing Model | F2: Space | O2: Power Capacity | Z2: Power Usage | AE2: Seating Space | AM2: Revenue (Monthly ) | AT2: Contract Information
A3: Floor | B3: Floor / Module | C3: Customer Name | D3: Power Subscription Model (Rated/Subscribed) | E3: Power Usage Model (Bundled / Metered) | F3: Subscription Mode | G3: Caged /Uncaged | H3: UoM | I3: Subscription | J3: In Use | K3: Yet to be given/ | L3: Billed | M3: Reserved Capacity if any (Non-Billable) | N3: Per Unit rate (MRC) | O3: Subscription Model | P3: UoM | Q3: Total Capacity Purchased | R3: Capacity in Use | S3: Capacity to be given | T3: Reserved Capacity if any | U3: Subscribed Capacity to be given in KW | V3: "Allocated" Capacity in KW (for KVA subscribed customer 50% diversity is used to make kW ) | W3: DC NW Infra | X3: Billable Additional Capacity | Y3: Additional Capacity Charges (MRC) | Z3: Usage Model | AA3: Multiplier | AB3: Uit rate Model (Fixed/Variable) | AC3: Unit Rate (per KW-HR) | AD3: No Of Units (KW-HR/ Month | AE3: Subscription Model | AF3: UoM | AG3: Subscription | AH3: In Use | AI3: Yet to be given | AJ3: Billed | AK3: Reserved Capacity if any | AL3: Per Unit rate | AM3: Space revenue including capacity | AN3: Additional Capacity Revenue | AO3: Power Usage revenue | AP3: Seating Space | AQ3: Any Other Items | AR3: Total Revenue | AS3: Billing Frequency | AT3: Sales Order ref No | AU3: Contract Start Date | AV3: Term of Contract (No of Years) | AW3: Current Exiry Date | AX3: Remarks if any | AZ3: Avg revenue /Rack /Month | BA3: Avg revenue /KW /Month | BB3: Net Revenue / Resvd KW | BC3: Proj Net Revenue / Resvd KW | BD3: Sold Net Revenue / Resvd KW | BF3: Total Rev (Cap + Power) | BG3: Capacity Revenue | BH3: Power Revenue | BI3: Cost of Power @ Act Usage | BJ3: Proj Cost of Power @ Reserv Cap | BK3: Cost of Power @ Design Use | BL3: Net Rev Total | BM3: Target Capacity Revenue | BN3: Capacity Surplus/Leakage | BO3: Power Surplus/Leakage | BP3: Contribution to Target | BQ3: KW | BS3: Power Surplus/Leakage | BT3: Capacity Surplus/Leakage | BU3: Total Surplus/Leakage | BV3: Power Surplus/Leakage / KW | BW3: Capacity Surplus/Leakage / KW | BX3: Total Surplus/Leakage / KW
A4: L5 | B4: L5A-05-11 | C4: KESCO (Kanpur Elec) | D4: Rated | E4: Bundled | F4: Rack | G4: Uncaged | H4: =IF(F4="Rack","No of Racks",(IF(F4="Space","Sq Ft","U Space"))) -> No of Racks | I4: 1 | J4: 0 | K4: =I4-J4 -> 1 | L4: 0 | N4: =((5736886/6)/12)*0+(420000+200000)/12 -> 51666.667 | O4: =D4 -> Rated | P4: KVA | Q4: 0 | R4: 0 | S4: =Q4-R4 -> 0 | U4: =IF(S4<=0,0,(IF(O4="Rated",(S4+T4)*'Noida-01'!#REF!,(S4+T4)))) -> 0 | V4: =IF(O4="Rated",Q4*'Noida-01'!#REF!,Q4) -> #REF! | W4: 0 | X4: =IF((S4*-1)>0, (S4*-1), 0) -> 0 | Y4: 0 | Z4: =E4 -> Bundled | AF4: =IF(AE4="No of Seats","No of Seats",(IF(AE4="Space","Sq Ft",""))) | AI4: =AG4-AH4 -> 0 | AM4: =N4*L4 -> 0 | AN4: =Y4*X4 -> 0 | AO4: =AD4*AC4*AA4 -> 0 | AP4: =AL4*AJ4 -> 0 | AQ4: =(1923838/6)/12 -> 26719.972 | AR4: =SUBTOTAL(9,AM4:AQ4) -> 26719.972 | AT4: 721003675 & 711080579 | AZ4: =IF(F4="Rack",AR4/I4,0)+IF(F4="U Space",AR4*40/I4,0)+IF(F4="Space",AR4*30/I4,0) -> 26719.972 | BA4: =+AR4/V4 -> #REF! | BB4: =+($AM4+$AN4+$AO4-BI4)/$V4 -> #REF! | BC4: =+($AM4+$AN4+$AO4-BJ4)/$V4 -> #REF! | BD4: =+($AM4+$AN4+IF(E4="Bundled",0,V4*0.85*AA4*AC4*30.5*24)-BK4)/$V4 -> #REF! | BF4: =+AM4+AN4+AO4 -> 0 | BG4: =+BF4-BH4 -> #REF! | BH4: =IF(E4="Bundled",MIN(V4*'Noida-01'!#REF!*(1+#REF!),BF4),AO4) -> #REF! | BI4: =IF($AD4>0,$AD4*'Noida-01'!#REF!*'Noida-01'!#REF!*(1+'Noida-01'!#REF!*(20/'Noida-01'!#REF!)/732),'Noida-01'!#REF!*W4) -> #REF! | BJ4: =IF($AD4>0,$AD4*'Noida-01'!#REF!*'Noida-01'!#REF!*(1+'Noida-01'!#REF!*(20/'Noida-01'!#REF!)/732),+'Noida-01'!#REF!*(W4+U4)) -> #REF! | BK4: =IF(E4="Bundled",'Noida-01'!#REF!*V4,'Noida-01'!#REF!*V4*0.85) -> #REF! | BL4: =+BB4*V4 -> #REF! | BM4: =+#REF!*V4 -> #REF! | BN4: =+BG4-BM4 -> #REF! | BO4: =+BH4-BI4 -> #REF! | BP4: =+BN4+BO4 -> #REF! | BQ4: =+V4 -> #REF! | BR4: =+BB4 -> #REF! | BS4: =IF(E4="Bundled",BK4-BI4,AO4-BI4) -> #REF! | BT4: =IF(E4="Bundled",+(BD4-#REF!)*V4,(AM4+AN4)-V4*#REF!) -> #REF! | BU4: =+BS4+BT4 -> #REF! | BV4: =+BS4/$BQ4 -> #REF! | BW4: =+BT4/$BQ4 -> #REF! | BX4: =+BU4/$BQ4 -> #REF!
A5: L4 | B5: L4-F-24 & L4-F-29 | C5: Adani Wilmar Limited | D5: Rated | E5: Bundled | F5: Rack | G5: Uncaged | H5: =IF(F5="Rack","No of Racks",(IF(F5="Space","Sq Ft","U Space"))) -> No of Racks | I5: 4 | J5: 0 | K5: 0 | L5: 0 | N5: =((175000+619000+619000+619000)/4)/12 -> 42333.333 | O5: =D5 -> Rated | P5: KVA | Q5: 0 | R5: 0 | S5: =Q5-R5 -> 0 | U5: =IF(S5<=0,0,(IF(O5="Rated",(S5+T5)*'Noida-01'!#REF!,(S5+T5)))) -> 0 | V5: =IF(O5="Rated",Q5*'Noida-01'!#REF!,Q5) -> #REF! | W5: 0 | X5: =IF((S5*-1)>0, (S5*-1), 0) -> 0 | Y5: =70000/12 -> 5833.3333 | Z5: =E5 -> Bundled | AI5: =AG5-AH5 -> 0 | AL5: =(0)/12 -> 0 | AM5: =N5*L5 -> 0 | AN5: =Y5*X5 -> 0 | AO5: =AD5*AC5*AA5 -> 0 | AP5: =AL5*AJ5 -> 0 | AQ5: =(140000+88000+45000)/12 -> 22750 | AR5: =SUBTOTAL(9,AM5:AQ5) -> 22750 | AT5: 121000894 & 121000913 | AU5: 43831 | AV5: 1 | AW5: 44196 | AZ5: =IF(F5="Rack",AR5/I5,0)+IF(F5="U Space",AR5*40/I5,0)+IF(F5="Space",AR5*30/I5,0) -> 5687.5 | BA5: =+AR5/V5 -> #REF! | BB5: =+($AM5+$AN5+$AO5-BI5)/$V5 -> #REF! | BC5: =+($AM5+$AN5+$AO5-BJ5)/$V5 -> #REF! | BD5: =+($AM5+$AN5+IF(E5="Bundled",0,V5*0.85*AA5*AC5*30.5*24)-BK5)/$V5 -> #REF! | BF5: =+AM5+AN5+AO5 -> 0 | BG5: =+BF5-BH5 -> #REF! | BH5: =IF(E5="Bundled",MIN(V5*'Noida-01'!#REF!*(1+#REF!),BF5),AO5) -> #REF! | BI5: =IF($AD5>0,$AD5*'Noida-01'!#REF!*'Noida-01'!#REF!*(1+'Noida-01'!#REF!*(20/'Noida-01'!#REF!)/732),'Noida-01'!#REF!*W5) -> #REF! | BJ5: =IF($AD5>0,$AD5*'Noida-01'!#REF!*'Noida-01'!#REF!*(1+'Noida-01'!#REF!*(20/'Noida-01'!#REF!)/732),+'Noida-01'!#REF!*(W5+U5)) -> #REF! | BK5: =IF(E5="Bundled",'Noida-01'!#REF!*V5,'Noida-01'!#REF!*V5*0.85) -> #REF! | BL5: =+BB5*V5 -> #REF! | BM5: =+#REF!*V5 -> #REF! | BN5: =+BG5-BM5 -> #REF! | BO5: =+BH5-BI5 -> #REF! | BP5: =+BN5+BO5 -> #REF! | BQ5: =+V5 -> #REF! | BR5: =+BB5 -> #REF! | BS5: =IF(E5="Bundled",BK5-BI5,AO5-BI5) -> #REF! | BT5: =IF(E5="Bundled",+(BD5-#REF!)*V5,(AM5+AN5)-V5*#REF!) -> #REF! | BU5: =+BS5+BT5 -> #REF! | BV5: =+BS5/$BQ5 -> #REF! | BW5: =+BT5/$BQ5 -> #REF! | BX5: =+BU5/$BQ5 -> #REF!
A6: L5 | B6: L5B-01-05 & L5B-01-06 | C6: MJUNCTION SERVICES LIMITED | D6: Rated | E6: Bundled | F6: Rack | G6: Uncaged | H6: =IF(F6="Rack","No of Racks",(IF(F6="Space","Sq Ft","U Space"))) -> No of Racks | I6: 2 | J6: 0 | K6: 0 | L6: 0 | N6: =800000/12 -> 66666.667 | O6: =D6 -> Rated | P6: KVA | Q6: 0 | R6: 0 | S6: =Q6-R6 -> 0 | U6: =IF(S6<=0,0,(IF(O6="Rated",(S6+T6)*'Noida-01'!#REF!,(S6+T6)))) -> 0 | V6: =IF(O6="Rated",Q6*'Noida-01'!#REF!,Q6) -> #REF! | W6: 0 | X6: =IF((S6*-1)>0, (S6*-1), 0) -> 0 | Y6: =80000/12 -> 6666.6667 | Z6: =E6 -> Bundled | AE6: No of Seats | AF6: =IF(AE6="No of Seats","No of Seats",(IF(AE6="Space","Sq Ft",""))) -> No of Seats | AG6: 0 | AH6: 0 | AI6: =AG6-AH6 -> 0 | AJ6: 0 | AL6: 0 | AM6: =N6*L6 -> 0 | AN6: =Y6*X6 -> 0 | AO6: =AD6*AC6*AA6 -> 0 | AP6: =AL6*AJ6 -> 0 | AR6: =SUBTOTAL(9,AM6:AQ6) -> 0 | AT6: 721004949 | AZ6: =IF(F6="Rack",AR6/I6,0)+IF(F6="U Space",AR6*40/I6,0)+IF(F6="Space",AR6*30/I6,0) -> 0 | BA6: =+AR6/V6 -> #REF! | BB6: =+($AM6+$AN6+$AO6-BI6)/$V6 -> #REF! | BC6: =+($AM6+$AN6+$AO6-BJ6)/$V6 -> #REF! | BD6: =+($AM6+$AN6+IF(E6="Bundled",0,V6*0.85*AA6*AC6*30.5*24)-BK6)/$V6 -> #REF! | BF6: =+AM6+AN6+AO6 -> 0 | BG6: =+BF6-BH6 -> #REF! | BH6: =IF(E6="Bundled",MIN(V6*'Noida-01'!#REF!*(1+#REF!),BF6),AO6) -> #REF! | BI6: =IF($AD6>0,$AD6*'Noida-01'!#REF!*'Noida-01'!#REF!*(1+'Noida-01'!#REF!*(20/'Noida-01'!#REF!)/732),'Noida-01'!#REF!*W6) -> #REF! | BJ6: =IF($AD6>0,$AD6*'Noida-01'!#REF!*'Noida-01'!#REF!*(1+'Noida-01'!#REF!*(20/'Noida-01'!#REF!)/732),+'Noida-01'!#REF!*(W6+U6)) -> #REF! | BK6: =IF(E6="Bundled",'Noida-01'!#REF!*V6,'Noida-01'!#REF!*V6*0.85) -> #REF! | BL6: =+BB6*V6 -> #REF! | BM6: =+#REF!*V6 -> #REF! | BN6: =+BG6-BM6 -> #REF! | BO6: =+BH6-BI6 -> #REF! | BP6: =+BN6+BO6 -> #REF! | BQ6: =+V6 -> #REF! | BR6: =+BB6 -> #REF! | BS6: =IF(E6="Bundled",BK6-BI6,AO6-BI6) -> #REF! | BT6: =IF(E6="Bundled",+(BD6-#REF!)*V6,(AM6+AN6)-V6*#REF!) -> #REF! | BU6: =+BS6+BT6 -> #REF! | BV6: =+BS6/$BQ6 -> #REF! | BW6: =+BT6/$BQ6 -> #REF! | BX6: =+BU6/$BQ6 -> #REF!
A7: L4 | B7: L4-E-29 | C7: E2 Info Solution | D7: Rated | E7: Bundled | F7: U space | G7: Uncaged | H7: =IF(F7="Rack","No of Racks",(IF(F7="Space","Sq Ft","U Space"))) -> U Space | I7: 2 | J7: 0 | K7: =I7-J7 -> 2 | L7: 0 | N7: =55000/12/2 -> 2291.6667 | O7: =D7 -> Rated | P7: KVA | Q7: 0 | R7: 0 | S7: =Q7-R7 -> 0 | U7: =IF(S7<=0,0,(IF(O7="Rated",(S7+T7)*$U$1,(S7+T7)))) -> 0 | V7: =IF(O7="Rated",Q7*$U$1,Q7) -> 0 | X7: =IF((S7*-1)>0, (S7*-1), 0) -> 0 | Y7: =90000/12 -> 7500 | Z7: =E7 -> Bundled | AI7: =AG7-AH7 -> 0 | AL7: =(0)/12 -> 0 | AM7: =N7*L7 -> 0 | AN7: =Y7*X7 -> 0 | AO7: =AD7*AC7*AA7 -> 0 | AP7: =AL7*AJ7 -> 0 | AQ7: =0/12 -> 0 | AR7: =SUBTOTAL(9,AM7:AQ7) -> 0 | AZ7: =IF(F7="Rack",AR7/I7,0)+IF(F7="U Space",AR7*40/I7,0)+IF(F7="Space",AR7*30/I7,0) -> 0 | BA7: =+AR7/V7 -> #DIV/0! | BB7: =+($AM7+$AN7+$AO7-BI7)/$V7 -> #DIV/0! | BC7: =+($AM7+$AN7+$AO7-BJ7)/$V7 -> #DIV/0! | BD7: =+($AM7+$AN7+IF(E7="Bundled",0,V7*0.85*AA7*AC7*30.5*24)-BK7)/$V7 -> #DIV/0! | BF7: =+AM7+AN7+AO7 -> 0 | BG7: =+BF7-BH7 -> #REF! | BH7: =IF(E7="Bundled",MIN(V7*$AD$1*(1+#REF!),BF7),AO7) -> #REF! | BI7: =IF($AD7>0,$AD7*$AA$1*$AC$1*(1+$AF$1*(20/$AC$1)/732),$AD$1*W7) -> 0 | BJ7: =IF($AD7>0,$AD7*$AA$1*$AC$1*(1+$AF$1*(20/$AC$1)/732),+$AD$1*(W7+U7)) -> 0 | BK7: =IF(E7="Bundled",$AD$1*V7,$AD$1*V7*0.85) -> 0 | BL7: =+BB7*V7 -> #DIV/0! | BM7: =+#REF!*V7 -> #REF! | BN7: =+BG7-BM7 -> #REF! | BO7: =+BH7-BI7 -> #REF! | BP7: =+BN7+BO7 -> #REF! | BQ7: =+V7 -> 0 | BR7: =+BB7 -> #DIV/0! | BS7: =IF(E7="Bundled",BK7-BI7,AO7-BI7) -> 0 | BT7: =IF(E7="Bundled",+(BD7-#REF!)*V7,(AM7+AN7)-V7*#REF!) -> #DIV/0! | BU7: =+BS7+BT7 -> #DIV/0! | BV7: =+BS7/$BQ7 -> #DIV/0! | BW7: =+BT7/$BQ7 -> #DIV/0! | BX7: =+BU7/$BQ7 -> #DIV/0!
A8: L6 | B8: L6-F-25 | C8: NGC Broadband | D8: Rated | E8: Bundled | F8: U space | G8: Uncaged | H8: =IF(F8="Rack","No of Racks",(IF(F8="Space","Sq Ft","U Space"))) -> U Space | I8: 2 | J8: 2 | K8: =I8-J8 -> 0 | L8: 2 | N8: =(35000)/12 -> 2916.6667 | O8: =D8 -> Rated | P8: KVA | Q8: 0.5 | R8: 0.28 | S8: =Q8-R8 -> 0.22 | U8: =IF(S8<=0,0,(IF(O8="Rated",(S8+T8)*$U$1,(S8+T8)))) -> 0.11 | V8: =IF(O8="Rated",Q8*$U$1,Q8) -> 0.25 | X8: =IF((S8*-1)>0, (S8*-1), 0) -> 0 | Y8: =99000/12 -> 8250 | Z8: =E8 -> Bundled | AF8: =IF(AE8="No of Seats","No of Seats",(IF(AE8="Space","Sq Ft",""))) | AI8: =AG8-AH8 -> 0 | AM8: =N8*L8 -> 5833.3333 | AN8: =Y8*X8 -> 0 | AO8: =AD8*AC8*AA8 -> 0 | AP8: =AL8*AJ8 -> 0 | AQ8: 0 | AR8: =SUBTOTAL(9,AM8:AQ8) -> 5833.3333 | AZ8: =IF(F8="Rack",AR8/I8,0)+IF(F8="U Space",AR8*40/I8,0)+IF(F8="Space",AR8*30/I8,0) -> 116666.67 | BA8: =+AR8/V8 -> 23333.333 | BB8: =+($AM8+$AN8+$AO8-BI8)/$V8 -> 23333.333 | BC8: =+($AM8+$AN8+$AO8-BJ8)/$V8 -> 15304.688 | BD8: =+($AM8+$AN8+IF(E8="Bundled",0,V8*0.85*AA8*AC8*30.5*24)-BK8)/$V8 -> 5086.4131 | BF8: =+AM8+AN8+AO8 -> 5833.3333 | BG8: =+BF8-BH8 -> #REF! | BH8: =IF(E8="Bundled",MIN(V8*$AD$1*(1+#REF!),BF8),AO8) -> #REF! | BI8: =IF($AD8>0,$AD8*$AA$1*$AC$1*(1+$AF$1*(20/$AC$1)/732),$AD$1*W8) -> 0 | BJ8: =IF($AD8>0,$AD8*$AA$1*$AC$1*(1+$AF$1*(20/$AC$1)/732),+$AD$1*(W8+U8)) -> 2007.1612 | BK8: =IF(E8="Bundled",$AD$1*V8,$AD$1*V8*0.85) -> 4561.7301 | BL8: =+BB8*V8 -> 5833.3333 | BM8: =+#REF!*V8 -> #REF! | BN8: =+BG8-BM8 -> #REF! | BO8: =+BH8-BI8 -> #REF! | BP8: =+BN8+BO8 -> #REF! | BQ8: =+V8 -> 0.25 | BR8: =+BB8 -> 23333.333 | BS8: =IF(E8="Bundled",BK8-BI8,AO8-BI8) -> 4561.7301 | BT8: =IF(E8="Bundled",+(BD8-#REF!)*V8,(AM8+AN8)-V8*#REF!) -> #REF! | BU8: =+BS8+BT8 -> #REF! | BV8: =+BS8/$BQ8 -> 18246.92 | BW8: =+BT8/$BQ8 -> #REF! | BX8: =+BU8/$BQ8 -> #REF!
A9: L6 | B9: L6-D-30, L6-D-29 | C9: ECSO | D9: Rated | E9: Bundled | F9: Rack | G9: Uncaged | H9: =IF(F9="Rack","No of Racks",(IF(F9="Space","Sq Ft","U Space"))) -> No of Racks | I9: 2 | J9: 0 | K9: =I9-J9 -> 2 | L9: 0 | N9: =(580000)/12 -> 48333.333 | O9: =D9 -> Rated | P9: KVA | Q9: 0 | R9: 0 | S9: =Q9-R9 -> 0 | U9: =IF(S9<=0,0,(IF(O9="Rated",(S9+T9)*$U$1,(S9+T9)))) -> 0 | V9: =IF(O9="Rated",Q9*$U$1,Q9) -> 0 | W9: 0 | X9: =IF((S9*-1)>0, (S9*-1), 0) -> 0 | Y9: =110000/12 -> 9166.6667 | Z9: =E9 -> Bundled | AI9: =AG9-AH9 -> 0 | AL9: =(0)/12 -> 0 | AM9: =N9*L9 -> 0 | AN9: =Y9*X9 -> 0 | AO9: =AD9*AC9*AA9 -> 0 | AP9: =AL9*AJ9 -> 0 | AQ9: =0/12 -> 0 | AR9: =SUBTOTAL(9,AM9:AQ9) -> 0 | AZ9: =IF(F9="Rack",AR9/I9,0)+IF(F9="U Space",AR9*40/I9,0)+IF(F9="Space",AR9*30/I9,0) -> 0 | BA9: =+AR9/V9 -> #DIV/0! | BB9: =+($AM9+$AN9+$AO9-BI9)/$V9 -> #DIV/0! | BC9: =+($AM9+$AN9+$AO9-BJ9)/$V9 -> #DIV/0! | BD9: =+($AM9+$AN9+IF(E9="Bundled",0,V9*0.85*AA9*AC9*30.5*24)-BK9)/$V9 -> #DIV/0! | BF9: =+AM9+AN9+AO9 -> 0 | BG9: =+BF9-BH9 -> #REF! | BH9: =IF(E9="Bundled",MIN(V9*$AD$1*(1+#REF!),BF9),AO9) -> #REF! | BI9: =IF($AD9>0,$AD9*$AA$1*$AC$1*(1+$AF$1*(20/$AC$1)/732),$AD$1*W9) -> 0 | BJ9: =IF($AD9>0,$AD9*$AA$1*$AC$1*(1+$AF$1*(20/$AC$1)/732),+$AD$1*(W9+U9)) -> 0 | BK9: =IF(E9="Bundled",$AD$1*V9,$AD$1*V9*0.85) -> 0 | BL9: =+BB9*V9 -> #DIV/0! | BM9: =+#REF!*V9 -> #REF! | BN9: =+BG9-BM9 -> #REF! | BO9: =+BH9-BI9 -> #REF! | BP9: =+BN9+BO9 -> #REF! | BQ9: =+V9 -> 0 | BR9: =+BB9 -> #DIV/0! | BS9: =IF(E9="Bundled",BK9-BI9,AO9-BI9) -> 0 | BT9: =IF(E9="Bundled",+(BD9-#REF!)*V9,(AM9+AN9)-V9*#REF!) -> #DIV/0! | BU9: =+BS9+BT9 -> #DIV/0! | BV9: =+BS9/$BQ9 -> #DIV/0! | BW9: =+BT9/$BQ9 -> #DIV/0! | BX9: =+BU9/$BQ9 -> #DIV/0!
A10: L5 | B10: Server Hall 5A L5A-01-08 | C10: RACSANN TECHNOLOGIES PVT LTD | D10: Rated | E10: Bundled | F10: U space | G10: Uncaged | H10: =IF(F10="Rack","No of Racks",(IF(F10="Space","Sq Ft","U Space"))) -> U Space | I10: 5 | J10: 5 | K10: =I10-J10 -> 0 | L10: 5 | N10: =(150000/5)/12 -> 2500 | O10: =D10 -> Rated | P10: KVA | Q10: 1.25 | R10: 1.01 | S10: =Q10-R10 -> 0.24 | U10: =IF(S10<=0,0,(IF(O10="Rated",(S10+T10)*$V$1,(S10+T10)))) -> #VALUE! | V10: =IF(O10="Rated",Q10*$V$1,Q10) -> #VALUE! | X10: =IF((S10*-1)>0, (S10*-1), 0) -> 0 | Y10: =105000/12 -> 8750 | Z10: =E10 -> Bundled | AF10: =IF(AE10="No of Seats","No of Seats",(IF(AE10="Space","Sq Ft",""))) | AI10: =AG10-AH10 -> 0 | AM10: =N10*L10 -> 12500 | AN10: =Y10*X10 -> 0 | AO10: =AD10*AC10*AA10 -> 0 | AP10: =AL10*AJ10 -> 0 | AQ10: =(90000)/12 -> 7500 | AR10: =SUBTOTAL(9,AM10:AQ10) -> 20000 | AT10: 121001215 | AZ10: =IF(F10="Rack",AR10/I10,0)+IF(F10="U Space",AR10*40/I10,0)+IF(F10="Space",AR10*30/I10,0) -> 160000 | BA10: =+AR10/V10 -> #VALUE! | BB10: =+($AM10+$AN10+$AO10-BI10)/$V10 -> #VALUE! | BC10: =+($AM10+$AN10+$AO10-BJ10)/$V10 -> #VALUE! | BD10: =+($AM10+$AN10+IF(E10="Bundled",0,V10*0.85*AA10*AC10*30.5*24)-BK10)/$V10 -> #VALUE! | BF10: =+AM10+AN10+AO10 -> 12500 | BG10: =+BF10-BH10 -> #VALUE! | BH10: =IF(E10="Bundled",MIN(V10*$AE$1*(1+#REF!),BF10),AO10) -> #VALUE! | BI10: =IF($AD10>0,$AD10*$AB$1*$AD$1*(1+$AG$1*(20/$AD$1)/732),$AE$1*W10) -> #VALUE! | BJ10: =IF($AD10>0,$AD10*$AB$1*$AD$1*(1+$AG$1*(20/$AD$1)/732),+$AE$1*(W10+U10)) -> #VALUE! | BK10: =IF(E10="Bundled",$AE$1*V10,$AE$1*V10*0.85) -> #VALUE! | BL10: =+BB10*V10 -> #VALUE! | BM10: =+#REF!*V10 -> #REF! | BN10: =+BG10-BM10 -> #VALUE! | BO10: =+BH10-BI10 -> #VALUE! | BP10: =+BN10+BO10 -> #VALUE! | BQ10: =+V10 -> #VALUE! | BR10: =+BB10 -> #VALUE! | BS10: =IF(E10="Bundled",BK10-BI10,AO10-BI10) -> #VALUE! | BT10: =IF(E10="Bundled",+(BD10-#REF!)*V10,(AM10+AN10)-V10*#REF!) -> #VALUE! | BU10: =+BS10+BT10 -> #VALUE! | BV10: =+BS10/$BQ10 -> #VALUE! | BW10: =+BT10/$BQ10 -> #VALUE! | BX10: =+BU10/$BQ10 -> #VALUE!
A11: L4 | B11: Server Hall L4 L4-D-29 | C11: Balaji Teleworks | D11: Rated | E11: Bundled | F11: U space | G11: Uncaged | H11: =IF(F11="Rack","No of Racks",(IF(F11="Space","Sq Ft","U Space"))) -> U Space | I11: 6 | J11: 6 | K11: =I11-J11 -> 0 | L11: 6 | N11: =(230000/6)/12 -> 3194.4444 | O11: =D11 -> Rated | P11: KVA | Q11: =500/900 -> 0.55555556 | R11: 1.11 | S11: =Q11-R11 -> -0.55444444 | U11: =IF(S11<=0,0,(IF(O11="Rated",(S11+T11)*$V$1,(S11+T11)))) -> 0 | V11: =IF(O11="Rated",Q11*$V$1,Q11) -> #VALUE! | X11: =IF((S11*-1)>0, (S11*-1), 0) -> 0.55444444 | Y11: =99000/12 -> 8250 | Z11: =E11 -> Bundled | AI11: =AG11-AH11 -> 0 | AL11: =(0)/12 -> 0 | AM11: =N11*L11 -> 19166.667 | AN11: =Y11*X11 -> 4574.1667 | AO11: =AD11*AC11*AA11 -> 0 | AP11: =AL11*AJ11 -> 0 | AQ11: =0/12 -> 0 | AR11: =SUBTOTAL(9,AM11:AQ11) -> 23740.833 | AZ11: =IF(F11="Rack",AR11/I11,0)+IF(F11="U Space",AR11*40/I11,0)+IF(F11="Space",AR11*30/I11,0) -> 158272.22 | BA11: =+AR11/V11 -> #VALUE! | BB11: =+($AM11+$AN11+$AO11-BI11)/$V11 -> #VALUE! | BC11: =+($AM11+$AN11+$AO11-BJ11)/$V11 -> #VALUE! | BD11: =+($AM11+$AN11+IF(E11="Bundled",0,V11*0.85*AA11*AC11*30.5*24)-BK11)/$V11 -> #VALUE! | BF11: =+AM11+AN11+AO11 -> 23740.833 | BG11: =+BF11-BH11 -> #VALUE! | BH11: =IF(E11="Bundled",MIN(V11*$AE$1*(1+#REF!),BF11),AO11) -> #VALUE! | BI11: =IF($AD11>0,$AD11*$AB$1*$AD$1*(1+$AG$1*(20/$AD$1)/732),$AE$1*W11) -> #VALUE! | BJ11: =IF($AD11>0,$AD11*$AB$1*$AD$1*(1+$AG$1*(20/$AD$1)/732),+$AE$1*(W11+U11)) -> #VALUE! | BK11: =IF(E11="Bundled",$AE$1*V11,$AE$1*V11*0.85) -> #VALUE! | BL11: =+BB11*V11 -> #VALUE! | BM11: =+#REF!*V11 -> #REF! | BN11: =+BG11-BM11 -> #VALUE! | BO11: =+BH11-BI11 -> #VALUE! | BP11: =+BN11+BO11 -> #VALUE! | BQ11: =+V11 -> #VALUE! | BR11: =+BB11 -> #VALUE! | BS11: =IF(E11="Bundled",BK11-BI11,AO11-BI11) -> #VALUE! | BT11: =IF(E11="Bundled",+(BD11-#REF!)*V11,(AM11+AN11)-V11*#REF!) -> #VALUE! | BU11: =+BS11+BT11 -> #VALUE! | BV11: =+BS11/$BQ11 -> #VALUE! | BW11: =+BT11/$BQ11 -> #VALUE! | BX11: =+BU11/$BQ11 -> #VALUE!
A12: L6 | B12: Server Hall L6 L6-E-03 | C12: SAIKRITI TECHSOFT PVT LTD | D12: Rated | E12: Bundled | F12: U space | G12: Uncaged | H12: =IF(F12="Rack","No of Racks",(IF(F12="Space","Sq Ft","U Space"))) -> U Space | I12: 21 | J12: 21 | K12: =I12-J12 -> 0 | L12: 21 | N12: =(350000/21)/12 -> 1388.8889 | O12: =D12 -> Rated | P12: KVA | Q12: 1.5 | R12: 3.38 | S12: =Q12-R12 -> -1.88 | U12: =IF(S12<=0,0,(IF(O12="Rated",(S12+T12)*$V$1,(S12+T12)))) -> 0 | V12: =IF(O12="Rated",Q12*$V$1,Q12) -> #VALUE! | X12: =IF((S12*-1)>0, (S12*-1), 0) -> 1.88 | Y12: =100000/12 -> 8333.3333 | Z12: =E12 -> Bundled | AF12: =IF(AE12="No of Seats","No of Seats",(IF(AE12="Space","Sq Ft",""))) | AI12: =AG12-AH12 -> 0 | AM12: =N12*L12 -> 29166.667 | AN12: =Y12*X12 -> 15666.667 | AO12: =AD12*AC12*AA12 -> 0 | AP12: =AL12*AJ12 -> 0 | AQ12: 0 | AR12: =SUBTOTAL(9,AM12:AQ12) -> 44833.333 | AZ12: =IF(F12="Rack",AR12/I12,0)+IF(F12="U Space",AR12*40/I12,0)+IF(F12="Space",AR12*30/I12,0) -> 85396.825 | BA12: =+AR12/V12 -> #VALUE! | BB12: =+($AM12+$AN12+$AO12-BI12)/$V12 -> #VALUE! | BC12: =+($AM12+$AN12+$AO12-BJ12)/$V12 -> #VALUE! | BD12: =+($AM12+$AN12+IF(E12="Bundled",0,V12*0.85*AA12*AC12*30.5*24)-BK12)/$V12 -> #VALUE! | BF12: =+AM12+AN12+AO12 -> 44833.333 | BG12: =+BF12-BH12 -> #VALUE! | BH12: =IF(E12="Bundled",MIN(V12*$AE$1*(1+#REF!),BF12),AO12) -> #VALUE! | BI12: =IF($AD12>0,$AD12*$AB$1*$AD$1*(1+$AG$1*(20/$AD$1)/732),$AE$1*W12) -> #VALUE! | BJ12: =IF($AD12>0,$AD12*$AB$1*$AD$1*(1+$AG$1*(20/$AD$1)/732),+$AE$1*(W12+U12)) -> #VALUE! | BK12: =IF(E12="Bundled",$AE$1*V12,$AE$1*V12*0.85) -> #VALUE! | BL12: =+BB12*V12 -> #VALUE! | BM12: =+#REF!*V12 -> #REF! | BN12: =+BG12-BM12 -> #VALUE! | BO12: =+BH12-BI12 -> #VALUE! | BP12: =+BN12+BO12 -> #VALUE! | BQ12: =+V12 -> #VALUE! | BR12: =+BB12 -> #VALUE! | BS12: =IF(E12="Bundled",BK12-BI12,AO12-BI12) -> #VALUE! | BT12: =IF(E12="Bundled",+(BD12-#REF!)*V12,(AM12+AN12)-V12*#REF!) -> #VALUE! | BU12: =+BS12+BT12 -> #VALUE! | BV12: =+BS12/$BQ12 -> #VALUE! | BW12: =+BT12/$BQ12 -> #VALUE! | BX12: =+BU12/$BQ12 -> #VALUE!
A13: L6 | B13: Server Hall L6 L6-F-25 | C13: ACME DIGINET CORPORATION PVT LTD | D13: Rated | E13: Bundled | F13: U space | G13: Uncaged | H13: =IF(F13="Rack","No of Racks",(IF(F13="Space","Sq Ft","U Space"))) -> U Space | I13: 6 | J13: 6 | K13: =I13-J13 -> 0 | L13: 6 | N13: =29000/12 -> 2416.6667 | O13: =D13 -> Rated | P13: KVA | Q13: 1.5 | R13: 2.67 | S13: =Q13-R13 -> -1.17 | U13: =IF(S13<=0,0,(IF(O13="Rated",(S13+T13)*$V$1,(S13+T13)))) -> 0 | V13: =IF(O13="Rated",Q13*$V$1,Q13) -> #VALUE! | X13: =IF((S13*-1)>0, (S13*-1), 0) -> 1.17 | Z13: =E13 -> Bundled | AF13: =IF(AE13="No of Seats","No of Seats",(IF(AE13="Space","Sq Ft",""))) | AI13: =AG13-AH13 -> 0 | AM13: =N13*L13 -> 14500 | AN13: =Y13*X13 -> 0 | AO13: =AD13*AC13*AA13 -> 0 | AP13: =AL13*AJ13 -> 0 | AQ13: 0 | AR13: =SUBTOTAL(9,AM13:AQ13) -> 14500 | AZ13: =IF(F13="Rack",AR13/I13,0)+IF(F13="U Space",AR13*40/I13,0)+IF(F13="Space",AR13*30/I13,0) -> 96666.667 | BA13: =+AR13/V13 -> #VALUE! | BB13: =+($AM13+$AN13+$AO13-BI13)/$V13 -> #VALUE! | BC13: =+($AM13+$AN13+$AO13-BJ13)/$V13 -> #VALUE! | BD13: =+($AM13+$AN13+IF(E13="Bundled",0,V13*0.85*AA13*AC13*30.5*24)-BK13)/$V13 -> #VALUE! | BF13: =+AM13+AN13+AO13 -> 14500 | BG13: =+BF13-BH13 -> #VALUE! | BH13: =IF(E13="Bundled",MIN(V13*$AE$1*(1+#REF!),BF13),AO13) -> #VALUE! | BI13: =IF($AD13>0,$AD13*$AB$1*$AD$1*(1+$AG$1*(20/$AD$1)/732),$AE$1*W13) -> #VALUE! | BJ13: =IF($AD13>0,$AD13*$AB$1*$AD$1*(1+$AG$1*(20/$AD$1)/732),+$AE$1*(W13+U13)) -> #VALUE! | BK13: =IF(E13="Bundled",$AE$1*V13,$AE$1*V13*0.85) -> #VALUE! | BL13: =+BB13*V13 -> #VALUE! | BM13: =+#REF!*V13 -> #REF! | BN13: =+BG13-BM13 -> #VALUE! | BO13: =+BH13-BI13 -> #VALUE! | BP13: =+BN13+BO13 -> #VALUE! | BQ13: =+V13 -> #VALUE! | BR13: =+BB13 -> #VALUE! | BS13: =IF(E13="Bundled",BK13-BI13,AO13-BI13) -> #VALUE! | BT13: =IF(E13="Bundled",+(BD13-#REF!)*V13,(AM13+AN13)-V13*#REF!) -> #VALUE! | BU13: =+BS13+BT13 -> #VALUE! | BV13: =+BS13/$BQ13 -> #VALUE! | BW13: =+BT13/$BQ13 -> #VALUE! | BX13: =+BU13/$BQ13 -> #VALUE!
A14: L4 | B14: Server Hall L4 L4-D-29 | C14: NAS INTERNET SERVICES PVT LTD | D14: Rated | E14: Bundled | F14: U space | G14: Uncaged | H14: =IF(F14="Rack","No of Racks",(IF(F14="Space","Sq Ft","U Space"))) -> U Space | I14: 3 | J14: 3 | K14: =I14-J14 -> 0 | L14: 3 | N14: =(35000)/12 -> 2916.6667 | O14: =D14 -> Rated | P14: KVA | Q14: 0.75 | R14: 0.61 | S14: =Q14-R14 -> 0.14 | U14: =IF(S14<=0,0,(IF(O14="Rated",(S14+T14)*$V$1,(S14+T14)))) -> #VALUE! | V14: =IF(O14="Rated",Q14*$V$1,Q14) -> #VALUE! | X14: =IF((S14*-1)>0, (S14*-1), 0) -> 0 | Y14: =90000/12 -> 7500 | Z14: =E14 -> Bundled | AI14: =AG14-AH14 -> 0 | AL14: =(0)/12 -> 0 | AM14: =N14*L14 -> 8750 | AN14: =Y14*X14 -> 0 | AO14: =AD14*AC14*AA14 -> 0 | AP14: =AL14*AJ14 -> 0 | AQ14: =0/12 -> 0 | AR14: =SUBTOTAL(9,AM14:AQ14) -> 8750 | AZ14: =IF(F14="Rack",AR14/I14,0)+IF(F14="U Space",AR14*40/I14,0)+IF(F14="Space",AR14*30/I14,0) -> 116666.67 | BA14: =+AR14/V14 -> #VALUE! | BB14: =+($AM14+$AN14+$AO14-BI14)/$V14 -> #VALUE! | BC14: =+($AM14+$AN14+$AO14-BJ14)/$V14 -> #VALUE! | BD14: =+($AM14+$AN14+IF(E14="Bundled",0,V14*0.85*AA14*AC14*30.5*24)-BK14)/$V14 -> #VALUE! | BF14: =+AM14+AN14+AO14 -> 8750 | BG14: =+BF14-BH14 -> #VALUE! | BH14: =IF(E14="Bundled",MIN(V14*$AE$1*(1+#REF!),BF14),AO14) -> #VALUE! | BI14: =IF($AD14>0,$AD14*$AB$1*$AD$1*(1+$AG$1*(20/$AD$1)/732),$AE$1*W14) -> #VALUE! | BJ14: =IF($AD14>0,$AD14*$AB$1*$AD$1*(1+$AG$1*(20/$AD$1)/732),+$AE$1*(W14+U14)) -> #VALUE! | BK14: =IF(E14="Bundled",$AE$1*V14,$AE$1*V14*0.85) -> #VALUE! | BL14: =+BB14*V14 -> #VALUE! | BM14: =+#REF!*V14 -> #REF! | BN14: =+BG14-BM14 -> #VALUE! | BO14: =+BH14-BI14 -> #VALUE! | BP14: =+BN14+BO14 -> #VALUE! | BQ14: =+V14 -> #VALUE! | BR14: =+BB14 -> #VALUE! | BS14: =IF(E14="Bundled",BK14-BI14,AO14-BI14) -> #VALUE! | BT14: =IF(E14="Bundled",+(BD14-#REF!)*V14,(AM14+AN14)-V14*#REF!) -> #VALUE! | BU14: =+BS14+BT14 -> #VALUE! | BV14: =+BS14/$BQ14 -> #VALUE! | BW14: =+BT14/$BQ14 -> #VALUE! | BX14: =+BU14/$BQ14 -> #VALUE!
A15: L5 | B15: Server Hall 5A L5A-04-11 | C15: SIMPLE TELECOM PVT LTD | D15: Rated | E15: Bundled | F15: U space | G15: Uncaged | H15: =IF(F15="Rack","No of Racks",(IF(F15="Space","Sq Ft","U Space"))) -> U Space | I15: 11 | J15: 11 | K15: =I15-J15 -> 0 | L15: 11 | N15: =(120000)/11/12 -> 909.09091 | O15: =D15 -> Rated | P15: KVA | Q15: 1 | R15: 2.1 | S15: =Q15-R15 -> -1.1 | U15: =IF(S15<=0,0,(IF(O15="Rated",(S15+T15)*$V$1,(S15+T15)))) -> 0 | V15: =IF(O15="Rated",Q15*$V$1,Q15) -> #VALUE! | X15: =IF((S15*-1)>0, (S15*-1), 0) -> 1.1 | Z15: =E15 -> Bundled | BK15: =IF(E15="Bundled",$AE$1*V15,$AE$1*V15*0.85) -> #VALUE! | BQ15: =+V15 -> #VALUE!
A16: L7 | B16: L7-E-05 | C16: SWAKSH INFRATECH | D16: Rated | E16: Bundled | F16: Rack | G16: Uncaged | H16: =IF(F16="Rack","No of Racks",(IF(F16="Space","Sq Ft","U Space"))) -> No of Racks | I16: 1 | J16: 1 | K16: =I16-J16 -> 0 | L16: 1 | N16: =(450000)/12 -> 37500 | O16: =D16 -> Rated | P16: KVA | Q16: 3 | R16: 0 | S16: =Q16-R16 -> 3 | U16: =IF(S16<=0,0,(IF(O16="Rated",(S16+T16)*'Noida-01'!#REF!,(S16+T16)))) -> #REF! | V16: =IF(O16="Rated",Q16*'Noida-01'!#REF!,Q16) -> #REF! | W16: =AD16/31/24 -> 0 | X16: =IF((S16*-1)>0, (S16*-1), 0) -> 0 | Z16: =E16 -> Bundled | AI16: =AG16-AH16 -> 0 | AL16: =(0)/12 -> 0 | AM16: =N16*L16 -> 37500 | AN16: =Y16*X16 -> 0 | AO16: =AD16*AC16*AA16 -> 0 | AP16: =AL16*AJ16 -> 0 | AQ16: =0/12 -> 0 | AR16: =SUBTOTAL(9,AM16:AQ16) -> 37500 | AZ16: =IF(F16="Rack",AR16/I16,0)+IF(F16="U Space",AR16*40/I16,0)+IF(F16="Space",AR16*30/I16,0) -> 37500 | BA16: =+AR16/V16 -> #REF! | BB16: =+($AM16+$AN16+$AO16-BI16)/$V16 -> #REF! | BC16: =+($AM16+$AN16+$AO16-BJ16)/$V16 -> #REF! | BD16: =+($AM16+$AN16+IF(E16="Bundled",0,V16*0.85*AA16*AC16*30.5*24)-BK16)/$V16 -> #REF! | BF16: =+AM16+AN16+AO16 -> 37500 | BG16: =+BF16-BH16 -> #REF! | BH16: =IF(E16="Bundled",MIN(V16*'Noida-01'!#REF!*(1+#REF!),BF16),AO16) -> #REF! | BI16: =IF($AD16>0,$AD16*'Noida-01'!#REF!*'Noida-01'!#REF!*(1+'Noida-01'!#REF!*(20/'Noida-01'!#REF!)/732),'Noida-01'!#REF!*W16) -> #REF! | BJ16: =IF($AD16>0,$AD16*'Noida-01'!#REF!*'Noida-01'!#REF!*(1+'Noida-01'!#REF!*(20/'Noida-01'!#REF!)/732),+'Noida-01'!#REF!*(W16+U16)) -> #REF! | BK16: =IF(E16="Bundled",'Noida-01'!#REF!*V16,'Noida-01'!#REF!*V16*0.85) -> #REF! | BL16: =+BB16*V16 -> #REF! | BM16: =+#REF!*V16 -> #REF! | BN16: =+BG16-BM16 -> #REF! | BO16: =+BH16-BI16 -> #REF! | BP16: =+BN16+BO16 -> #REF! | BQ16: =+V16 -> #REF! | BR16: =+BB16 -> #REF! | BS16: =IF(E16="Bundled",BK16-BI16,AO16-BI16) -> #REF! | BT16: =IF(E16="Bundled",+(BD16-#REF!)*V16,(AM16+AN16)-V16*#REF!) -> #REF! | BU16: =+BS16+BT16 -> #REF! | BV16: =+BS16/$BQ16 -> #REF! | BW16: =+BT16/$BQ16 -> #REF! | BX16: =+BU16/$BQ16 -> #REF!
A17: L5 | B17: L5A-02-02, L5A-02-03, L5A-02-04, L5A-02-05, L5A-02-06 & L5A-02-10 | C17: L&T (RVNL) | D17: Rated | E17: Bundled | F17: Rack | G17: Uncaged | H17: =IF(F17="Rack","No of Racks",(IF(F17="Space","Sq Ft","U Space"))) -> No of Racks | I17: 6 | J17: 6 | K17: =I17-J17 -> 0 | L17: 6 | N17: =((3601628+672384)/6)/12 -> 59361.278 | O17: =D17 -> Rated | P17: KVA | Q17: 84.65 | R17: 84.65 | S17: =Q17-R17 -> 0 | U17: =IF(S17<=0,0,(IF(O17="Rated",(S17+T17)*'Noida-01'!#REF!,(S17+T17)))) -> 0 | V17: =IF(O17="Rated",Q17*'Noida-01'!#REF!,Q17) -> #REF! | W17: 14.66 | X17: =IF((S17*-1)>0, (S17*-1), 0) -> 0 | Y17: =92700/12 -> 7725 | Z17: =E17 -> Bundled | AF17: =IF(AE17="No of Seats","No of Seats",(IF(AE17="Space","Sq Ft",""))) | AI17: =AG17-AH17 -> 0 | AM17: =N17*L17 -> 356167.67 | AN17: =Y17*X17 -> 0 | AO17: =AD17*AC17*AA17 -> 0 | AP17: =AL17*AJ17 -> 0 | AR17: =SUBTOTAL(9,AM17:AQ17) -> 356167.67 | AT17: Renewal | AU17: 43922 | AV17: 1 | AW17: 44286 | AZ17: =IF(F17="Rack",AR17/I17,0)+IF(F17="U Space",AR17*40/I17,0)+IF(F17="Space",AR17*30/I17,0) -> 59361.278 | BA17: =+AR17/V17 -> #REF! | BB17: =+($AM17+$AN17+$AO17-BI17)/$V17 -> #REF! | BC17: =+($AM17+$AN17+$AO17-BJ17)/$V17 -> #REF! | BD17: =+($AM17+$AN17+IF(E17="Bundled",0,V17*0.85*AA17*AC17*30.5*24)-BK17)/$V17 -> #REF! | BF17: =+AM17+AN17+AO17 -> 356167.67 | BG17: =+BF17-BH17 -> #REF! | BH17: =IF(E17="Bundled",MIN(V17*'Noida-01'!#REF!*(1+#REF!),BF17),AO17) -> #REF! | BI17: =IF($AD17>0,$AD17*'Noida-01'!#REF!*'Noida-01'!#REF!*(1+'Noida-01'!#REF!*(20/'Noida-01'!#REF!)/732),'Noida-01'!#REF!*W17) -> #REF! | BJ17: =IF($AD17>0,$AD17*'Noida-01'!#REF!*'Noida-01'!#REF!*(1+'Noida-01'!#REF!*(20/'Noida-01'!#REF!)/732),+'Noida-01'!#REF!*(W17+U17)) -> #REF! | BK17: =IF(E17="Bundled",'Noida-01'!#REF!*V17,'Noida-01'!#REF!*V17*0.85) -> #REF! | BL17: =+BB17*V17 -> #REF! | BM17: =+#REF!*V17 -> #REF! | BN17: =+BG17-BM17 -> #REF! | BO17: =+BH17-BI17 -> #REF! | BP17: =+BN17+BO17 -> #REF! | BQ17: =+V17 -> #REF! | BR17: =+BB17 -> #REF! | BS17: =IF(E17="Bundled",BK17-BI17,AO17-BI17) -> #REF! | BT17: =IF(E17="Bundled",+(BD17-#REF!)*V17,(AM17+AN17)-V17*#REF!) -> #REF! | BU17: =+BS17+BT17 -> #REF! | BV17: =+BS17/$BQ17 -> #REF! | BW17: =+BT17/$BQ17 -> #REF! | BX17: =+BU17/$BQ17 -> #REF!
A18: L6 | B18: L6-B-33 | C18: DEHRADUN E NET SOLUTIONS (P) LTD. | D18: Rated | E18: Bundled | F18: Rack | G18: Uncaged | H18: =IF(F18="Rack","No of Racks",(IF(F18="Space","Sq Ft","U Space"))) -> No of Racks | I18: 1 | J18: 1 | K18: =I18-J18 -> 0 | L18: 1 | N18: =(442500)/12 -> 36875 | O18: =D18 -> Rated | P18: KVA | Q18: 3.5 | R18: 3.33 | S18: =Q18-R18 -> 0.17 | U18: =IF(S18<=0,0,(IF(O18="Rated",(S18+T18)*'Noida-01'!#REF!,(S18+T18)))) -> #REF! | V18: =IF(O18="Rated",Q18*'Noida-01'!#REF!,Q18) -> #REF! | W18: 2.41 | X18: =IF((S18*-1)>0, (S18*-1), 0) -> 0 | Y18: =90000/12 -> 7500 | Z18: =E18 -> Bundled | AF18: =IF(AE18="No of Seats","No of Seats",(IF(AE18="Space","Sq Ft",""))) | AI18: =AG18-AH18 -> 0 | AM18: =N18*L18 -> 36875 | AN18: =Y18*X18 -> 0 | AO18: =AD18*AC18*AA18 -> 0 | AP18: =AL18*AJ18 -> 0 | AR18: =SUBTOTAL(9,AM18:AQ18) -> 36875 | AZ18: =IF(F18="Rack",AR18/I18,0)+IF(F18="U Space",AR18*40/I18,0)+IF(F18="Space",AR18*30/I18,0) -> 36875 | BA18: =+AR18/V18 -> #REF! | BB18: =+($AM18+$AN18+$AO18-BI18)/$V18 -> #REF! | BC18: =+($AM18+$AN18+$AO18-BJ18)/$V18 -> #REF! | BD18: =+($AM18+$AN18+IF(E18="Bundled",0,V18*0.85*AA18*AC18*30.5*24)-BK18)/$V18 -> #REF! | BF18: =+AM18+AN18+AO18 -> 36875 | BG18: =+BF18-BH18 -> #REF! | BH18: =IF(E18="Bundled",MIN(V18*'Noida-01'!#REF!*(1+#REF!),BF18),AO18) -> #REF! | BI18: =IF($AD18>0,$AD18*'Noida-01'!#REF!*'Noida-01'!#REF!*(1+'Noida-01'!#REF!*(20/'Noida-01'!#REF!)/732),'Noida-01'!#REF!*W18) -> #REF! | BJ18: =IF($AD18>0,$AD18*'Noida-01'!#REF!*'Noida-01'!#REF!*(1+'Noida-01'!#REF!*(20/'Noida-01'!#REF!)/732),+'Noida-01'!#REF!*(W18+U18)) -> #REF! | BK18: =IF(E18="Bundled",'Noida-01'!#REF!*V18,'Noida-01'!#REF!*V18*0.85) -> #REF! | BL18: =+BB18*V18 -> #REF! | BM18: =+#REF!*V18 -> #REF! | BN18: =+BG18-BM18 -> #REF! | BO18: =+BH18-BI18 -> #REF! | BP18: =+BN18+BO18 -> #REF! | BQ18: =+V18 -> #REF! | BR18: =+BB18 -> #REF! | BS18: =IF(E18="Bundled",BK18-BI18,AO18-BI18) -> #REF! | BT18: =IF(E18="Bundled",+(BD18-#REF!)*V18,(AM18+AN18)-V18*#REF!) -> #REF! | BU18: =+BS18+BT18 -> #REF! | BV18: =+BS18/$BQ18 -> #REF! | BW18: =+BT18/$BQ18 -> #REF! | BX18: =+BU18/$BQ18 -> #REF!
A19: L6 | B19: L6-D-03 | C19: EMINENCE SOFTECH PVT LTD | D19: Subscribed | E19: Metered | F19: Rack | G19: Uncaged | H19: =IF(F19="Rack","No of Racks",(IF(F19="Space","Sq Ft","U Space"))) -> No of Racks | I19: 1 | J19: 1 | K19: =I19-J19 -> 0 | L19: 1 | N19: =(270000)/12 -> 22500 | O19: =D19 -> Subscribed | P19: KW | Q19: 3 | R19: =W19 -> 0.037634409 | S19: =Q19-R19 -> 2.9623656 | U19: =IF(S19<=0,0,(IF(O19="Rated",(S19+T19)*'Noida-01'!#REF!,(S19+T19)))) -> 2.9623656 | V19: =IF(O19="Rated",Q19*'Noida-01'!#REF!,Q19) -> 3 | W19: =AD19/31/24 -> 0.037634409 | X19: =IF((S19*-1)>0, (S19*-1), 0) -> 0 | Y19: =95000/12 -> 7916.6667 | Z19: =E19 -> Metered | AA19: 1 | AB19: Fixed | AC19: 17 | AD19: 28 | AI19: =AG19-AH19 -> 0 | AL19: =(0)/12 -> 0 | AM19: =N19*L19 -> 22500 | AN19: =Y19*X19 -> 0 | AO19: =AD19*AC19*AA19 -> 476 | AP19: =AL19*AJ19 -> 0 | AQ19: =0/12 -> 0 | AR19: =SUBTOTAL(9,AM19:AQ19) -> 22976 | AZ19: =IF(F19="Rack",AR19/I19,0)+IF(F19="U Space",AR19*40/I19,0)+IF(F19="Space",AR19*30/I19,0) -> 22976 | BA19: =+AR19/V19 -> 7658.6667 | BB19: =+($AM19+$AN19+$AO19-BI19)/$V19 -> #REF! | BC19: =+($AM19+$AN19+$AO19-BJ19)/$V19 -> #REF! | BD19: =+($AM19+$AN19+IF(E19="Bundled",0,V19*0.85*AA19*AC19*30.5*24)-BK19)/$V19 -> #REF! | BF19: =+AM19+AN19+AO19 -> 22976 | BG19: =+BF19-BH19 -> 22500 | BH19: =IF(E19="Bundled",MIN(V19*'Noida-01'!#REF!*(1+#REF!),BF19),AO19) -> 476 | BI19: =IF($AD19>0,$AD19*'Noida-01'!#REF!*'Noida-01'!#REF!*(1+'Noida-01'!#REF!*(20/'Noida-01'!#REF!)/732),'Noida-01'!#REF!*W19) -> #REF! | BJ19: =IF($AD19>0,$AD19*'Noida-01'!#REF!*'Noida-01'!#REF!*(1+'Noida-01'!#REF!*(20/'Noida-01'!#REF!)/732),+'Noida-01'!#REF!*(W19+U19)) -> #REF! | BK19: =IF(E19="Bundled",'Noida-01'!#REF!*V19,'Noida-01'!#REF!*V19*0.85) -> #REF! | BL19: =+BB19*V19 -> #REF! | BM19: =+#REF!*V19 -> #REF! | BN19: =+BG19-BM19 -> #REF! | BO19: =+BH19-BI19 -> #REF! | BP19: =+BN19+BO19 -> #REF! | BQ19: =+V19 -> 3 | BR19: =+BB19 -> #REF! | BS19: =IF(E19="Bundled",BK19-BI19,AO19-BI19) -> #REF! | BT19: =IF(E19="Bundled",+(BD19-#REF!)*V19,(AM19+AN19)-V19*#REF!) -> #REF! | BU19: =+BS19+BT19 -> #REF! | BV19: =+BS19/$BQ19 -> #REF! | BW19: =+BT19/$BQ19 -> #REF! | BX19: =+BU19/$BQ19 -> #REF!
A20: L7 | B20: L7-F-26 to L7-F-29 | C20: NEXTRA ONLINE SERVICES PRIVATE LIMITED | D20: Subscribed | E20: Metered | F20: Rack | G20: Uncaged | H20: =IF(F20="Rack","No of Racks",(IF(F20="Space","Sq Ft","U Space"))) -> No of Racks | I20: 4 | J20: 4 | K20: =I20-J20 -> 0 | L20: 4 | N20: =(31100) -> 31100 | O20: =D20 -> Subscribed | P20: KW | Q20: 16.6 | R20: =W20 -> 6.8954167 | S20: =Q20-R20 -> 9.7045833 | U20: =IF(S20<=0,0,(IF(O20="Rated",(S20+T20)*'Noida-01'!#REF!,(S20+T20)))) -> 9.7045833 | V20: =IF(O20="Rated",Q20*'Noida-01'!#REF!,Q20) -> 16.6 | W20: =AD20/30/24 -> 6.8954167 | X20: =IF((S20*-1)>0, (S20*-1), 0) -> 0 | Y20: =0/12 -> 0 | Z20: =E20 -> Metered | AA20: 1 | AB20: Fixed | AC20: 0 | AD20: 4964.7 | AI20: =AG20-AH20 -> 0 | AL20: =(0)/12 -> 0 | AM20: =N20*L20 -> 124400 | AN20: =Y20*X20 -> 0 | AO20: =AD20*AC20*AA20 -> 0 | AP20: =AL20*AJ20 -> 0 | AQ20: =0/12 -> 0 | AR20: =SUBTOTAL(9,AM20:AQ20) -> 124400 | AZ20: =IF(F20="Rack",AR20/I20,0)+IF(F20="U Space",AR20*40/I20,0)+IF(F20="Space",AR20*30/I20,0) -> 31100 | BA20: =+AR20/V20 -> 7493.9759 | BB20: =+($AM20+$AN20+$AO20-BI20)/$V20 -> #REF! | BC20: =+($AM20+$AN20+$AO20-BJ20)/$V20 -> #REF! | BD20: =+($AM20+$AN20+IF(E20="Bundled",0,V20*0.85*AA20*AC20*30.5*24)-BK20)/$V20 -> #REF! | BF20: =+AM20+AN20+AO20 -> 124400 | BG20: =+BF20-BH20 -> 124400 | BH20: =IF(E20="Bundled",MIN(V20*'Noida-01'!#REF!*(1+#REF!),BF20),AO20) -> 0 | BI20: =IF($AD20>0,$AD20*'Noida-01'!#REF!*'Noida-01'!#REF!*(1+'Noida-01'!#REF!*(20/'Noida-01'!#REF!)/732),'Noida-01'!#REF!*W20) -> #REF! | BJ20: =IF($AD20>0,$AD20*'Noida-01'!#REF!*'Noida-01'!#REF!*(1+'Noida-01'!#REF!*(20/'Noida-01'!#REF!)/732),+'Noida-01'!#REF!*(W20+U20)) -> #REF! | BK20: =IF(E20="Bundled",'Noida-01'!#REF!*V20,'Noida-01'!#REF!*V20*0.85) -> #REF! | BL20: =+BB20*V20 -> #REF! | BM20: =+#REF!*V20 -> #REF! | BN20: =+BG20-BM20 -> #REF! | BO20: =+BH20-BI20 -> #REF! | BP20: =+BN20+BO20 -> #REF! | BQ20: =+V20 -> 16.6 | BR20: =+BB20 -> #REF! | BS20: =IF(E20="Bundled",BK20-BI20,AO20-BI20) -> #REF! | BT20: =IF(E20="Bundled",+(BD20-#REF!)*V20,(AM20+AN20)-V20*#REF!) -> #REF! | BU20: =+BS20+BT20 -> #REF! | BV20: =+BS20/$BQ20 -> #REF! | BW20: =+BT20/$BQ20 -> #REF! | BX20: =+BU20/$BQ20 -> #REF!
A21: L5 | B21: Server Hall 5A L5A-04-11 | C21: NESECURE TELECOM | D21: Rated | E21: Bundled | F21: U space | G21: Uncaged | H21: =IF(F21="Rack","No of Racks",(IF(F21="Space","Sq Ft","U Space"))) -> U Space | I21: 6 | J21: 6 | K21: =I21-J21 -> 0 | L21: 6 | N21: =120000/12/6 -> 1666.6667 | O21: =D21 -> Rated | P21: KVA | Q21: 1 | R21: 0.05 | S21: =Q21-R21 -> 0.95 | U21: =IF(S21<=0,0,(IF(O21="Rated",(S21+T21)*$S$20,(S21+T21)))) -> 9.2193542 | V21: =IF(O21="Rated",Q21*$S$20,Q21) -> 9.7045833 | X21: =IF((S21*-1)>0, (S21*-1), 0) -> 0 | Y21: =110000/12 -> 9166.6667 | Z21: =E21 -> Bundled | AF21: =IF(AE21="No of Seats","No of Seats",(IF(AE21="Space","Sq Ft",""))) | AI21: =AG21-AH21 -> 0 | AM21: =N21*L21 -> 10000 | AN21: =Y21*X21 -> 0 | AO21: =AD21*AC21*AA21 -> 0 | AP21: =AL21*AJ21 -> 0 | AQ21: 0 | AR21: =SUBTOTAL(9,AM21:AQ21) -> 10000 | AZ21: =IF(F21="Rack",AR21/I21,0)+IF(F21="U Space",AR21*40/I21,0)+IF(F21="Space",AR21*30/I21,0) -> 66666.667 | BA21: =+AR21/V21 -> 1030.4409 | BB21: =+($AK21+$AL21+$AM21-BI21)/$T21 -> #VALUE! | BC21: =+($AK21+$AL21+$AM21-BJ21)/$T21 -> #VALUE! | BD21: =+($AK21+$AL21+IF(E21="Bundled",0,V21*0.85*AA21*AC21*30.5*24)-BK21)/$T21 -> #VALUE! | BF21: =+AM21+AN21+AO21 -> 10000 | BG21: =+BF21-BH21 -> #VALUE! | BH21: =IF(E21="Bundled",MIN(V21*$AB$20*(1+$K$2),BF21),AO21) -> #VALUE! | BI21: =IF($AB21>0,$AB21*$Y$20*$AA$20*(1+$AD$20*(20/$AA$20)/732),$AB$20*W21) -> #VALUE! | BJ21: =IF($AB21>0,$AB21*$Y$20*$AA$20*(1+$AD$20*(20/$AA$20)/732),+$AB$20*(W21+U21)) -> #VALUE! | BK21: =IF(E21="Bundled",$AB$20*V21,$AB$20*V21*0.85) -> #VALUE! | BL21: =+BB21*V21 -> #VALUE! | BM21: =+$J$2*V21 -> 0 | BN21: =+BG21-BM21 -> #VALUE! | BO21: =+BH21-BI21 -> #VALUE! | BP21: =+BN21+BO21 -> #VALUE! | BQ21: =+V21 -> 9.7045833 | BR21: =+BB21 -> #VALUE! | BS21: =IF(E21="Bundled",BK21-BI21,AO21-BI21) -> #VALUE! | BT21: =IF(E21="Bundled",+(BD21-$J$2)*V21,(AM21+AN21)-V21*$J$2) -> #VALUE! | BU21: =+BS21+BT21 -> #VALUE! | BV21: =+BS21/$BO21 -> #VALUE! | BW21: =+BT21/$BO21 -> #VALUE! | BX21: =+BU21/$BO21 -> #VALUE!
A22: L4 | B22: L4-E-27 & L4-E-28 | C22: CLOUDFLARE INC | D22: Subscribed | E22: Bundled | F22: Rack | G22: Uncaged | H22: =IF(F22="Rack","No of Racks",(IF(F22="Space","Sq Ft","U Space"))) -> No of Racks | I22: 2 | J22: 2 | K22: =I22-J22 -> 0 | L22: 2 | N22: 1840 | O22: =D22 -> Subscribed | P22: KVA | Q22: 14.36 | R22: =W22/0.9 -> 8.0506327 | S22: =Q22-R22 -> 6.3093673 | U22: =IF(S22<=0,0,(IF(O22="Rated",(S22+T22)*$V$1,(S22+T22)))) -> 6.3093673 | V22: =IF(O22="Rated",Q22*$V$1,Q22) -> 14.36 | W22: =AD22/30/24 -> 7.2455694 | X22: =IF((S22*-1)>0, (S22*-1), 0) -> 0 | Y22: 250 | Z22: =E22 -> Bundled | AA22: 1 | AB22: Fixed | AC22: 0 | AD22: 5216.81 | AI22: =AG22-AH22 -> 0 | AM22: =N22*L22 -> 3680 | AN22: =Y22*X22 -> 0 | AO22: =AD22*AC22*AA22 -> 0 | AP22: =AL22*AJ22 -> 0 | AQ22: 0 | AR22: =SUBTOTAL(9,AM22:AQ22) -> 3680 | AT22: 121000084 | AZ22: =IF(F22="Rack",AR22/I22,0)+IF(F22="U Space",AR22*40/I22,0)+IF(F22="Space",AR22*30/I22,0) -> 1840 | BA22: =+AR22/V22 -> 256.26741 | BB22: =+($AN22+$AO22+$AP22-BI22)/$W22 -> #VALUE! | BC22: =+($AN22+$AO22+$AP22-BJ22)/$W22 -> #VALUE! | BD22: =+($AN22+$AO22+IF(E22="Bundled",0,V22*0.85*AA22*AC22*30.5*24)-BK22)/$W22 -> #VALUE! | BF22: =+AM22+AN22+AO22 -> 3680 | BG22: =+BF22-BH22 -> #VALUE! | BH22: =IF(E22="Bundled",MIN(V22*$AE$1*(1+#REF!),BF22),AO22) -> #VALUE! | BI22: =IF($AE22>0,$AE22*$AB$1*$AD$1*(1+$AG$1*(20/$AD$1)/732),$AE$1*W22) -> #VALUE! | BJ22: =IF($AE22>0,$AE22*$AB$1*$AD$1*(1+$AG$1*(20/$AD$1)/732),+$AE$1*(W22+U22)) -> #VALUE! | BK22: =IF(E22="Bundled",$AE$1*V22,$AE$1*V22*0.85) -> #VALUE! | BL22: =+BB22*V22 -> #VALUE! | BM22: =+#REF!*V22 -> #REF! | BN22: =+BG22-BM22 -> #VALUE! | BO22: =+BH22-BI22 -> #VALUE! | BP22: =+BN22+BO22 -> #VALUE! | BQ22: =+V22 -> 14.36 | BR22: =+BB22 -> #VALUE! | BS22: =IF(E22="Bundled",BK22-BI22,AO22-BI22) -> #VALUE! | BT22: =IF(E22="Bundled",+(BD22-#REF!)*V22,(AM22+AN22)-V22*#REF!) -> #VALUE! | BU22: =+BS22+BT22 -> #VALUE! | BV22: =+BS22/$BR22 -> #VALUE! | BW22: =+BT22/$BR22 -> #VALUE! | BX22: =+BU22/$BR22 -> #VALUE!
A23: L6 | B23: L6-D-01, L6-D-02 | C23: Cloudflare | D23: Subscribed | E23: Bundled | F23: Rack | G23: Uncaged | H23: =IF(F23="Rack","No of Racks",(IF(F23="Space","Sq Ft","U Space"))) -> No of Racks | I23: 2 | J23: 2 | K23: =I23-J23 -> 0 | L23: 2 | N23: 1840 | O23: =D23 -> Subscribed | P23: KW | Q23: 13 | R23: =W23 -> 0 | S23: =Q23-R23 -> 13 | U23: =IF(S23<=0,0,(IF(O23="Rated",(S23+T23)*$V$1,(S23+T23)))) -> 13 | V23: =IF(O23="Rated",Q23*$V$1,Q23) -> 13 | W23: =AD23/31/24 -> 0 | X23: =IF((S23*-1)>0, (S23*-1), 0) -> 0 | Y23: 283 | Z23: =E23 -> Bundled | AA23: 1 | AB23: Fixed | AC23: 0 | AD23: 0 | AI23: =AG23-AH23 -> 0 | AM23: =N23*L23 -> 3680 | AN23: =Y23*X23 -> 0 | AO23: =AD23*AC23*AA23 -> 0 | AP23: =AL23*AJ23 -> 0 | AQ23: 0 | AR23: =SUBTOTAL(9,AM23:AQ23) -> 3680 | AZ23: =IF(F23="Rack",AR23/I23,0)+IF(F23="U Space",AR23*40/I23,0)+IF(F23="Space",AR23*30/I23,0) -> 1840 | BA23: =+AR23/V23 -> 283.07692 | BB23: =+($AN23+$AO23+$AP23-BI23)/$W23 -> #VALUE! | BC23: =+($AN23+$AO23+$AP23-BJ23)/$W23 -> #VALUE! | BD23: =+($AN23+$AO23+IF(E23="Bundled",0,V23*0.85*AA23*AC23*30.5*24)-BK23)/$W23 -> #VALUE! | BF23: =+AM23+AN23+AO23 -> 3680 | BG23: =+BF23-BH23 -> #VALUE! | BH23: =IF(E23="Bundled",MIN(V23*$AE$1*(1+#REF!),BF23),AO23) -> #VALUE! | BI23: =IF($AE23>0,$AE23*$AB$1*$AD$1*(1+$AG$1*(20/$AD$1)/732),$AE$1*W23) -> #VALUE! | BJ23: =IF($AE23>0,$AE23*$AB$1*$AD$1*(1+$AG$1*(20/$AD$1)/732),+$AE$1*(W23+U23)) -> #VALUE! | BK23: =IF(E23="Bundled",$AE$1*V23,$AE$1*V23*0.85) -> #VALUE! | BL23: =+BB23*V23 -> #VALUE! | BM23: =+#REF!*V23 -> #REF! | BN23: =+BG23-BM23 -> #VALUE! | BO23: =+BH23-BI23 -> #VALUE! | BP23: =+BN23+BO23 -> #VALUE! | BQ23: =+V23 -> 13 | BR23: =+BB23 -> #VALUE! | BS23: =IF(E23="Bundled",BK23-BI23,AO23-BI23) -> #VALUE! | BT23: =IF(E23="Bundled",+(BD23-#REF!)*V23,(AM23+AN23)-V23*#REF!) -> #VALUE! | BU23: =+BS23+BT23 -> #VALUE! | BV23: =+BS23/$BR23 -> #VALUE! | BW23: =+BT23/$BR23 -> #VALUE! | BX23: =+BU23/$BR23 -> #VALUE!
A24: L4 | B24: L4-F-30 | C24: CP WHOLESALE INDIA PVT LTD | D24: Rated | E24: Metered | F24: Rack | G24: Uncaged | H24: =IF(F24="Rack","No of Racks",(IF(F24="Space","Sq Ft","U Space"))) -> No of Racks | I24: 1 | J24: 1 | K24: =I24-J24 -> 0 | L24: 1 | N24: =(360000)/12 -> 30000 | O24: =D24 -> Rated | P24: KVA | Q24: 9 | R24: 9 | S24: =Q24-R24 -> 0 | U24: =IF(S24<=0,0,(IF(O24="Rated",(S24+T24)*$V$1,(S24+T24)))) -> 0 | V24: =IF(O24="Rated",Q24*$V$1,Q24) -> #VALUE! | W24: =AD24/31/24 -> 0.81201613 | X24: =IF((S24*-1)>0, (S24*-1), 0) -> 0 | Y24: 0 | Z24: =E24 -> Metered | AA24: 1 | AB24: Fixed | AC24: 17 | AD24: 604.14 | AF24: =IF(AE24="No of Seats","No of Seats",(IF(AE24="Space","Sq Ft",""))) | AI24: =AG24-AH24 -> 0 | AM24: =N24*L24 -> 30000 | AN24: =Y24*X24 -> 0 | AO24: =AD24*AC24*AA24 -> 10270.38 | AP24: =AL24*AJ24 -> 0 | AQ24: =600000/12 -> 50000 | AR24: =SUBTOTAL(9,AM24:AQ24) -> 90270.38 | AT24: 721005527 & 711120937 | AZ24: =IF(F24="Rack",AR24/I24,0)+IF(F24="U Space",AR24*40/I24,0)+IF(F24="Space",AR24*30/I24,0) -> 90270.38 | BA24: =+AR24/V24 -> #VALUE! | BB24: =+($AM24+$AN24+$AO24-BI24)/$V24 -> #VALUE! | BC24: =+($AM24+$AN24+$AO24-BJ24)/$V24 -> #VALUE! | BD24: =+($AM24+$AN24+IF(E24="Bundled",0,V24*0.85*AA24*AC24*30.5*24)-BK24)/$V24 -> #VALUE! | BF24: =+AM24+AN24+AO24 -> 40270.38 | BG24: =+BF24-BH24 -> 30000 | BH24: =IF(E24="Bundled",MIN(V24*$AE$1*(1+#REF!),BF24),AO24) -> 10270.38 | BI24: =IF($AD24>0,$AD24*$AB$1*$AD$1*(1+$AG$1*(20/$AD$1)/732),$AE$1*W24) -> #VALUE! | BJ24: =IF($AD24>0,$AD24*$AB$1*$AD$1*(1+$AG$1*(20/$AD$1)/732),+$AE$1*(W24+U24)) -> #VALUE! | BK24: =IF(E24="Bundled",$AE$1*V24,$AE$1*V24*0.85) -> #VALUE! | BL24: =+BB24*V24 -> #VALUE! | BM24: =+#REF!*V24 -> #REF! | BN24: =+BG24-BM24 -> #REF! | BO24: =+BH24-BI24 -> #VALUE! | BP24: =+BN24+BO24 -> #REF! | BQ24: =+V24 -> #VALUE! | BR24: =+BB24 -> #VALUE! | BS24: =IF(E24="Bundled",BK24-BI24,AO24-BI24) -> #VALUE! | BT24: =IF(E24="Bundled",+(BD24-#REF!)*V24,(AM24+AN24)-V24*#REF!) -> #VALUE! | BU24: =+BS24+BT24 -> #VALUE! | BV24: =+BS24/$BQ24 -> #VALUE! | BW24: =+BT24/$BQ24 -> #VALUE! | BX24: =+BU24/$BQ24 -> #VALUE!
A25: L4 | B25: L4-E-33 | C25: CP WHOLESALE INDIA PVT LTD | D25: Rated | E25: Metered | F25: Rack | G25: Uncaged | H25: =IF(F25="Rack","No of Racks",(IF(F25="Space","Sq Ft","U Space"))) -> No of Racks | I25: 1 | J25: 1 | K25: 0 | L25: 1 | N25: =(750000+320000+225000)/12/3 -> 35972.222 | O25: =D25 -> Rated | P25: KVA | Q25: 8 | R25: 10.62 | S25: =Q25-R25 -> -2.62 | U25: =IF(S25<=0,0,(IF(O25="Rated",(S25+T25)*$V$1,(S25+T25)))) -> 0 | V25: =IF(O25="Rated",Q25*$V$1,Q25) -> #VALUE! | W25: =AD25/31/24 -> 4.4697849 | X25: =IF((S25*-1)>0, (S25*-1), 0) -> 2.62 | Y25: =90000/12 -> 7500 | Z25: =E25 -> Metered | AA25: 1 | AB25: Fixed | AC25: 15.75 | AD25: 3325.52 | AF25: =IF(AE25="No of Seats","No of Seats",(IF(AE25="Space","Sq Ft",""))) | AI25: =AG25-AH25 -> 0 | AM25: =N25*L25 -> 35972.222 | AN25: =Y25*X25 -> 19650 | AO25: =AD25*AC25*AA25 -> 52376.94 | AP25: =AL25*AJ25 -> 0 | AQ25: =600000/12 -> 50000 | AR25: =SUBTOTAL(9,AM25:AQ25) -> 157999.16 | AT25: 721005527 & 711120937 | AZ25: =IF(F25="Rack",AR25/I25,0)+IF(F25="U Space",AR25*40/I25,0)+IF(F25="Space",AR25*30/I25,0) -> 157999.16 | BA25: =+AR25/V25 -> #VALUE! | BB25: =+($AM25+$AN25+$AO25-BI25)/$V25 -> #VALUE! | BC25: =+($AM25+$AN25+$AO25-BJ25)/$V25 -> #VALUE! | BD25: =+($AM25+$AN25+IF(E25="Bundled",0,V25*0.85*AA25*AC25*30.5*24)-BK25)/$V25 -> #VALUE! | BF25: =+AM25+AN25+AO25 -> 107999.16 | BG25: =+BF25-BH25 -> 55622.222 | BH25: =IF(E25="Bundled",MIN(V25*$AE$1*(1+#REF!),BF25),AO25) -> 52376.94 | BI25: =IF($AD25>0,$AD25*$AB$1*$AD$1*(1+$AG$1*(20/$AD$1)/732),$AE$1*W25) -> #VALUE! | BJ25: =IF($AD25>0,$AD25*$AB$1*$AD$1*(1+$AG$1*(20/$AD$1)/732),+$AE$1*(W25+U25)) -> #VALUE! | BK25: =IF(E25="Bundled",$AE$1*V25,$AE$1*V25*0.85) -> #VALUE! | BL25: =+BB25*V25 -> #VALUE! | BM25: =+#REF!*V25 -> #REF! | BN25: =+BG25-BM25 -> #REF! | BO25: =+BH25-BI25 -> #VALUE! | BP25: =+BN25+BO25 -> #REF! | BQ25: =+V25 -> #VALUE! | BR25: =+BB25 -> #VALUE! | BS25: =IF(E25="Bundled",BK25-BI25,AO25-BI25) -> #VALUE! | BT25: =IF(E25="Bundled",+(BD25-#REF!)*V25,(AM25+AN25)-V25*#REF!) -> #VALUE! | BU25: =+BS25+BT25 -> #VALUE! | BV25: =+BS25/$BQ25 -> #VALUE! | BW25: =+BT25/$BQ25 -> #VALUE! | BX25: =+BU25/$BQ25 -> #VALUE!
A26: L7 | B26: L7-A-15, L7-A-16, L7-A-17 & L7-A-18 | C26: Stackpath | D26: Subscribed | E26: Metered | F26: Rack | G26: Caged | H26: =IF(F26="Rack","No of Racks",(IF(F26="Space","Sq Ft","U Space"))) -> No of Racks | I26: 4 | J26: 4 | K26: =I26-J26 -> 0 | L26: 4 | N26: =(0)/12 -> 0 | O26: =D26 -> Subscribed | P26: KW | Q26: 30 | R26: =W26 -> 12.166935 | S26: =Q26-R26 -> 17.833065 | U26: =IF(S26<=0,0,(IF(O26="Rated",(S26+T26)*'Noida-01'!#REF!,(S26+T26)))) -> 17.833065 | V26: =IF(O26="Rated",Q26*'Noida-01'!#REF!,Q26) -> 30 | W26: =AD26/31/24 -> 12.166935 | X26: =IF((S26*-1)>0, (S26*-1), 0) -> 0 | Y26: =0/12 -> 0 | Z26: =E26 -> Metered | AB26: Fixed | AC26: 0 | AD26: 9052.2 | AI26: =AG26-AH26 -> 0 | AL26: =(0)/12 -> 0 | AM26: =N26*L26 -> 0 | AN26: =Y26*X26 -> 0 | AO26: =AD26*AC26*AA26 -> 0 | AP26: =AL26*AJ26 -> 0 | AQ26: =0/12 -> 0 | AR26: =SUBTOTAL(9,AM26:AQ26) -> 0 | AZ26: =IF(F26="Rack",AR26/I26,0)+IF(F26="U Space",AR26*40/I26,0)+IF(F26="Space",AR26*30/I26,0) -> 0 | BA26: =+AR26/V26 -> 0 | BB26: =+($AM26+$AN26+$AO26-BI26)/$V26 -> #REF! | BC26: =+($AM26+$AN26+$AO26-BJ26)/$V26 -> #REF! | BD26: =+($AM26+$AN26+IF(E26="Bundled",0,V26*0.85*AA26*AC26*30.5*24)-BK26)/$V26 -> #REF! | BF26: =+AM26+AN26+AO26 -> 0 | BG26: =+BF26-BH26 -> 0 | BH26: =IF(E26="Bundled",MIN(V26*'Noida-01'!#REF!*(1+#REF!),BF26),AO26) -> 0 | BI26: =IF($AD26>0,$AD26*'Noida-01'!#REF!*'Noida-01'!#REF!*(1+'Noida-01'!#REF!*(20/'Noida-01'!#REF!)/732),'Noida-01'!#REF!*W26) -> #REF! | BJ26: =IF($AD26>0,$AD26*'Noida-01'!#REF!*'Noida-01'!#REF!*(1+'Noida-01'!#REF!*(20/'Noida-01'!#REF!)/732),+'Noida-01'!#REF!*(W26+U26)) -> #REF! | BK26: =IF(E26="Bundled",'Noida-01'!#REF!*V26,'Noida-01'!#REF!*V26*0.85) -> #REF! | BL26: =+BB26*V26 -> #REF! | BM26: =+#REF!*V26 -> #REF! | BN26: =+BG26-BM26 -> #REF! | BO26: =+BH26-BI26 -> #REF! | BP26: =+BN26+BO26 -> #REF! | BQ26: =+V26 -> 30 | BR26: =+BB26 -> #REF! | BS26: =IF(E26="Bundled",BK26-BI26,AO26-BI26) -> #REF! | BT26: =IF(E26="Bundled",+(BD26-#REF!)*V26,(AM26+AN26)-V26*#REF!) -> #REF! | BU26: =+BS26+BT26 -> #REF! | BV26: =+BS26/$BQ26 -> #REF! | BW26: =+BT26/$BQ26 -> #REF! | BX26: =+BU26/$BQ26 -> #REF!
A27: L4 | B27: L4-E-23 | C27: iBOSS, INC. | D27: Rated | E27: Bundled | F27: Rack | G27: Uncaged | H27: =IF(F27="Rack","No of Racks",(IF(F27="Space","Sq Ft","U Space"))) -> No of Racks | I27: 1 | J27: 1 | K27: =I27-J27 -> 0 | L27: 1 | N27: =(13000*70)/12 -> 75833.333 | O27: =D27 -> Rated | P27: KVA | Q27: 5 | R27: 19.62 | S27: =Q27-R27 -> -14.62 | U27: =IF(S27<=0,0,(IF(O27="Rated",(S27+T27)*'Noida-01'!#REF!,(S27+T27)))) -> 0 | V27: =IF(O27="Rated",Q27*'Noida-01'!#REF!,Q27) -> #REF! | W27: 5.49 | X27: =IF((S27*-1)>0, (S27*-1), 0) -> 14.62 | Y27: =0/12 -> 0 | Z27: =E27 -> Bundled | AI27: =AG27-AH27 -> 0 | AL27: =(0)/12 -> 0 | AM27: =N27*L27 -> 75833.333 | AN27: =Y27*X27 -> 0 | AO27: =AD27*AC27*AA27 -> 0 | AP27: =AL27*AJ27 -> 0 | AQ27: =((19700+2850)*70)/12 -> 131541.67 | AR27: =SUBTOTAL(9,AM27:AQ27) -> 207375 | AT27: 121000513 | AU27: 43700 | AV27: 3 | AW27: 44795 | AZ27: =IF(F27="Rack",AR27/I27,0)+IF(F27="U Space",AR27*40/I27,0)+IF(F27="Space",AR27*30/I27,0) -> 207375 | BA27: =+AR27/V27 -> #REF! | BB27: =+($AM27+$AN27+$AO27-BI27)/$V27 -> #REF! | BC27: =+($AM27+$AN27+$AO27-BJ27)/$V27 -> #REF! | BD27: =+($AM27+$AN27+IF(E27="Bundled",0,V27*0.85*AA27*AC27*30.5*24)-BK27)/$V27 -> #REF! | BF27: =+AM27+AN27+AO27 -> 75833.333 | BG27: =+BF27-BH27 -> #REF! | BH27: =IF(E27="Bundled",MIN(V27*'Noida-01'!#REF!*(1+#REF!),BF27),AO27) -> #REF! | BI27: =IF($AD27>0,$AD27*'Noida-01'!#REF!*'Noida-01'!#REF!*(1+'Noida-01'!#REF!*(20/'Noida-01'!#REF!)/732),'Noida-01'!#REF!*W27) -> #REF! | BJ27: =IF($AD27>0,$AD27*'Noida-01'!#REF!*'Noida-01'!#REF!*(1+'Noida-01'!#REF!*(20/'Noida-01'!#REF!)/732),+'Noida-01'!#REF!*(W27+U27)) -> #REF! | BK27: =IF(E27="Bundled",'Noida-01'!#REF!*V27,'Noida-01'!#REF!*V27*0.85) -> #REF! | BL27: =+BB27*V27 -> #REF! | BM27: =+#REF!*V27 -> #REF! | BN27: =+BG27-BM27 -> #REF! | BO27: =+BH27-BI27 -> #REF! | BP27: =+BN27+BO27 -> #REF! | BQ27: =+V27 -> #REF! | BR27: =+BB27 -> #REF! | BS27: =IF(E27="Bundled",BK27-BI27,AO27-BI27) -> #REF! | BT27: =IF(E27="Bundled",+(BD27-#REF!)*V27,(AM27+AN27)-V27*#REF!) -> #REF! | BU27: =+BS27+BT27 -> #REF! | BV27: =+BS27/$BQ27 -> #REF! | BW27: =+BT27/$BQ27 -> #REF! | BX27: =+BU27/$BQ27 -> #REF!
A28: L7 | B28: L7-F-25 | C28: ONEOTT INTERTAINMENT LTD | D28: Subscribed | E28: Metered | F28: Rack | G28: Uncaged | H28: =IF(F28="Rack","No of Racks",(IF(F28="Space","Sq Ft","U Space"))) -> No of Racks | I28: 1 | J28: 1 | K28: =I28-J28 -> 0 | L28: 1 | O28: =D28 -> Subscribed | P28: KW | Q28: 2.5 | S28: =Q28-R28 -> 2.5 | U28: =IF(S28<=0,0,(IF(O28="Rated",(S28+T28)*$V$1,(S28+T28)))) -> 2.5 | V28: =IF(O28="Rated",Q28*$V$1,Q28) -> 2.5 | W28: =AD28/31/24 -> 0 | X28: =IF((S28*-1)>0, (S28*-1), 0) -> 0 | Z28: =E28 -> Metered
A29: L5 | B29: L5A-01-06 | C29: STAR BROADBAND SERVICES I PVT LTD | D29: Rated | E29: Bundled | F29: U space | G29: Uncaged | H29: =IF(F29="Rack","No of Racks",(IF(F29="Space","Sq Ft","U Space"))) -> U Space | I29: 1 | J29: 1 | K29: =I29-J29 -> 0 | L29: 1 | N29: =55000/12 -> 4583.3333 | O29: =D29 -> Rated | P29: KVA | Q29: 0.25 | R29: 0.26 | S29: =Q29-R29 -> -0.01 | U29: =IF(S29<=0,0,(IF(O29="Rated",(S29+T29)*$V$1,(S29+T29)))) -> 0 | V29: =IF(O29="Rated",Q29*$V$1,Q29) -> #VALUE! | X29: =IF((S29*-1)>0, (S29*-1), 0) -> 0.01 | Y29: =90000/12 -> 7500 | Z29: =E29 -> Bundled | AF29: =IF(AE29="No of Seats","No of Seats",(IF(AE29="Space","Sq Ft",""))) | AI29: =AG29-AH29 -> 0 | AM29: =N29*L29 -> 4583.3333 | AN29: =Y29*X29 -> 75 | AO29: =AD29*AC29*AA29 -> 0 | AP29: =AL29*AJ29 -> 0 | AQ29: =(10000+140000)/12 -> 12500 | AR29: =SUBTOTAL(9,AM29:AQ29) -> 17158.333 | AT29: 121000867 | AZ29: =IF(F29="Rack",AR29/I29,0)+IF(F29="U Space",AR29*40/I29,0)+IF(F29="Space",AR29*30/I29,0) -> 686333.33 | BA29: =+AR29/V29 -> #VALUE! | BB29: =+($AM29+$AN29+$AO29-BI29)/$V29 -> #VALUE! | BC29: =+($AM29+$AN29+$AO29-BJ29)/$V29 -> #VALUE! | BD29: =+($AM29+$AN29+IF(E29="Bundled",0,V29*0.85*AA29*AC29*30.5*24)-BK29)/$V29 -> #VALUE! | BF29: =+AM29+AN29+AO29 -> 4658.3333 | BG29: =+BF29-BH29 -> #VALUE! | BH29: =IF(E29="Bundled",MIN(V29*$AE$1*(1+#REF!),BF29),AO29) -> #VALUE! | BI29: =IF($AD29>0,$AD29*$AB$1*$AD$1*(1+$AG$1*(20/$AD$1)/732),$AE$1*W29) -> #VALUE! | BJ29: =IF($AD29>0,$AD29*$AB$1*$AD$1*(1+$AG$1*(20/$AD$1)/732),+$AE$1*(W29+U29)) -> #VALUE! | BK29: =IF(E29="Bundled",$AE$1*V29,$AE$1*V29*0.85) -> #VALUE! | BL29: =+BB29*V29 -> #VALUE! | BM29: =+#REF!*V29 -> #REF! | BN29: =+BG29-BM29 -> #VALUE! | BO29: =+BH29-BI29 -> #VALUE! | BP29: =+BN29+BO29 -> #VALUE! | BQ29: =+V29 -> #VALUE! | BR29: =+BB29 -> #VALUE! | BS29: =IF(E29="Bundled",BK29-BI29,AO29-BI29) -> #VALUE! | BT29: =IF(E29="Bundled",+(BD29-#REF!)*V29,(AM29+AN29)-V29*#REF!) -> #VALUE! | BU29: =+BS29+BT29 -> #VALUE! | BV29: =+BS29/$BQ29 -> #VALUE! | BW29: =+BT29/$BQ29 -> #VALUE! | BX29: =+BU29/$BQ29 -> #VALUE!
A30: L5 | B30: L5A-02-01 | C30: PRACTION NETWORKS PVT LTD | D30: Rated | E30: Bundled | F30: U space | G30: Uncaged | H30: =IF(F30="Rack","No of Racks",(IF(F30="Space","Sq Ft","U Space"))) -> U Space | I30: 4 | J30: 4 | K30: =I30-J30 -> 0 | L30: 4 | N30: =35000/12 -> 2916.6667 | O30: =D30 -> Rated | P30: KVA | Q30: 1 | R30: 0.17 | S30: =Q30-R30 -> 0.83 | U30: =IF(S30<=0,0,(IF(O30="Rated",(S30+T30)*$V$1,(S30+T30)))) -> #VALUE! | V30: =IF(O30="Rated",Q30*$V$1,Q30) -> #VALUE! | X30: =IF((S30*-1)>0, (S30*-1), 0) -> 0 | Y30: =110000/12 -> 9166.6667 | Z30: =E30 -> Bundled | AF30: =IF(AE30="No of Seats","No of Seats",(IF(AE30="Space","Sq Ft",""))) | AI30: =AG30-AH30 -> 0 | AM30: =N30*L30 -> 11666.667 | AN30: =Y30*X30 -> 0 | AO30: =AD30*AC30*AA30 -> 0 | AP30: =AL30*AJ30 -> 0 | AQ30: =(100000+60000)/12 -> 13333.333 | AR30: =SUBTOTAL(9,AM30:AQ30) -> 25000 | AT30: 121000185 | AZ30: =IF(F30="Rack",AR30/I30,0)+IF(F30="U Space",AR30*40/I30,0)+IF(F30="Space",AR30*30/I30,0) -> 250000 | BA30: =+AR30/V30 -> #VALUE! | BB30: =+($AM30+$AN30+$AO30-BI30)/$V30 -> #VALUE! | BC30: =+($AM30+$AN30+$AO30-BJ30)/$V30 -> #VALUE! | BD30: =+($AM30+$AN30+IF(E30="Bundled",0,V30*0.85*AA30*AC30*30.5*24)-BK30)/$V30 -> #VALUE! | BF30: =+AM30+AN30+AO30 -> 11666.667 | BG30: =+BF30-BH30 -> #VALUE! | BH30: =IF(E30="Bundled",MIN(V30*$AE$1*(1+#REF!),BF30),AO30) -> #VALUE! | BI30: =IF($AD30>0,$AD30*$AB$1*$AD$1*(1+$AG$1*(20/$AD$1)/732),$AE$1*W30) -> #VALUE! | BJ30: =IF($AD30>0,$AD30*$AB$1*$AD$1*(1+$AG$1*(20/$AD$1)/732),+$AE$1*(W30+U30)) -> #VALUE! | BK30: =IF(E30="Bundled",$AE$1*V30,$AE$1*V30*0.85) -> #VALUE! | BL30: =+BB30*V30 -> #VALUE! | BM30: =+#REF!*V30 -> #REF! | BN30: =+BG30-BM30 -> #VALUE! | BO30: =+BH30-BI30 -> #VALUE! | BP30: =+BN30+BO30 -> #VALUE! | BQ30: =+V30 -> #VALUE! | BR30: =+BB30 -> #VALUE! | BS30: =IF(E30="Bundled",BK30-BI30,AO30-BI30) -> #VALUE! | BT30: =IF(E30="Bundled",+(BD30-#REF!)*V30,(AM30+AN30)-V30*#REF!) -> #VALUE! | BU30: =+BS30+BT30 -> #VALUE! | BV30: =+BS30/$BQ30 -> #VALUE! | BW30: =+BT30/$BQ30 -> #VALUE! | BX30: =+BU30/$BQ30 -> #VALUE!
A31: L4 | B31: Server Hall L4 L4-D-29 | C31: SPEEDNET UNIQUE NETWORK PVT LTD | D31: Rated | E31: Bundled | F31: U space | G31: Uncaged | H31: =IF(F31="Rack","No of Racks",(IF(F31="Space","Sq Ft","U Space"))) -> U Space | I31: 1 | J31: 1 | K31: =I31-J31 -> 0 | L31: 1 | N31: =(35000)/12 -> 2916.6667 | O31: =D31 -> Rated | P31: KVA | Q31: 0.25 | R31: 0.13 | S31: =Q31-R31 -> 0.12 | U31: =IF(S31<=0,0,(IF(O31="Rated",(S31+T31)*$W$1,(S31+T31)))) -> 0 | V31: =IF(O31="Rated",Q31*$W$1,Q31) -> 0 | X31: =IF((S31*-1)>0, (S31*-1), 0) -> 0 | Y31: =0/12 -> 0 | Z31: =E31 -> Bundled | AI31: =AG31-AH31 -> 0 | AL31: =(0)/12 -> 0 | AM31: =N31*L31 -> 2916.6667 | AN31: =Y31*X31 -> 0 | AO31: =AD31*AC31*AA31 -> 0 | AP31: =AL31*AJ31 -> 0 | AQ31: =0/12 -> 0 | AR31: =SUBTOTAL(9,AM31:AQ31) -> 2916.6667 | AZ31: =IF(F31="Rack",AR31/I31,0)+IF(F31="U Space",AR31*40/I31,0)+IF(F31="Space",AR31*30/I31,0) -> 116666.67 | BA31: =+AR31/V31 -> #DIV/0! | BB31: =+($AM31+$AN31+$AO31-BI31)/$V31 -> #DIV/0! | BC31: =+($AM31+$AN31+$AO31-BJ31)/$V31 -> #DIV/0! | BD31: =+($AM31+$AN31+IF(E31="Bundled",0,V31*0.85*AA31*AC31*30.5*24)-BK31)/$V31 -> #DIV/0! | BF31: =+AM31+AN31+AO31 -> 2916.6667 | BG31: =+BF31-BH31 -> #REF! | BH31: =IF(E31="Bundled",MIN(V31*$AF$1*(1+#REF!),BF31),AO31) -> #REF! | BI31: =IF($AD31>0,$AD31*$AC$1*$AE$1*(1+$AH$1*(20/$AE$1)/732),$AF$1*W31) -> 0 | BJ31: =IF($AD31>0,$AD31*$AC$1*$AE$1*(1+$AH$1*(20/$AE$1)/732),+$AF$1*(W31+U31)) -> 0 | BK31: =IF(E31="Bundled",$AF$1*V31,$AF$1*V31*0.85) -> 0 | BL31: =+BB31*V31 -> #DIV/0! | BM31: =+#REF!*V31 -> #REF! | BN31: =+BG31-BM31 -> #REF! | BO31: =+BH31-BI31 -> #REF! | BP31: =+BN31+BO31 -> #REF! | BQ31: =+V31 -> 0 | BR31: =+BB31 -> #DIV/0! | BS31: =IF(E31="Bundled",BK31-BI31,AO31-BI31) -> 0 | BT31: =IF(E31="Bundled",+(BD31-#REF!)*V31,(AM31+AN31)-V31*#REF!) -> #DIV/0! | BU31: =+BS31+BT31 -> #DIV/0! | BV31: =+BS31/$BQ31 -> #DIV/0! | BW31: =+BT31/$BQ31 -> #DIV/0! | BX31: =+BU31/$BQ31 -> #DIV/0!
A32: L4 | B32: Server Hall L4 L4-E-29 | C32: FIBLIB DIGITAL NETWORKS | D32: Rated | E32: Bundled | F32: U space | G32: Uncaged | H32: =IF(F32="Rack","No of Racks",(IF(F32="Space","Sq Ft","U Space"))) -> U Space | I32: 2 | J32: 2 | K32: =I32-J32 -> 0 | L32: 2 | N32: =(75000/2)/12 -> 3125 | O32: =D32 -> Rated | P32: KVA | Q32: 0.5 | R32: 0.25 | S32: =Q32-R32 -> 0.25 | U32: =IF(S32<=0,0,(IF(O32="Rated",(S32+T32)*$W$1,(S32+T32)))) -> 0 | V32: =IF(O32="Rated",Q32*$W$1,Q32) -> 0 | X32: =IF((S32*-1)>0, (S32*-1), 0) -> 0 | Z32: =E32 -> Bundled | AI32: =AG32-AH32 -> 0 | AL32: =(0)/12 -> 0 | AN32: =Y32*X32 -> 0 | AO32: =AD32*AC32*AA32 -> 0 | AP32: =AL32*AJ32 -> 0 | AQ32: =0/12 -> 0 | AR32: =SUBTOTAL(9,AM32:AQ32) -> 0 | AZ32: =IF(F32="Rack",AR32/I32,0)+IF(F32="U Space",AR32*40/I32,0)+IF(F32="Space",AR32*30/I32,0) -> 0 | BA32: =+AR32/V32 -> #DIV/0! | BB32: =+($AM32+$AN32+$AO32-BI32)/$V32 -> #DIV/0! | BC32: =+($AM32+$AN32+$AO32-BJ32)/$V32 -> #DIV/0! | BD32: =+($AM32+$AN32+IF(E32="Bundled",0,V32*0.85*AA32*AC32*30.5*24)-BK32)/$V32 -> #DIV/0! | BF32: =+AM32+AN32+AO32 -> 0 | BG32: =+BF32-BH32 -> #REF! | BH32: =IF(E32="Bundled",MIN(V32*$AF$1*(1+#REF!),BF32),AO32) -> #REF! | BI32: =IF($AD32>0,$AD32*$AC$1*$AE$1*(1+$AH$1*(20/$AE$1)/732),$AF$1*W32) -> 0 | BJ32: =IF($AD32>0,$AD32*$AC$1*$AE$1*(1+$AH$1*(20/$AE$1)/732),+$AF$1*(W32+U32)) -> 0 | BK32: =IF(E32="Bundled",$AF$1*V32,$AF$1*V32*0.85) -> 0 | BL32: =+BB32*V32 -> #DIV/0! | BM32: =+#REF!*V32 -> #REF! | BN32: =+BG32-BM32 -> #REF! | BO32: =+BH32-BI32 -> #REF! | BP32: =+BN32+BO32 -> #REF! | BQ32: =+V32 -> 0 | BR32: =+BB32 -> #DIV/0! | BS32: =IF(E32="Bundled",BK32-BI32,AO32-BI32) -> 0 | BT32: =IF(E32="Bundled",+(BD32-#REF!)*V32,(AM32+AN32)-V32*#REF!) -> #DIV/0! | BU32: =+BS32+BT32 -> #DIV/0! | BV32: =+BS32/$BQ32 -> #DIV/0! | BW32: =+BT32/$BQ32 -> #DIV/0! | BX32: =+BU32/$BQ32 -> #DIV/0!
A33: L6 | B33: L6-G-26 to L6-G-33, L6-F-26 to L6-F-33 | C33: GLORYBIRD INDIA PRIVATE LIMITED | D33: Subscribed | E33: Bundled | F33: Rack | G33: Uncaged | H33: =IF(F33="Rack","No of Racks",(IF(F33="Space","Sq Ft","U Space"))) -> No of Racks | I33: 16 | J33: 16 | K33: =I33-J33 -> 0 | L33: 16 | N33: =2042880/16 -> 127680 | O33: =D33 -> Subscribed | P33: KW | Q33: 78 | R33: =W33 -> 0 | S33: =Q33-R33 -> 78 | U33: =IF(S33<=0,0,(IF(O33="Rated",(S33+T33)*'Noida-01'!#REF!,(S33+T33)))) -> 78 | V33: =IF(O33="Rated",Q33*'Noida-01'!#REF!,Q33) -> 78 | W33: =AD33/30/24 -> 0 | X33: =IF((S33*-1)>0, (S33*-1), 0) -> 0 | Y33: 0 | Z33: =E33 -> Bundled | AA33: 1 | AB33: Fixed | AC33: 0 | AD33: 0 | AI33: =AG33-AH33 -> 0 | AL33: =(0)/12 -> 0 | AM33: =N33*L33 -> 2042880 | AN33: =Y33*X33 -> 0 | AO33: =AD33*AC33*AA33 -> 0 | AP33: =AL33*AJ33 -> 0 | AQ33: =0/12 -> 0 | AR33: =SUBTOTAL(9,AM33:AQ33) -> 2042880 | AZ33: =IF(F33="Rack",AR33/I33,0)+IF(F33="U Space",AR33*40/I33,0)+IF(F33="Space",AR33*30/I33,0) -> 127680 | BA33: =+AR33/V33 -> 26190.769 | BB33: =+($AM33+$AN33+$AO33-BI33)/$V33 -> #REF! | BC33: =+($AM33+$AN33+$AO33-BJ33)/$V33 -> #REF! | BD33: =+($AM33+$AN33+IF(E33="Bundled",0,V33*0.85*AA33*AC33*30.5*24)-BK33)/$V33 -> #REF! | BF33: =+AM33+AN33+AO33 -> 2042880 | BG33: =+BF33-BH33 -> #REF! | BH33: =IF(E33="Bundled",MIN(V33*'Noida-01'!#REF!*(1+#REF!),BF33),AO33) -> #REF! | BI33: =IF($AD33>0,$AD33*'Noida-01'!#REF!*'Noida-01'!#REF!*(1+'Noida-01'!#REF!*(20/'Noida-01'!#REF!)/732),'Noida-01'!#REF!*W33) -> #REF! | BJ33: =IF($AD33>0,$AD33*'Noida-01'!#REF!*'Noida-01'!#REF!*(1+'Noida-01'!#REF!*(20/'Noida-01'!#REF!)/732),+'Noida-01'!#REF!*(W33+U33)) -> #REF! | BK33: =IF(E33="Bundled",'Noida-01'!#REF!*V33,'Noida-01'!#REF!*V33*0.85) -> #REF! | BL33: =+BB33*V33 -> #REF! | BM33: =+#REF!*V33 -> #REF! | BN33: =+BG33-BM33 -> #REF! | BO33: =+BH33-BI33 -> #REF! | BP33: =+BN33+BO33 -> #REF! | BQ33: =+V33 -> 78 | BR33: =+BB33 -> #REF! | BS33: =IF(E33="Bundled",BK33-BI33,AO33-BI33) -> #REF! | BT33: =IF(E33="Bundled",+(BD33-#REF!)*V33,(AM33+AN33)-V33*#REF!) -> #REF! | BU33: =+BS33+BT33 -> #REF! | BV33: =+BS33/$BQ33 -> #REF! | BW33: =+BT33/$BQ33 -> #REF! | BX33: =+BU33/$BQ33 -> #REF!
A34: L6 | B34: Server Hall L6 L6-F-24 | C34: IPNET BROADBAND NETWORK PVT LTD ( 29U TO 30U) | D34: Rated | E34: Bundled | F34: U space | G34: Uncaged | H34: =IF(F34="Rack","No of Racks",(IF(F34="Space","Sq Ft","U Space"))) -> U Space | I34: 2 | J34: 2 | K34: =I34-J34 -> 0 | L34: 2 | N34: =(18000)/12 -> 1500 | O34: =D34 -> Rated | P34: KVA | Q34: 0.3 | R34: 0.04 | S34: =Q34-R34 -> 0.26 | U34: =IF(S34<=0,0,(IF(O34="Rated",(S34+T34)*$W$1,(S34+T34)))) -> 0 | V34: =IF(O34="Rated",Q34*$W$1,Q34) -> 0 | X34: =IF((S34*-1)>0, (S34*-1), 0) -> 0 | Z34: =E34 -> Bundled | AF34: =IF(AE34="No of Seats","No of Seats",(IF(AE34="Space","Sq Ft",""))) | AI34: =AG34-AH34 -> 0 | AM34: =N34*L34 -> 3000 | AN34: =Y34*X34 -> 0 | AO34: =AD34*AC34*AA34 -> 0 | AP34: =AL34*AJ34 -> 0 | AQ34: 0 | AR34: =SUBTOTAL(9,AM34:AQ34) -> 3000 | AZ34: =IF(F34="Rack",AR34/I34,0)+IF(F34="U Space",AR34*40/I34,0)+IF(F34="Space",AR34*30/I34,0) -> 60000 | BA34: =+AR34/V34 -> #DIV/0! | BB34: =+($AM34+$AN34+$AO34-BI34)/$V34 -> #DIV/0! | BC34: =+($AM34+$AN34+$AO34-BJ34)/$V34 -> #DIV/0! | BD34: =+($AM34+$AN34+IF(E34="Bundled",0,V34*0.85*AA34*AC34*30.5*24)-BK34)/$V34 -> #DIV/0! | BF34: =+AM34+AN34+AO34 -> 3000 | BG34: =+BF34-BH34 -> #REF! | BH34: =IF(E34="Bundled",MIN(V34*$AF$1*(1+#REF!),BF34),AO34) -> #REF! | BI34: =IF($AD34>0,$AD34*$AC$1*$AE$1*(1+$AH$1*(20/$AE$1)/732),$AF$1*W34) -> 0 | BJ34: =IF($AD34>0,$AD34*$AC$1*$AE$1*(1+$AH$1*(20/$AE$1)/732),+$AF$1*(W34+U34)) -> 0 | BK34: =IF(E34="Bundled",$AF$1*V34,$AF$1*V34*0.85) -> 0 | BL34: =+BB34*V34 -> #DIV/0! | BM34: =+#REF!*V34 -> #REF! | BN34: =+BG34-BM34 -> #REF! | BO34: =+BH34-BI34 -> #REF! | BP34: =+BN34+BO34 -> #REF! | BQ34: =+V34 -> 0 | BR34: =+BB34 -> #DIV/0! | BS34: =IF(E34="Bundled",BK34-BI34,AO34-BI34) -> 0 | BT34: =IF(E34="Bundled",+(BD34-#REF!)*V34,(AM34+AN34)-V34*#REF!) -> #DIV/0! | BU34: =+BS34+BT34 -> #DIV/0! | BV34: =+BS34/$BQ34 -> #DIV/0! | BW34: =+BT34/$BQ34 -> #DIV/0! | BX34: =+BU34/$BQ34 -> #DIV/0!
A35: L4 | B35: L4-C-28 | C35: UNITAS GLOBAL INDIA PVT LTD | D35: Rated | E35: Bundled | F35: Rack | G35: Uncaged | H35: =IF(F35="Rack","No of Racks",(IF(F35="Space","Sq Ft","U Space"))) -> No of Racks | I35: 1 | J35: 1 | K35: =I35-J35 -> 0 | L35: 1 | N35: =(9740*70)/12 -> 56816.667 | O35: =D35 -> Rated | P35: KVA | Q35: 5 | R35: 3.56 | S35: =Q35-R35 -> 1.44 | U35: =IF(S35<=0,0,(IF(O35="Rated",(S35+T35)*$W$1,(S35+T35)))) -> 0 | V35: =IF(O35="Rated",Q35*$W$1,Q35) -> 0 | W35: 0.91 | X35: =IF((S35*-1)>0, (S35*-1), 0) -> 0 | Y35: =120000/12 -> 10000 | Z35: =E35 -> Bundled | AI35: =AG35-AH35 -> 0 | AL35: =(0)/12 -> 0 | AM35: =N35*L35 -> 56816.667 | AN35: =Y35*X35 -> 0 | AO35: =AD35*AC35*AA35 -> 0 | AP35: =AL35*AJ35 -> 0 | AQ35: =((7792+325+9091)*70)/12 -> 100380 | AR35: =SUBTOTAL(9,AM35:AQ35) -> 157196.67 | AT35: 121001564 | AZ35: =IF(F35="Rack",AR35/I35,0)+IF(F35="U Space",AR35*40/I35,0)+IF(F35="Space",AR35*30/I35,0) -> 157196.67 | BA35: =+AR35/V35 -> #DIV/0! | BB35: =+($AO35+$AP35+$AQ35-BI35)/$X35 -> #DIV/0! | BC35: =+($AO35+$AP35+$AQ35-BJ35)/$X35 -> #DIV/0! | BD35: =+($AO35+$AP35+IF(E35="Bundled",0,V35*0.85*AA35*AC35*30.5*24)-BK35)/$X35 -> #DIV/0! | BF35: =+AM35+AN35+AO35 -> 56816.667 | BG35: =+BF35-BH35 -> #REF! | BH35: =IF(E35="Bundled",MIN(V35*$AF$1*(1+#REF!),BF35),AO35) -> #REF! | BI35: =IF($AF35>0,$AF35*$AC$1*$AE$1*(1+$AH$1*(20/$AE$1)/732),$AF$1*W35) -> 64.155 | BJ35: =IF($AF35>0,$AF35*$AC$1*$AE$1*(1+$AH$1*(20/$AE$1)/732),+$AF$1*(W35+U35)) -> 64.155 | BK35: =IF(E35="Bundled",$AF$1*V35,$AF$1*V35*0.85) -> 0 | BL35: =+BB35*V35 -> #DIV/0! | BM35: =+#REF!*V35 -> #REF! | BN35: =+BG35-BM35 -> #REF! | BO35: =+BH35-BI35 -> #REF! | BP35: =+BN35+BO35 -> #REF! | BQ35: =+V35 -> 0 | BR35: =+BB35 -> #DIV/0! | BS35: =IF(E35="Bundled",BK35-BI35,AO35-BI35) -> -64.155 | BT35: =IF(E35="Bundled",+(BD35-#REF!)*V35,(AM35+AN35)-V35*#REF!) -> #DIV/0! | BU35: =+BS35+BT35 -> #DIV/0! | BV35: =+BS35/$BS35 -> 1 | BW35: =+BT35/$BS35 -> #DIV/0! | BX35: =+BU35/$BS35 -> #DIV/0!
A36: L4 | B36: L4-C-29 | C36: SUBSPACE COMMUNICATION LLC | D36: Subscribed | E36: Bundled | F36: Rack | G36: Uncaged | H36: =IF(F36="Rack","No of Racks",(IF(F36="Space","Sq Ft","U Space"))) -> No of Racks | I36: 1 | J36: 1 | K36: =I36-J36 -> 0 | L36: 1 | N36: =(1080*70) -> 75600 | O36: =D36 -> Subscribed | P36: KW | Q36: 4 | R36: =W36 -> 0.35441667 | S36: =Q36-R36 -> 3.6455833 | U36: =IF(S36<=0,0,(IF(O36="Rated",(S36+T36)*$W$1,(S36+T36)))) -> 3.6455833 | V36: =IF(O36="Rated",Q36*$W$1,Q36) -> 4 | W36: =AD36/30/24 -> 0.35441667 | X36: =IF((S36*-1)>0, (S36*-1), 0) -> 0 | Y36: =0/12 -> 0 | Z36: =E36 -> Bundled | AD36: 255.18 | AI36: =AG36-AH36 -> 0 | AL36: =(0)/12 -> 0 | AM36: =N36*L36 -> 75600 | AN36: =Y36*X36 -> 0 | AO36: =AD36*AC36*AA36 -> 0 | AP36: =AL36*AJ36 -> 0 | AQ36: =0/12 -> 0 | AR36: =SUBTOTAL(9,AM36:AQ36) -> 75600 | AZ36: =IF(F36="Rack",AR36/I36,0)+IF(F36="U Space",AR36*40/I36,0)+IF(F36="Space",AR36*30/I36,0) -> 75600 | BA36: =+AR36/V36 -> 18900 | BB36: =+($AO36+$AP36+$AQ36-BI36)/$X36 -> #DIV/0! | BC36: =+($AO36+$AP36+$AQ36-BJ36)/$X36 -> #DIV/0! | BD36: =+($AO36+$AP36+IF(E36="Bundled",0,V36*0.85*AA36*AC36*30.5*24)-BK36)/$X36 -> #DIV/0! | BF36: =+AM36+AN36+AO36 -> 75600 | BG36: =+BF36-BH36 -> #REF! | BH36: =IF(E36="Bundled",MIN(V36*$AF$1*(1+#REF!),BF36),AO36) -> #REF! | BI36: =IF($AF36>0,$AF36*$AC$1*$AE$1*(1+$AH$1*(20/$AE$1)/732),$AF$1*W36) -> 24.986375 | BJ36: =IF($AF36>0,$AF36*$AC$1*$AE$1*(1+$AH$1*(20/$AE$1)/732),+$AF$1*(W36+U36)) -> 282 | BK36: =IF(E36="Bundled",$AF$1*V36,$AF$1*V36*0.85) -> 282 | BL36: =+BB36*V36 -> #DIV/0! | BM36: =+#REF!*V36 -> #REF! | BN36: =+BG36-BM36 -> #REF! | BO36: =+BH36-BI36 -> #REF! | BP36: =+BN36+BO36 -> #REF! | BQ36: =+V36 -> 4 | BR36: =+BB36 -> #DIV/0! | BS36: =IF(E36="Bundled",BK36-BI36,AO36-BI36) -> 257.01362 | BT36: =IF(E36="Bundled",+(BD36-#REF!)*V36,(AM36+AN36)-V36*#REF!) -> #DIV/0! | BU36: =+BS36+BT36 -> #DIV/0! | BV36: =+BS36/$BS36 -> 1 | BW36: =+BT36/$BS36 -> #DIV/0! | BX36: =+BU36/$BS36 -> #DIV/0!
A37: L5 | B37: L5A-01-01 | C37: THE NAGALAND STATE CO-OPERATIVE BANK LTD | D37: Rated | E37: Bundled | F37: Rack | G37: Uncaged | H37: =IF(F37="Rack","No of Racks",(IF(F37="Space","Sq Ft","U Space"))) -> No of Racks | I37: 1 | J37: 1 | K37: =I37-J37 -> 0 | L37: 1 | N37: =80000/12 -> 6666.6667 | O37: =D37 -> Rated | P37: KVA | Q37: 3 | R37: 4.49 | S37: =Q37-R37 -> -1.49 | U37: =IF(S37<=0,0,(IF(O37="Rated",(S37+T37)*'Noida-01'!#REF!,(S37+T37)))) -> 0 | V37: =IF(O37="Rated",Q37*'Noida-01'!#REF!,Q37) -> #REF! | W37: 1.17 | X37: =IF((S37*-1)>0, (S37*-1), 0) -> 1.49 | Y37: 0 | Z37: =E37 -> Bundled | AF37: =IF(AE37="No of Seats","No of Seats",(IF(AE37="Space","Sq Ft",""))) | AI37: =AG37-AH37 -> 0 | AM37: =N37*L37 -> 6666.6667 | AN37: =Y37*X37 -> 0 | AO37: =AD37*AC37*AA37 -> 0 | AP37: =AL37*AJ37 -> 0 | AQ37: =10000/12 -> 833.33333 | AR37: =SUBTOTAL(9,AM37:AQ37) -> 7500 | AT37: Renewal | AZ37: =IF(F37="Rack",AR37/I37,0)+IF(F37="U Space",AR37*40/I37,0)+IF(F37="Space",AR37*30/I37,0) -> 7500 | BA37: =+AR37/V37 -> #REF! | BB37: =+($AM37+$AN37+$AO37-BI37)/$V37 -> #REF! | BC37: =+($AM37+$AN37+$AO37-BJ37)/$V37 -> #REF! | BD37: =+($AM37+$AN37+IF(E37="Bundled",0,V37*0.85*AA37*AC37*30.5*24)-BK37)/$V37 -> #REF! | BF37: =+AM37+AN37+AO37 -> 6666.6667 | BG37: =+BF37-BH37 -> #REF! | BH37: =IF(E37="Bundled",MIN(V37*'Noida-01'!#REF!*(1+#REF!),BF37),AO37) -> #REF! | BI37: =IF($AD37>0,$AD37*'Noida-01'!#REF!*'Noida-01'!#REF!*(1+'Noida-01'!#REF!*(20/'Noida-01'!#REF!)/732),'Noida-01'!#REF!*W37) -> #REF! | BJ37: =IF($AD37>0,$AD37*'Noida-01'!#REF!*'Noida-01'!#REF!*(1+'Noida-01'!#REF!*(20/'Noida-01'!#REF!)/732),+'Noida-01'!#REF!*(W37+U37)) -> #REF! | BK37: =IF(E37="Bundled",'Noida-01'!#REF!*V37,'Noida-01'!#REF!*V37*0.85) -> #REF! | BL37: =+BB37*V37 -> #REF! | BM37: =+#REF!*V37 -> #REF! | BN37: =+BG37-BM37 -> #REF! | BO37: =+BH37-BI37 -> #REF! | BP37: =+BN37+BO37 -> #REF! | BQ37: =+V37 -> #REF! | BR37: =+BB37 -> #REF! | BS37: =IF(E37="Bundled",BK37-BI37,AO37-BI37) -> #REF! | BT37: =IF(E37="Bundled",+(BD37-#REF!)*V37,(AM37+AN37)-V37*#REF!) -> #REF! | BU37: =+BS37+BT37 -> #REF! | BV37: =+BS37/$BQ37 -> #REF! | BW37: =+BT37/$BQ37 -> #REF! | BX37: =+BU37/$BQ37 -> #REF!
A38: L5 | B38: L5A-01-11 | C38: PEERCAST TELECOM INDIA PRIVATE LIMITED | D38: Subscribed | E38: Metered | F38: Rack | G38: Uncaged | H38: =IF(F38="Rack","No of Racks",(IF(F38="Space","Sq Ft","U Space"))) -> No of Racks | I38: 1 | J38: 1 | K38: =I38-J38 -> 0 | L38: 1 | N38: =188000/12 -> 15666.667 | O38: =D38 -> Subscribed | P38: KW | Q38: 3 | R38: =W38 -> 1.5194355 | S38: =Q38-R38 -> 1.4805645 | U38: =IF(S38<=0,0,(IF(O38="Rated",(S38+T38)*$W$1,(S38+T38)))) -> 1.4805645 | V38: =IF(O38="Rated",Q38*$W$1,Q38) -> 3 | W38: =AD38/31/24 -> 1.5194355 | X38: =IF((S38*-1)>0, (S38*-1), 0) -> 0 | Z38: =E38 -> Metered | AA38: 1 | AB38: Fixed | AD38: 1130.46 | AF38: =IF(AE38="No of Seats","No of Seats",(IF(AE38="Space","Sq Ft",""))) | AI38: =AG38-AH38 -> 0 | AN38: =Y38*X38 -> 0 | AO38: =AD38*AC38*AA38 -> 0 | AP38: =AL38*AJ38 -> 0 | AR38: =SUBTOTAL(9,AM38:AQ38) -> 0 | AZ38: =IF(F38="Rack",AR38/I38,0)+IF(F38="U Space",AR38*40/I38,0)+IF(F38="Space",AR38*30/I38,0) -> 0 | BA38: =+AR38/V38 -> 0 | BB38: =+($AM38+$AN38+$AO38-BI38)/$V38 -> #VALUE! | BF38: =+AM38+AN38+AO38 -> 0 | BG38: =+BF38-BH38 -> 0 | BH38: =IF(E38="Bundled",MIN(V38*$AF$1*(1+#REF!),BF38),AO38) -> 0 | BI38: =IF($AD38>0,$AD38*$AC$1*$AE$1*(1+$AH$1*(20/$AE$1)/732),$AF$1*W38) -> #VALUE! | BL38: =+BB38*V38 -> #VALUE! | BM38: =+#REF!*V38 -> #REF! | BN38: =+BG38-BM38 -> #REF! | BO38: =+BH38-BI38 -> #VALUE! | BP38: =+BN38+BO38 -> #REF! | BQ38: =+V38 -> 3 | BR38: =+BB38 -> #VALUE! | BS38: =IF(E38="Bundled",BK38-BI38,AO38-BI38) -> #VALUE! | BT38: =IF(E38="Bundled",+(BD38-#REF!)*V38,(AM38+AN38)-V38*#REF!) -> #REF! | BU38: =+BS38+BT38 -> #VALUE! | BV38: =+BS38/$BQ38 -> #VALUE! | BW38: =+BT38/$BQ38 -> #REF! | BX38: =+BU38/$BQ38 -> #VALUE!
A39: L5 | B39: L5A-02-01 | C39: ISHAN NETSOL PVT LTD | D39: Rated | E39: Bundled | F39: U space | G39: Uncaged | H39: =IF(F39="Rack","No of Racks",(IF(F39="Space","Sq Ft","U Space"))) -> U Space | I39: 5 | J39: 5 | K39: =I39-J39 -> 0 | L39: 5 | N39: =4166.67/2 -> 2083.335 | O39: =D39 -> Rated | P39: KVA | Q39: 1.25 | R39: 0.78 | S39: =Q39-R39 -> 0.47 | U39: =IF(S39<=0,0,(IF(O39="Rated",(S39+T39)*$W$1,(S39+T39)))) -> 0 | V39: =IF(O39="Rated",Q39*$W$1,Q39) -> 0 | W39: 0.66 | X39: =IF((S39*-1)>0, (S39*-1), 0) -> 0 | Y39: =90000/12 -> 7500 | Z39: =E39 -> Bundled | AF39: =IF(AE39="No of Seats","No of Seats",(IF(AE39="Space","Sq Ft",""))) | AI39: =AG39-AH39 -> 0 | AM39: =N39*L39 -> 10416.675 | AN39: =Y39*X39 -> 0 | AO39: =AD39*AC39*AA39 -> 0 | AP39: =AL39*AJ39 -> 0 | AQ39: =(8334+1000) -> 9334 | AR39: =SUBTOTAL(9,AM39:AQ39) -> 19750.675 | AT39: 121000328 | AZ39: =IF(F39="Rack",AR39/I39,0)+IF(F39="U Space",AR39*40/I39,0)+IF(F39="Space",AR39*30/I39,0) -> 158005.4 | BA39: =+AR39/V39 -> #DIV/0! | BB39: =+($AP39+$AQ39+$AR39-BI39)/$Y39 -> 3.8779567 | BC39: =+($AP39+$AQ39+$AR39-BJ39)/$Y39 -> 3.8779567 | BD39: =+($AP39+$AQ39+IF(E39="Bundled",0,V39*0.85*AA39*AC39*30.5*24)-BK39)/$Y39 -> 1.2445333 | BF39: =+AM39+AN39+AO39 -> 10416.675 | BG39: =+BF39-BH39 -> #REF! | BH39: =IF(E39="Bundled",MIN(V39*$AG$1*(1+#REF!),BF39),AO39) -> #REF! | BI39: =IF($AG39>0,$AG39*$AD$1*$AF$1*(1+$AI$1*(20/$AF$1)/732),$AG$1*W39) -> 0 | BJ39: =IF($AG39>0,$AG39*$AD$1*$AF$1*(1+$AI$1*(20/$AF$1)/732),+$AG$1*(W39+U39)) -> 0 | BK39: =IF(E39="Bundled",$AG$1*V39,$AG$1*V39*0.85) -> 0 | BL39: =+BB39*V39 -> 0 | BM39: =+#REF!*V39 -> #REF! | BN39: =+BG39-BM39 -> #REF! | BO39: =+BH39-BI39 -> #REF! | BP39: =+BN39+BO39 -> #REF! | BQ39: =+V39 -> 0 | BR39: =+BB39 -> 3.8779567 | BS39: =IF(E39="Bundled",BK39-BI39,AO39-BI39) -> 0 | BT39: =IF(E39="Bundled",+(BD39-#REF!)*V39,(AM39+AN39)-V39*#REF!) -> #REF! | BU39: =+BS39+BT39 -> #REF! | BV39: =+BS39/$BT39 -> #REF! | BW39: =+BT39/$BT39 -> #REF! | BX39: =+BU39/$BT39 -> #REF!
A40: L5 | B40: L5A-07-05, L5A-07-06, L5A-07-07, L5A-06-06, L5A-06-07 & L5A-06-08 | C40: AGRICULTURE INSURANCE COMPANY OF INDIA LIMITED | D40: Rated | E40: Metered | F40: Rack | G40: Uncaged | H40: =IF(F40="Rack","No of Racks",(IF(F40="Space","Sq Ft","U Space"))) -> No of Racks | I40: 6 | J40: 6 | K40: =I40-J40 -> 0 | L40: 6 | N40: =260000/12 -> 21666.667 | O40: =D40 -> Rated | P40: KVA | Q40: 45 | R40: 26.34 | S40: =Q40-R40 -> 18.66 | U40: =IF(S40<=0,0,(IF(O40="Rated",(S40+T40)*'Noida-01'!#REF!,(S40+T40)))) -> #REF! | V40: =IF(O40="Rated",Q40*'Noida-01'!#REF!,Q40) -> #REF! | W40: =AD40/31/24 -> 5.3492473 | X40: =IF((S40*-1)>0, (S40*-1), 0) -> 0 | Y40: 0 | Z40: =E40 -> Metered | AA40: 1 | AB40: Fixed | AC40: 14.516 | AD40: 3979.84 | AE40: No of Seats | AF40: =IF(AE40="No of Seats","No of Seats",(IF(AE40="Space","Sq Ft",""))) -> No of Seats | AG40: 1 | AH40: 1 | AI40: =AG40-AH40 -> 0 | AJ40: 1 | AL40: =100000/12 -> 8333.3333 | AM40: =N40*L40 -> 130000 | AN40: =Y40*X40 -> 0 | AO40: =AD40*AC40*AA40 -> 57771.357 | AP40: =AL40*AJ40 -> 8333.3333 | AR40: =SUBTOTAL(9,AM40:AQ40) -> 196104.69 | AT40: 721005172 | AZ40: =IF(F40="Rack",AR40/I40,0)+IF(F40="U Space",AR40*40/I40,0)+IF(F40="Space",AR40*30/I40,0) -> 32684.115 | BA40: =+AR40/V40 -> #REF! | BB40: =+($AM40+$AN40+$AO40-BI40)/$V40 -> #REF! | BC40: =+($AM40+$AN40+$AO40-BJ40)/$V40 -> #REF! | BD40: =+($AM40+$AN40+IF(E40="Bundled",0,V40*0.85*AA40*AC40*30.5*24)-BK40)/$V40 -> #REF! | BF40: =+AM40+AN40+AO40 -> 187771.36 | BG40: =+BF40-BH40 -> 130000 | BH40: =IF(E40="Bundled",MIN(V40*'Noida-01'!#REF!*(1+#REF!),BF40),AO40) -> 57771.357 | BI40: =IF($AD40>0,$AD40*'Noida-01'!#REF!*'Noida-01'!#REF!*(1+'Noida-01'!#REF!*(20/'Noida-01'!#REF!)/732),'Noida-01'!#REF!*W40) -> #REF! | BJ40: =IF($AD40>0,$AD40*'Noida-01'!#REF!*'Noida-01'!#REF!*(1+'Noida-01'!#REF!*(20/'Noida-01'!#REF!)/732),+'Noida-01'!#REF!*(W40+U40)) -> #REF! | BK40: =IF(E40="Bundled",'Noida-01'!#REF!*V40,'Noida-01'!#REF!*V40*0.85) -> #REF! | BL40: =+BB40*V40 -> #REF! | BM40: =+#REF!*V40 -> #REF! | BN40: =+BG40-BM40 -> #REF! | BO40: =+BH40-BI40 -> #REF! | BP40: =+BN40+BO40 -> #REF! | BQ40: =+V40 -> #REF! | BR40: =+BB40 -> #REF! | BS40: =IF(E40="Bundled",BK40-BI40,AO40-BI40) -> #REF! | BT40: =IF(E40="Bundled",+(BD40-#REF!)*V40,(AM40+AN40)-V40*#REF!) -> #REF! | BU40: =+BS40+BT40 -> #REF! | BV40: =+BS40/$BQ40 -> #REF! | BW40: =+BT40/$BQ40 -> #REF! | BX40: =+BU40/$BQ40 -> #REF!
A41: L5 | B41: L5A-07-03 | C41: AGRICULTURE INSURANCE COMPANY OF INDIA LIMITED | D41: Rated | E41: Metered | F41: Rack | G41: Uncaged | H41: =IF(F41="Rack","No of Racks",(IF(F41="Space","Sq Ft","U Space"))) -> No of Racks | I41: 1 | J41: 1 | K41: =I41-J41 -> 0 | L41: 1 | N41: =260000/12 -> 21666.667 | O41: =D41 -> Rated | P41: KVA | Q41: 3 | R41: 8.32 | S41: =Q41-R41 -> -5.32 | U41: =IF(S41<=0,0,(IF(O41="Rated",(S41+T41)*'Noida-01'!#REF!,(S41+T41)))) -> 0 | V41: =IF(O41="Rated",Q41*'Noida-01'!#REF!,Q41) -> #REF! | W41: =AD41/31/24 -> 0.19745968 | X41: =IF((S41*-1)>0, (S41*-1), 0) -> 5.32 | Y41: 0 | Z41: =E41 -> Metered | AA41: 1 | AB41: Fixed | AC41: 14.516 | AD41: 146.91 | AF41: =IF(AE41="No of Seats","No of Seats",(IF(AE41="Space","Sq Ft",""))) | AI41: =AG41-AH41 -> 0 | AM41: =N41*L41 -> 21666.667 | AN41: =Y41*X41 -> 0 | AO41: =AD41*AC41*AA41 -> 2132.5456 | AP41: =AL41*AJ41 -> 0 | AR41: =SUBTOTAL(9,AM41:AQ41) -> 23799.212 | AT41: 121001567 | AZ41: =IF(F41="Rack",AR41/I41,0)+IF(F41="U Space",AR41*40/I41,0)+IF(F41="Space",AR41*30/I41,0) -> 23799.212 | BA41: =+AR41/V41 -> #REF! | BB41: =+($AM41+$AN41+$AO41-BI41)/$V41 -> #REF! | BC41: =+($AM41+$AN41+$AO41-BJ41)/$V41 -> #REF! | BD41: =+($AM41+$AN41+IF(E41="Bundled",0,V41*0.85*AA41*AC41*30.5*24)-BK41)/$V41 -> #REF! | BF41: =+AM41+AN41+AO41 -> 23799.212 | BG41: =+BF41-BH41 -> 21666.667 | BH41: =IF(E41="Bundled",MIN(V41*'Noida-01'!#REF!*(1+#REF!),BF41),AO41) -> 2132.5456 | BI41: =IF($AD41>0,$AD41*'Noida-01'!#REF!*'Noida-01'!#REF!*(1+'Noida-01'!#REF!*(20/'Noida-01'!#REF!)/732),'Noida-01'!#REF!*W41) -> #REF! | BJ41: =IF($AD41>0,$AD41*'Noida-01'!#REF!*'Noida-01'!#REF!*(1+'Noida-01'!#REF!*(20/'Noida-01'!#REF!)/732),+'Noida-01'!#REF!*(W41+U41)) -> #REF! | BK41: =IF(E41="Bundled",'Noida-01'!#REF!*V41,'Noida-01'!#REF!*V41*0.85) -> #REF! | BL41: =+BB41*V41 -> #REF! | BM41: =+#REF!*V41 -> #REF! | BN41: =+BG41-BM41 -> #REF! | BO41: =+BH41-BI41 -> #REF! | BP41: =+BN41+BO41 -> #REF! | BQ41: =+V41 -> #REF! | BR41: =+BB41 -> #REF! | BS41: =IF(E41="Bundled",BK41-BI41,AO41-BI41) -> #REF! | BT41: =IF(E41="Bundled",+(BD41-#REF!)*V41,(AM41+AN41)-V41*#REF!) -> #REF! | BU41: =+BS41+BT41 -> #REF! | BV41: =+BS41/$BQ41 -> #REF! | BW41: =+BT41/$BQ41 -> #REF! | BX41: =+BU41/$BQ41 -> #REF!
A42: L5 | B42: L5B-10-15, L5B-10-16, L5B-10-17, L5B-10-18, L5B-11-15 & L5B-11-16 | C42: AGRICULTURE INSURANCE COMPANY OF INDIA LIMITED | D42: Rated | E42: Metered | F42: Rack | G42: Uncaged | H42: =IF(F42="Rack","No of Racks",(IF(F42="Space","Sq Ft","U Space"))) -> No of Racks | I42: 6 | J42: 6 | K42: =I42-J42 -> 0 | L42: 6 | N42: =260000/12 -> 21666.667 | O42: =D42 -> Rated | P42: KVA | Q42: 50 | R42: 43.1 | S42: =Q42-R42 -> 6.9 | U42: =IF(S42<=0,0,(IF(O42="Rated",(S42+T42)*'Noida-01'!#REF!,(S42+T42)))) -> #REF! | V42: =IF(O42="Rated",Q42*'Noida-01'!#REF!,Q42) -> #REF! | W42: =AD42/31/24 -> 3.2056855 | X42: =IF((S42*-1)>0, (S42*-1), 0) -> 0 | Y42: 0 | Z42: =E42 -> Metered | AA42: 1 | AB42: Fixed | AC42: 14.516 | AD42: 2385.03 | AE42: No of Seats | AF42: =IF(AE42="No of Seats","No of Seats",(IF(AE42="Space","Sq Ft",""))) -> No of Seats | AG42: 1 | AH42: 1 | AI42: =AG42-AH42 -> 0 | AJ42: 1 | AL42: =100000/12 -> 8333.3333 | AM42: =N42*L42 -> 130000 | AN42: =Y42*X42 -> 0 | AO42: =AD42*AC42*AA42 -> 34621.095 | AP42: =AL42*AJ42 -> 8333.3333 | AQ42: 0 | AR42: =SUBTOTAL(9,AM42:AQ42) -> 172954.43 | AT42: 721004381, 721004451 & 721004508 | AZ42: =IF(F42="Rack",AR42/I42,0)+IF(F42="U Space",AR42*40/I42,0)+IF(F42="Space",AR42*30/I42,0) -> 28825.738 | BA42: =+AR42/V42 -> #REF! | BB42: =+($AM42+$AN42+$AO42-BI42)/$V42 -> #REF! | BC42: =+($AM42+$AN42+$AO42-BJ42)/$V42 -> #REF! | BD42: =+($AM42+$AN42+IF(E42="Bundled",0,V42*0.85*AA42*AC42*30.5*24)-BK42)/$V42 -> #REF! | BF42: =+AM42+AN42+AO42 -> 164621.1 | BG42: =+BF42-BH42 -> 130000 | BH42: =IF(E42="Bundled",MIN(V42*'Noida-01'!#REF!*(1+#REF!),BF42),AO42) -> 34621.095 | BI42: =IF($AD42>0,$AD42*'Noida-01'!#REF!*'Noida-01'!#REF!*(1+'Noida-01'!#REF!*(20/'Noida-01'!#REF!)/732),'Noida-01'!#REF!*W42) -> #REF! | BJ42: =IF($AD42>0,$AD42*'Noida-01'!#REF!*'Noida-01'!#REF!*(1+'Noida-01'!#REF!*(20/'Noida-01'!#REF!)/732),+'Noida-01'!#REF!*(W42+U42)) -> #REF! | BK42: =IF(E42="Bundled",'Noida-01'!#REF!*V42,'Noida-01'!#REF!*V42*0.85) -> #REF! | BL42: =+BB42*V42 -> #REF! | BM42: =+#REF!*V42 -> #REF! | BN42: =+BG42-BM42 -> #REF! | BO42: =+BH42-BI42 -> #REF! | BP42: =+BN42+BO42 -> #REF! | BQ42: =+V42 -> #REF! | BR42: =+BB42 -> #REF! | BS42: =IF(E42="Bundled",BK42-BI42,AO42-BI42) -> #REF! | BT42: =IF(E42="Bundled",+(BD42-#REF!)*V42,(AM42+AN42)-V42*#REF!) -> #REF! | BU42: =+BS42+BT42 -> #REF! | BV42: =+BS42/$BQ42 -> #REF! | BW42: =+BT42/$BQ42 -> #REF! | BX42: =+BU42/$BQ42 -> #REF!
A43: L5 | B43: L5A-05-08, L5A-05-09 & L5A-05-10 | C43: DENSO INTERNATIONAL INDIA PVT LTD | D43: Rated | E43: Bundled | F43: Rack | G43: Uncaged | H43: =IF(F43="Rack","No of Racks",(IF(F43="Space","Sq Ft","U Space"))) -> No of Racks | I43: 1 | J43: 1 | K43: 0 | L43: 1 | N43: =((860000+550000+200000)/3)/12 -> 44722.222 | O43: =D43 -> Rated | P43: KVA | Q43: 6 | R43: 6 | S43: =Q43-R43 -> 0 | U43: =IF(S43<=0,0,(IF(O43="Rated",(S43+T43)*$X$1,(S43+T43)))) -> 0 | V43: =IF(O43="Rated",Q43*$X$1,Q43) -> #REF! | W43: 1.87 | X43: =IF((S43*-1)>0, (S43*-1), 0) -> 0 | Y43: =90000/12 -> 7500 | Z43: =E43 -> Bundled | AF43: =IF(AE43="No of Seats","No of Seats",(IF(AE43="Space","Sq Ft",""))) | AI43: =AG43-AH43 -> 0 | AM43: =N43*L43 -> 44722.222 | AN43: =Y43*X43 -> 0 | AO43: =AD43*AC43*AA43 -> 0 | AP43: =AL43*AJ43 -> 0 | AQ43: =(20000+200000+50000+5000)/12 -> 22916.667 | AR43: =SUBTOTAL(9,AM43:AQ43) -> 67638.889 | AT43: Renewal | AZ43: =IF(F43="Rack",AR43/I43,0)+IF(F43="U Space",AR43*40/I43,0)+IF(F43="Space",AR43*30/I43,0) -> 67638.889 | BA43: =+AR43/V43 -> #REF! | BB43: =+($AM43+$AN43+$AO43-BI43)/$V43 -> #REF! | BC43: =+($AM43+$AN43+$AO43-BJ43)/$V43 -> #REF! | BD43: =+($AM43+$AN43+IF(E43="Bundled",0,V43*0.85*AA43*AC43*30.5*24)-BK43)/$V43 -> #REF! | BF43: =+AM43+AN43+AO43 -> 44722.222 | BG43: =+BF43-BH43 -> #REF! | BH43: =IF(E43="Bundled",MIN(V43*$AG$1*(1+#REF!),BF43),AO43) -> #REF! | BI43: =IF($AD43>0,$AD43*$AD$1*$AF$1*(1+$AI$1*(20/$AF$1)/732),$AG$1*W43) -> 0 | BJ43: =IF($AD43>0,$AD43*$AD$1*$AF$1*(1+$AI$1*(20/$AF$1)/732),+$AG$1*(W43+U43)) -> 0 | BK43: =IF(E43="Bundled",$AG$1*V43,$AG$1*V43*0.85) -> #REF! | BL43: =+BB43*V43 -> #REF! | BM43: =+#REF!*V43 -> #REF! | BN43: =+BG43-BM43 -> #REF! | BO43: =+BH43-BI43 -> #REF! | BP43: =+BN43+BO43 -> #REF! | BQ43: =+V43 -> #REF! | BR43: =+BB43 -> #REF! | BS43: =IF(E43="Bundled",BK43-BI43,AO43-BI43) -> #REF! | BT43: =IF(E43="Bundled",+(BD43-#REF!)*V43,(AM43+AN43)-V43*#REF!) -> #REF! | BU43: =+BS43+BT43 -> #REF! | BV43: =+BS43/$BQ43 -> #REF! | BW43: =+BT43/$BQ43 -> #REF! | BX43: =+BU43/$BQ43 -> #REF!
A44: L5 | B44: L5B-01-03 & L5B-01-04 | C44: BHARAT SANCHAR NIGAM LIMITED-HOSTING | D44: Rated | E44: Bundled | F44: Rack | G44: Uncaged | H44: =IF(F44="Rack","No of Racks",(IF(F44="Space","Sq Ft","U Space"))) -> No of Racks | I44: 2 | J44: 2 | K44: =I44-J44 -> 0 | L44: 2 | N44: =600000/12 -> 50000 | O44: =D44 -> Rated | P44: KVA | Q44: 6 | R44: 4.68 | S44: =Q44-R44 -> 1.32 | U44: =IF(S44<=0,0,(IF(O44="Rated",(S44+T44)*'Noida-01'!#REF!,(S44+T44)))) -> #REF! | V44: =IF(O44="Rated",Q44*'Noida-01'!#REF!,Q44) -> #REF! | W44: 0.93 | X44: =IF((S44*-1)>0, (S44*-1), 0) -> 0 | Y44: =98000/12 -> 8166.6667 | Z44: =E44 -> Bundled | AF44: =IF(AE44="No of Seats","No of Seats",(IF(AE44="Space","Sq Ft",""))) | AI44: =AG44-AH44 -> 0 | AM44: =N44*L44 -> 100000 | AN44: =Y44*X44 -> 0 | AO44: =AD44*AC44*AA44 -> 0 | AP44: =AL44*AJ44 -> 0 | AQ44: =(120000)/12 -> 10000 | AR44: =SUBTOTAL(9,AM44:AQ44) -> 110000 | AT44: 721005561 | AZ44: =IF(F44="Rack",AR44/I44,0)+IF(F44="U Space",AR44*40/I44,0)+IF(F44="Space",AR44*30/I44,0) -> 55000 | BA44: =+AR44/V44 -> #REF! | BB44: =+($AM44+$AN44+$AO44-BI44)/$V44 -> #REF! | BC44: =+($AM44+$AN44+$AO44-BJ44)/$V44 -> #REF! | BD44: =+($AM44+$AN44+IF(E44="Bundled",0,V44*0.85*AA44*AC44*30.5*24)-BK44)/$V44 -> #REF! | BF44: =+AM44+AN44+AO44 -> 100000 | BG44: =+BF44-BH44 -> #REF! | BH44: =IF(E44="Bundled",MIN(V44*'Noida-01'!#REF!*(1+#REF!),BF44),AO44) -> #REF! | BI44: =IF($AD44>0,$AD44*'Noida-01'!#REF!*'Noida-01'!#REF!*(1+'Noida-01'!#REF!*(20/'Noida-01'!#REF!)/732),'Noida-01'!#REF!*W44) -> #REF! | BJ44: =IF($AD44>0,$AD44*'Noida-01'!#REF!*'Noida-01'!#REF!*(1+'Noida-01'!#REF!*(20/'Noida-01'!#REF!)/732),+'Noida-01'!#REF!*(W44+U44)) -> #REF! | BK44: =IF(E44="Bundled",'Noida-01'!#REF!*V44,'Noida-01'!#REF!*V44*0.85) -> #REF! | BL44: =+BB44*V44 -> #REF! | BM44: =+#REF!*V44 -> #REF! | BN44: =+BG44-BM44 -> #REF! | BO44: =+BH44-BI44 -> #REF! | BP44: =+BN44+BO44 -> #REF! | BQ44: =+V44 -> #REF! | BR44: =+BB44 -> #REF! | BS44: =IF(E44="Bundled",BK44-BI44,AO44-BI44) -> #REF! | BT44: =IF(E44="Bundled",+(BD44-#REF!)*V44,(AM44+AN44)-V44*#REF!) -> #REF! | BU44: =+BS44+BT44 -> #REF! | BV44: =+BS44/$BQ44 -> #REF! | BW44: =+BT44/$BQ44 -> #REF! | BX44: =+BU44/$BQ44 -> #REF!
A45: L6 | B45: L6-B-33 | C45: STG SOFTWARE SOLUTION PRIVATE LIMITED | D45: Rated | E45: Bundled | F45: Rack | G45: Uncaged | H45: =IF(F45="Rack","No of Racks",(IF(F45="Space","Sq Ft","U Space"))) -> No of Racks | I45: 1 | J45: 1 | K45: 0 | L45: 1 | O45: =D45 -> Rated | P45: KVA | Q45: 12 | R45: 7.31 | S45: =Q45-R45 -> 4.69 | U45: =IF(S45<=0,0,(IF(O45="Rated",(S45+T45)*'Noida-01'!#REF!,(S45+T45)))) -> #REF! | V45: =IF(O45="Rated",Q45*'Noida-01'!#REF!,Q45) -> #REF! | W45: =AD45/30/24 -> 6.3906944 | Z45: =E45 -> Bundled | AD45: 4601.3 | BK45: =IF(E45="Bundled",'Noida-01'!#REF!*V45,'Noida-01'!#REF!*V45*0.85) -> #REF! | BQ45: =+V45 -> #REF!
A46: L5 | B46: L5A-01-10 | C46: PEERCAST TELECOM INDIA PRIVATE LIMITED | D46: Subscribed | E46: Metered | F46: Rack | G46: Uncaged | H46: =IF(F46="Rack","No of Racks",(IF(F46="Space","Sq Ft","U Space"))) -> No of Racks | I46: 1 | J46: 1 | K46: =I46-J46 -> 0 | L46: 1 | O46: =D46 -> Subscribed | P46: KW | Q46: 3 | R46: =W46 -> 1.0707639 | S46: =Q46-R46 -> 1.9292361 | U46: =IF(S46<=0,0,(IF(O46="Rated",(S46+T46)*'Noida-01'!#REF!,(S46+T46)))) -> 1.9292361 | V46: =IF(O46="Rated",Q46*'Noida-01'!#REF!,Q46) -> 3 | W46: =AD46/30/24 -> 1.0707639 | X46: =IF((S46*-1)>0, (S46*-1), 0) -> 0 | Z46: =E46 -> Metered | AA46: 1 | AB46: Fixed | AD46: 770.95 | AF46: =IF(AE46="No of Seats","No of Seats",(IF(AE46="Space","Sq Ft",""))) | AI46: =AG46-AH46 -> 0 | AN46: =Y46*X46 -> 0 | AO46: =AD46*AC46*AA46 -> 0 | AP46: =AL46*AJ46 -> 0 | AR46: =SUBTOTAL(9,AM46:AQ46) -> 0 | AZ46: =IF(F46="Rack",AR46/I46,0)+IF(F46="U Space",AR46*40/I46,0)+IF(F46="Space",AR46*30/I46,0) -> 0 | BA46: =+AR46/V46 -> 0 | BB46: =+($AM46+$AN46+$AO46-BI46)/$V46 -> #REF! | BF46: =+AM46+AN46+AO46 -> 0 | BG46: =+BF46-BH46 -> 0 | BH46: =IF(E46="Bundled",MIN(V46*'Noida-01'!#REF!*(1+#REF!),BF46),AO46) -> 0 | BI46: =IF($AD46>0,$AD46*'Noida-01'!#REF!*'Noida-01'!#REF!*(1+'Noida-01'!#REF!*(20/'Noida-01'!#REF!)/732),'Noida-01'!#REF!*W46) -> #REF! | BL46: =+BB46*V46 -> #REF! | BM46: =+#REF!*V46 -> #REF! | BN46: =+BG46-BM46 -> #REF! | BO46: =+BH46-BI46 -> #REF! | BP46: =+BN46+BO46 -> #REF! | BQ46: =+V46 -> 3 | BR46: =+BB46 -> #REF! | BS46: =IF(E46="Bundled",BK46-BI46,AO46-BI46) -> #REF! | BT46: =IF(E46="Bundled",+(BD46-#REF!)*V46,(AM46+AN46)-V46*#REF!) -> #REF! | BU46: =+BS46+BT46 -> #REF! | BV46: =+BS46/$BQ46 -> #REF! | BW46: =+BT46/$BQ46 -> #REF! | BX46: =+BU46/$BQ46 -> #REF!
A47: L7 | B47: L7-F-18 | C47: DELACON TECH SOLUTIONS PRIVATE LIMITED | D47: Rated | E47: Bundled | F47: U space | G47: Uncaged | H47: =IF(F47="Rack","No of Racks",(IF(F47="Space","Sq Ft","U Space"))) -> U Space | I47: 6 | J47: 6 | K47: 0 | L47: 6 | O47: Rated | P47: KVA | Q47: 1.5 | R47: 2.1 | S47: =Q47-R47 -> -0.6 | U47: =IF(S47<=0,0,(IF(O47="Rated",(S47+T47)*$X$1,(S47+T47)))) -> 0 | V47: =IF(O47="Rated",Q47*$X$1,Q47) -> #REF! | X47: =IF((S47*-1)>0, (S47*-1), 0) -> 0.6
A48: L6 | B48: L6-F-24 | C48: REISNET BROADBAND PRIVATE LIMITED ( 5U TO 8U) | D48: Rated | E48: Bundled | F48: U space | G48: Uncaged | H48: =IF(F48="Rack","No of Racks",(IF(F48="Space","Sq Ft","U Space"))) -> U Space | I48: 4 | J48: 4 | K48: =I48-J48 -> 0 | L48: 4 | O48: =D48 -> Rated | P48: KVA | Q48: 1 | R48: 0.3 | S48: =Q48-R48 -> 0.7 | U48: =IF(S48<=0,0,(IF(O48="Rated",(S48+T48)*$X$1,(S48+T48)))) -> #REF! | V48: =IF(O48="Rated",Q48*$X$1,Q48) -> #REF! | X48: =IF((S48*-1)>0, (S48*-1), 0) -> 0 | Z48: =E48 -> Bundled | BK48: =IF(E48="Bundled",$AG$1*V48,$AG$1*V48*0.85) -> #REF! | BM48: =+#REF!*V48 -> #REF! | BQ48: =+V48 -> #REF!
A49: L1 | B49: NOI-TB-L1-A-15 TO NOI-TB-L1-A-17 | C49: ACRO ENGINEERING | D49: Subscribed | E49: Metered | F49: Rack | G49: Uncaged | H49: Racks | I49: 3 | J49: 3 | K49: 0 | L49: 3 | N49: 474999 | O49: =D49 -> Subscribed | P49: KW | Q49: 27 | R49: =W49 -> 0 | S49: =Q49-R49 -> 27 | U49: =IF(S49<=0,0,(IF(O49="Rated",(S49+T49)*#REF!,(S49+T49)))) -> 27 | V49: =IF(O49="Rated",Q49*#REF!,Q49) -> 27 | W49: =AD49/28/24 -> 0 | X49: =IF((S49*-1)>0, (S49*-1), 0) -> 0 | Z49: Bundal Metered | AD49: 0 | BY49: Noida -02

Sheet Noida-01
A1: Floor | B1: Floor / Module | C1: Customer Name | D1: RHS/SH | E1: Sitting Space (Subscription) | F1: IR DATE | G1: Power Subscription Model (Rated/Subscribed) | H1: Power Usage Model (Bundled / Metered) | I1: Subscription Mode | J1: Caged /Uncaged | K1: UoM | L1: Subscription | M1: In Use | N1: Yet to be given/ | O1: Billed | P1: Reserved Capacity if any (Non-Billable) | Q1: Per Unit rate (MRC) | R1: Subscription Model | S1: UoM | T1: Total Capacity Purchased | U1: Capacity in Use | V1: Capacity to be given | W1: Reserved Capacity if any | X1: Subscribed Capacity to be given in KW | Y1: "Allocated" Capacity in KW (for KVA subscribed customer 50% diversity is used to make kW ) | Z1: DC NW Infra | AA1: Billable Additional Capacity | AB1: Additional Capacity Charges (MRC) | AC1: Usage Model | AD1: Multiplier | AE1: Uit rate Model (Fixed/Variable) | AF1: Unit Rate (per KW-HR) | AG1: No Of Units (KW-HR/ Month | AH1: Subscription Model | AI1: UoM | AJ1: Subscription | AK1: In Use | AL1: Yet to be given | AM1: Billed | AN1: Reserved Capacity if any | AO1: Per Unit rate | AP1: Space revenue including capacity | AQ1: Additional Capacity Revenue | AR1: Power Usage revenue | AS1: Seating Space | AT1: Any Other Items | AU1: Total Revenue | AV1: Billing Frequency | AW1: Sales Order ref No | AX1: Contract Start Date | AY1: Term of Contract (No of Years) | AZ1: Current Exiry Date | BA1: Remarks if any | BC1: Avg revenue /Rack /Month | BD1: Avg revenue /KW /Month | BE1: Net Revenue / Resvd KW | BF1: Proj Net Revenue / Resvd KW | BG1: Sold Net Revenue / Resvd KW | BI1: Total Rev (Cap + Power) | BJ1: Capacity Revenue | BK1: Power Revenue | BL1: Cost of Power @ Act Usage | BM1: Proj Cost of Power @ Reserv Cap | BN1: Cost of Power @ Design Use | BO1: Net Rev Total | BP1: Target Capacity Revenue | BQ1: Capacity Surplus/Leakage | BR1: Power Surplus/Leakage | BS1: Contribution to Target | BT1: KW | BV1: Power Surplus/Leakage | BW1: Capacity Surplus/Leakage | BX1: Total Surplus/Leakage | BY1: Power Surplus/Leakage / KW | BZ1: Capacity Surplus/Leakage / KW | CA1: Total Surplus/Leakage / KW
A2: L5 | B2: L5A-01-02 | C2: V2 RETAIL LTD | D2: NO | G2: Rated | H2: Bundled | I2: Rack | J2: Uncaged | K2: =IF(I2="Rack","No of Racks",(IF(I2="Space","Sq Ft","U Space"))) -> No of Racks | L2: 1 | M2: 1 | N2: =L2-M2 -> 0 | O2: 1 | Q2: =519750/12 -> 43312.5 | R2: =G2 -> Rated | S2: KVA | T2: 8.93 | U2: 9.77 | V2: =T2-U2 -> -0.84 | X2: =IF(V2<=0,0,(IF(R2="Rated",(V2+W2)*#REF!,(V2+W2)))) -> 0 | Y2: =IF(R2="Rated",T2*#REF!,T2) -> #REF! | Z2: =AG2/28/24 -> 5.1572024 | AA2: =IF((V2*-1)>0, (V2*-1), 0) -> 0.84 | AB2: =100000/12 -> 8333.3333 | AC2: =H2 -> Bundled | AG2: 3465.64 | AI2: =IF(AH2="No of Seats","No of Seats",(IF(AH2="Space","Sq Ft",""))) | AL2: =AJ2-AK2 -> 0 | AP2: =Q2*O2 -> 43312.5 | AQ2: =AB2*AA2 -> 7000 | AR2: =AG2*AF2*AD2 -> 0 | AS2: =AO2*AM2 -> 0 | AT2: =(593000+30000)/12 -> 51916.667 | AU2: =SUBTOTAL(9,AP2:AT2) -> 102229.17 | AW2: Renewal | BC2: =IF(I2="Rack",AU2/L2,0)+IF(I2="U Space",AU2*40/L2,0)+IF(I2="Space",AU2*30/L2,0) -> 102229.17 | BD2: =+AU2/Y2 -> #REF! | BE2: =+($AP2+$AQ2+$AR2-BL2)/$Y2 -> #REF! | BF2: =+($AP2+$AQ2+$AR2-BM2)/$Y2 -> #REF! | BG2: =+($AP2+$AQ2+IF(H2="Bundled",0,Y2*0.85*AD2*AF2*30.5*24)-BN2)/$Y2 -> #REF! | BI2: =+AP2+AQ2+AR2 -> 50312.5 | BJ2: =+BI2-BK2 -> #REF! | BK2: =IF(H2="Bundled",MIN(Y2*#REF!*(1+#REF!),BI2),AR2) -> #REF! | BL2: =IF($AG2>0,$AG2*#REF!*#REF!*(1+#REF!*(20/#REF!)/732),#REF!*Z2) -> #REF! | BM2: =IF($AG2>0,$AG2*#REF!*#REF!*(1+#REF!*(20/#REF!)/732),+#REF!*(Z2+X2)) -> #REF! | BN2: =IF(H2="Bundled",#REF!*Y2,#REF!*Y2*0.85) -> #REF! | BO2: =+BE2*Y2 -> #REF! | BP2: =+#REF!*Y2 -> #REF! | BQ2: =+BJ2-BP2 -> #REF! | BR2: =+BK2-BL2 -> #REF! | BS2: =+BQ2+BR2 -> #REF! | BT2: =+Y2 -> #REF! | BU2: =+BE2 -> #REF! | BV2: =IF(H2="Bundled",BN2-BL2,AR2-BL2) -> #REF! | BW2: =IF(H2="Bundled",+(BG2-#REF!)*Y2,(AP2+AQ2)-Y2*#REF!) -> #REF! | BX2: =+BV2+BW2 -> #REF! | BY2: =+BV2/$BT2 -> #REF! | BZ2: =+BW2/$BT2 -> #REF! | CA2: =+BX2/$BT2 -> #REF!
A3: L5 | B3: L5A-06-10 | C3: V2 RETAIL LTD | D3: NO | G3: Rated | H3: Bundled | I3: Rack | J3: Uncaged | K3: =IF(I3="Rack","No of Racks",(IF(I3="Space","Sq Ft","U Space"))) -> No of Racks | L3: 1 | M3: 1 | N3: =L3-M3 -> 0 | O3: 1 | Q3: =1020000/12 -> 85000 | R3: =G3 -> Rated | S3: KVA | T3: 10 | U3: 7.46 | V3: =T3-U3 -> 2.54 | X3: =IF(V3<=0,0,(IF(R3="Rated",(V3+W3)*#REF!,(V3+W3)))) -> #REF! | Y3: =IF(R3="Rated",T3*#REF!,T3) -> #REF! | Z3: =AG3/28/24 -> 2.9673363 | AA3: =IF((V3*-1)>0, (V3*-1), 0) -> 0 | AB3: =90000/12 -> 7500 | AC3: =H3 -> Bundled | AG3: 1994.05 | AI3: =IF(AH3="No of Seats","No of Seats",(IF(AH3="Space","Sq Ft",""))) | AL3: =AJ3-AK3 -> 0 | AP3: =Q3*O3 -> 85000 | AQ3: =AB3*AA3 -> 0 | AR3: =AG3*AF3*AD3 -> 0 | AS3: =AO3*AM3 -> 0 | AU3: =SUBTOTAL(9,AP3:AT3) -> 85000 | AW3: 721006057 | BC3: =IF(I3="Rack",AU3/L3,0)+IF(I3="U Space",AU3*40/L3,0)+IF(I3="Space",AU3*30/L3,0) -> 85000 | BD3: =+AU3/Y3 -> #REF! | BE3: =+($AP3+$AQ3+$AR3-BL3)/$Y3 -> #REF! | BF3: =+($AP3+$AQ3+$AR3-BM3)/$Y3 -> #REF! | BG3: =+($AP3+$AQ3+IF(H3="Bundled",0,Y3*0.85*AD3*AF3*30.5*24)-BN3)/$Y3 -> #REF! | BI3: =+AP3+AQ3+AR3 -> 85000 | BJ3: =+BI3-BK3 -> #REF! | BK3: =IF(H3="Bundled",MIN(Y3*#REF!*(1+#REF!),BI3),AR3) -> #REF! | BL3: =IF($AG3>0,$AG3*#REF!*#REF!*(1+#REF!*(20/#REF!)/732),#REF!*Z3) -> #REF! | BM3: =IF($AG3>0,$AG3*#REF!*#REF!*(1+#REF!*(20/#REF!)/732),+#REF!*(Z3+X3)) -> #REF! | BN3: =IF(H3="Bundled",#REF!*Y3,#REF!*Y3*0.85) -> #REF! | BO3: =+BE3*Y3 -> #REF! | BP3: =+#REF!*Y3 -> #REF! | BQ3: =+BJ3-BP3 -> #REF! | BR3: =+BK3-BL3 -> #REF! | BS3: =+BQ3+BR3 -> #REF! | BT3: =+Y3 -> #REF! | BU3: =+BE3 -> #REF! | BV3: =IF(H3="Bundled",BN3-BL3,AR3-BL3) -> #REF! | BW3: =IF(H3="Bundled",+(BG3-#REF!)*Y3,(AP3+AQ3)-Y3*#REF!) -> #REF! | BX3: =+BV3+BW3 -> #REF! | BY3: =+BV3/$BT3 -> #REF! | BZ3: =+BW3/$BT3 -> #REF! | CA3: =+BX3/$BT3 -> #REF!
A4: L5 | B4: L5A-02-08 | C4: EXCITEL BROADBAND PVT LTD | D4: YES | G4: Rated | H4: Metered | I4: Rack | J4: Uncaged | K4: =IF(I4="Rack","No of Racks",(IF(I4="Space","Sq Ft","U Space"))) -> No of Racks | L4: 1 | M4: 1 | N4: =L4-M4 -> 0 | O4: 1 | Q4: =300000/12 -> 25000 | R4: =G4 -> Rated | S4: KVA | T4: 3 | U4: 4.07 | V4: =T4-U4 -> -1.07 | X4: =IF(V4<=0,0,(IF(R4="Rated",(V4+W4)*#REF!,(V4+W4)))) -> 0 | Y4: =IF(R4="Rated",T4*#REF!,T4) -> #REF! | Z4: =AG4/28/24 -> 1.3959524 | AA4: =IF((V4*-1)>0, (V4*-1), 0) -> 1.07 | AB4: 0 | AC4: =H4 -> Metered | AD4: 1 | AE4: Fixed | AF4: 19 | AG4: 938.08 | AI4: =IF(AH4="No of Seats","No of Seats",(IF(AH4="Space","Sq Ft",""))) | AL4: =AJ4-AK4 -> 0 | AP4: =Q4*O4 -> 25000 | AQ4: =AB4*AA4 -> 0 | AR4: =AG4*AF4*AD4 -> 17823.52 | AS4: =AO4*AM4 -> 0 | AT4: 2083.3333 | AU4: =SUBTOTAL(9,AP4:AT4) -> 44906.853 | AW4: 721004322 | BC4: =IF(I4="Rack",AU4/L4,0)+IF(I4="U Space",AU4*40/L4,0)+IF(I4="Space",AU4*30/L4,0) -> 44906.853 | BD4: =+AU4/Y4 -> #REF! | BE4: =+($AP4+$AQ4+$AR4-BL4)/$Y4 -> #REF! | BF4: =+($AP4+$AQ4+$AR4-BM4)/$Y4 -> #REF! | BG4: =+($AP4+$AQ4+IF(H4="Bundled",0,Y4*0.85*AD4*AF4*30.5*24)-BN4)/$Y4 -> #REF! | BI4: =+AP4+AQ4+AR4 -> 42823.52 | BJ4: =+BI4-BK4 -> 25000 | BK4: =IF(H4="Bundled",MIN(Y4*#REF!*(1+#REF!),BI4),AR4) -> 17823.52 | BL4: =IF($AG4>0,$AG4*#REF!*#REF!*(1+#REF!*(20/#REF!)/732),#REF!*Z4) -> #REF! | BM4: =IF($AG4>0,$AG4*#REF!*#REF!*(1+#REF!*(20/#REF!)/732),+#REF!*(Z4+X4)) -> #REF! | BN4: =IF(H4="Bundled",#REF!*Y4,#REF!*Y4*0.85) -> #REF! | BO4: =+BE4*Y4 -> #REF! | BP4: =+#REF!*Y4 -> #REF! | BQ4: =+BJ4-BP4 -> #REF! | BR4: =+BK4-BL4 -> #REF! | BS4: =+BQ4+BR4 -> #REF! | BT4: =+Y4 -> #REF! | BU4: =+BE4 -> #REF! | BV4: =IF(H4="Bundled",BN4-BL4,AR4-BL4) -> #REF! | BW4: =IF(H4="Bundled",+(BG4-#REF!)*Y4,(AP4+AQ4)-Y4*#REF!) -> #REF! | BX4: =+BV4+BW4 -> #REF! | BY4: =+BV4/$BT4 -> #REF! | BZ4: =+BW4/$BT4 -> #REF! | CA4: =+BX4/$BT4 -> #REF!
A5: L5 | B5: L5A-02-11 & L5A-02-12 | C5: NEEL METAL PRODUCTS LTD(JBM) | D5: YES | G5: Subscribed | H5: Metered | I5: Rack | J5: Uncaged | K5: =IF(I5="Rack","No of Racks",(IF(I5="Space","Sq Ft","U Space"))) -> No of Racks | L5: 2 | M5: 2 | N5: =L5-M5 -> 0 | O5: 2 | Q5: =(798000+760000)/2/12 -> 64916.667 | R5: =G5 -> Subscribed | S5: KW | T5: 7.5 | U5: =Z5 -> 5.6367113 | V5: =T5-U5 -> 1.8632887 | X5: =IF(V5<=0,0,(IF(R5="Rated",(V5+W5)*#REF!,(V5+W5)))) -> 1.8632887 | Y5: =IF(R5="Rated",T5*#REF!,T5) -> 7.5 | Z5: =AG5/28/24 -> 5.6367113 | AA5: =IF((V5*-1)>0, (V5*-1), 0) -> 0 | AB5: =110000/12 -> 9166.6667 | AC5: =H5 -> Metered | AD5: 1 | AE5: Fixed | AF5: 19.5 | AG5: 3787.87 | AI5: =IF(AH5="No of Seats","No of Seats",(IF(AH5="Space","Sq Ft",""))) | AL5: =AJ5-AK5 -> 0 | AP5: =Q5*O5 -> 129833.33 | AQ5: =AB5*AA5 -> 0 | AR5: =AG5*AF5*AD5 -> 73863.465 | AS5: =AO5*AM5 -> 0 | AT5: =(15450)/12 -> 1287.5 | AU5: =SUBTOTAL(9,AP5:AT5) -> 204984.3 | AW5: Renewal | BC5: =IF(I5="Rack",AU5/L5,0)+IF(I5="U Space",AU5*40/L5,0)+IF(I5="Space",AU5*30/L5,0) -> 102492.15 | BD5: =+AU5/Y5 -> 27331.24 | BE5: =+($AP5+$AQ5+$AR5-BL5)/$Y5 -> #REF! | BF5: =+($AP5+$AQ5+$AR5-BM5)/$Y5 -> #REF! | BG5: =+($AP5+$AQ5+IF(H5="Bundled",0,Y5*0.85*AD5*AF5*30.5*24)-BN5)/$Y5 -> #REF! | BI5: =+AP5+AQ5+AR5 -> 203696.8 | BJ5: =+BI5-BK5 -> 129833.33 | BK5: =IF(H5="Bundled",MIN(Y5*#REF!*(1+#REF!),BI5),AR5) -> 73863.465 | BL5: =IF($AG5>0,$AG5*#REF!*#REF!*(1+#REF!*(20/#REF!)/732),#REF!*Z5) -> #REF! | BM5: =IF($AG5>0,$AG5*#REF!*#REF!*(1+#REF!*(20/#REF!)/732),+#REF!*(Z5+X5)) -> #REF! | BN5: =IF(H5="Bundled",#REF!*Y5,#REF!*Y5*0.85) -> #REF! | BO5: =+BE5*Y5 -> #REF! | BP5: =+#REF!*Y5 -> #REF! | BQ5: =+BJ5-BP5 -> #REF! | BR5: =+BK5-BL5 -> #REF! | BS5: =+BQ5+BR5 -> #REF! | BT5: =+Y5 -> 7.5 | BU5: =+BE5 -> #REF! | BV5: =IF(H5="Bundled",BN5-BL5,AR5-BL5) -> #REF! | BW5: =IF(H5="Bundled",+(BG5-#REF!)*Y5,(AP5+AQ5)-Y5*#REF!) -> #REF! | BX5: =+BV5+BW5 -> #REF! | BY5: =+BV5/$BT5 -> #REF! | BZ5: =+BW5/$BT5 -> #REF! | CA5: =+BX5/$BT5 -> #REF! | CB5: not able to trace in inventory or Oracle.
A6: L5 | B6: L5A-03-10 | C6: NEEL METAL PRODUCTS LTD(JBM) | D6: YES | G6: Subscribed | H6: Metered | I6: Rack | J6: Uncaged | K6: =IF(I6="Rack","No of Racks",(IF(I6="Space","Sq Ft","U Space"))) -> No of Racks | L6: 1 | M6: 0 | N6: =L6-M6 -> 1 | O6: 0 | R6: =G6 -> Subscribed | S6: KW | T6: 3 | V6: =T6-U6 -> 3 | X6: =IF(V6<=0,0,(IF(R6="Rated",(V6+W6)*#REF!,(V6+W6)))) -> 3 | Y6: =IF(R6="Rated",T6*#REF!,T6) -> 3 | AC6: =H6 -> Metered | BN6: =IF(H6="Bundled",#REF!*Y6,#REF!*Y6*0.85) -> #REF! | BT6: =+Y6 -> 3
A7: L5 | B7: L5A-02-13 | C7: PRECIOUS NETCOM PVT LTD | D7: NO | G7: Subscribed | H7: Metered | I7: Rack | J7: Uncaged | K7: =IF(I7="Rack","No of Racks",(IF(I7="Space","Sq Ft","U Space"))) -> No of Racks | L7: 1 | M7: 1 | N7: =L7-M7 -> 0 | O7: 1 | Q7: =270000/12 -> 22500 | R7: =G7 -> Subscribed | S7: KW | T7: 3 | U7: =Z7 -> 2.9718304 | V7: =T7-U7 -> 0.028169643 | X7: =IF(V7<=0,0,(IF(R7="Rated",(V7+W7)*#REF!,(V7+W7)))) -> 0.028169643 | Y7: =IF(R7="Rated",T7*#REF!,T7) -> 3 | Z7: =AG7/28/24 -> 2.9718304 | AA7: =IF((V7*-1)>0, (V7*-1), 0) -> 0 | AB7: =100000/12 -> 8333.3333 | AC7: =H7 -> Metered | AD7: 1 | AE7: Fixed | AF7: 17 | AG7: 1997.07 | AI7: =IF(AH7="No of Seats","No of Seats",(IF(AH7="Space","Sq Ft",""))) | AL7: =AJ7-AK7 -> 0 | AP7: =Q7*O7 -> 22500 | AQ7: =AB7*AA7 -> 0 | AR7: =AG7*AF7*AD7 -> 33950.19 | AS7: =AO7*AM7 -> 0 | AT7: =107880/12 -> 8990 | AU7: =SUBTOTAL(9,AP7:AT7) -> 65440.19 | AW7: Renewal | BC7: =IF(I7="Rack",AU7/L7,0)+IF(I7="U Space",AU7*40/L7,0)+IF(I7="Space",AU7*30/L7,0) -> 65440.19 | BD7: =+AU7/Y7 -> 21813.397 | BE7: =+($AP7+$AQ7+$AR7-BL7)/$Y7 -> #REF! | BF7: =+($AP7+$AQ7+$AR7-BM7)/$Y7 -> #REF! | BG7: =+($AP7+$AQ7+IF(H7="Bundled",0,Y7*0.85*AD7*AF7*30.5*24)-BN7)/$Y7 -> #REF! | BI7: =+AP7+AQ7+AR7 -> 56450.19 | BJ7: =+BI7-BK7 -> 22500 | BK7: =IF(H7="Bundled",MIN(Y7*#REF!*(1+#REF!),BI7),AR7) -> 33950.19 | BL7: =IF($AG7>0,$AG7*#REF!*#REF!*(1+#REF!*(20/#REF!)/732),#REF!*Z7) -> #REF! | BM7: =IF($AG7>0,$AG7*#REF!*#REF!*(1+#REF!*(20/#REF!)/732),+#REF!*(Z7+X7)) -> #REF! | BN7: =IF(H7="Bundled",#REF!*Y7,#REF!*Y7*0.85) -> #REF! | BO7: =+BE7*Y7 -> #REF! | BP7: =+#REF!*Y7 -> #REF! | BQ7: =+BJ7-BP7 -> #REF! | BR7: =+BK7-BL7 -> #REF! | BS7: =+BQ7+BR7 -> #REF! | BT7: =+Y7 -> 3 | BU7: =+BE7 -> #REF! | BV7: =IF(H7="Bundled",BN7-BL7,AR7-BL7) -> #REF! | BW7: =IF(H7="Bundled",+(BG7-#REF!)*Y7,(AP7+AQ7)-Y7*#REF!) -> #REF! | BX7: =+BV7+BW7 -> #REF! | BY7: =+BV7/$BT7 -> #REF! | BZ7: =+BW7/$BT7 -> #REF! | CA7: =+BX7/$BT7 -> #REF!
A8: L5 | B8: L5A-04-12 | C8: PERFECT INTERNET PVT LTD | D8: YES | G8: Subscribed | H8: Metered | I8: Rack | J8: Uncaged | K8: =IF(I8="Rack","No of Racks",(IF(I8="Space","Sq Ft","U Space"))) -> No of Racks | L8: 1 | M8: 1 | N8: =L8-M8 -> 0 | O8: 1 | Q8: =(264600)/12 -> 22050 | R8: =G8 -> Subscribed | S8: KW | T8: 3 | U8: =Z8 -> 2.811622 | V8: =T8-U8 -> 0.18837798 | X8: =IF(V8<=0,0,(IF(R8="Rated",(V8+W8)*#REF!,(V8+W8)))) -> 0.18837798 | Y8: =IF(R8="Rated",T8*#REF!,T8) -> 3 | Z8: =AG8/28/24 -> 2.811622 | AA8: =IF((V8*-1)>0, (V8*-1), 0) -> 0 | AB8: =80000/12 -> 6666.6667 | AC8: =H8 -> Metered | AD8: 1 | AE8: Fixed | AF8: 17 | AG8: 1889.41 | AI8: =IF(AH8="No of Seats","No of Seats",(IF(AH8="Space","Sq Ft",""))) | AL8: =AJ8-AK8 -> 0 | AP8: =Q8*O8 -> 22050 | AQ8: =AB8*AA8 -> 0 | AR8: =AG8*AF8*AD8 -> 32119.97 | AS8: =AO8*AM8 -> 0 | AT8: =(220500+11025)/12 -> 19293.75 | AU8: =SUBTOTAL(9,AP8:AT8) -> 73463.72 | AW8: Renewal | BC8: =IF(I8="Rack",AU8/L8,0)+IF(I8="U Space",AU8*40/L8,0)+IF(I8="Space",AU8*30/L8,0) -> 73463.72 | BD8: =+AU8/Y8 -> 24487.907 | BE8: =+($AP8+$AQ8+$AR8-BL8)/$Y8 -> #REF! | BF8: =+($AP8+$AQ8+$AR8-BM8)/$Y8 -> #REF! | BG8: =+($AP8+$AQ8+IF(H8="Bundled",0,Y8*0.85*AD8*AF8*30.5*24)-BN8)/$Y8 -> #REF! | BI8: =+AP8+AQ8+AR8 -> 54169.97 | BJ8: =+BI8-BK8 -> 22050 | BK8: =IF(H8="Bundled",MIN(Y8*#REF!*(1+#REF!),BI8),AR8) -> 32119.97 | BL8: =IF($AG8>0,$AG8*#REF!*#REF!*(1+#REF!*(20/#REF!)/732),#REF!*Z8) -> #REF! | BM8: =IF($AG8>0,$AG8*#REF!*#REF!*(1+#REF!*(20/#REF!)/732),+#REF!*(Z8+X8)) -> #REF! | BN8: =IF(H8="Bundled",#REF!*Y8,#REF!*Y8*0.85) -> #REF! | BO8: =+BE8*Y8 -> #REF! | BP8: =+#REF!*Y8 -> #REF! | BQ8: =+BJ8-BP8 -> #REF! | BR8: =+BK8-BL8 -> #REF! | BS8: =+BQ8+BR8 -> #REF! | BT8: =+Y8 -> 3 | BU8: =+BE8 -> #REF! | BV8: =IF(H8="Bundled",BN8-BL8,AR8-BL8) -> #REF! | BW8: =IF(H8="Bundled",+(BG8-#REF!)*Y8,(AP8+AQ8)-Y8*#REF!) -> #REF! | BX8: =+BV8+BW8 -> #REF! | BY8: =+BV8/$BT8 -> #REF! | BZ8: =+BW8/$BT8 -> #REF! | CA8: =+BX8/$BT8 -> #REF! | CB8: Changed to reflect renewed rate and also the rate for 4 additional racks (total 5 racks). Pls confirm if this is correct.
A9: L5 | B9: Server Hall L5A | C9: GODFREY PHILLIPS INDIA LIMITED | D9: MANAGE SERVICES | G9: Rated | H9: Bundled | I9: Space | J9: Caged | K9: Sq Ft | L9: 224 | M9: 224 | N9: 0 | O9: 3 | Q9: =(595000)/12 -> 49583.333 | R9: =G9 -> Rated | S9: KVA | T9: 15.39 | U9: 15.73 | V9: =T9-U9 -> -0.34 | X9: =IF(V9<=0,0,(IF(R9="Rated",(V9+W9)*#REF!,(V9+W9)))) -> 0 | Y9: =IF(R9="Rated",T9*#REF!,T9) -> #REF! | Z9: 3.48 | AA9: =IF((V9*-1)>0, (V9*-1), 0) -> 0.34 | AB9: =109945/12 -> 9162.0833 | AC9: =H9 -> Bundled | AH9: No of Seats | AI9: =IF(AH9="No of Seats","No of Seats",(IF(AH9="Space","Sq Ft",""))) -> No of Seats | AJ9: 1 | AK9: 1 | AL9: =AJ9-AK9 -> 0 | AM9: 1 | AO9: =102000/12 -> 8500 | AP9: =Q9*O9 -> 148750 | AQ9: =AB9*AA9 -> 3115.1083 | AR9: =AG9*AF9*AD9 -> 0 | AS9: =AO9*AM9 -> 8500 | AT9: =(300000+37000+42000)/12 -> 31583.333 | AU9: =SUBTOTAL(9,AP9:AT9) -> 191948.44 | AW9: Renewal | BC9: =IF(I9="Rack",AU9/L9,0)+IF(I9="U Space",AU9*40/L9,0)+IF(I9="Space",AU9*30/L9,0) -> 25707.381 | BD9: =+AU9/Y9 -> #REF! | BE9: =+($AP9+$AQ9+$AR9-BL9)/$Y9 -> #REF! | BF9: =+($AP9+$AQ9+$AR9-BM9)/$Y9 -> #REF! | BG9: =+($AP9+$AQ9+IF(H9="Bundled",0,Y9*0.85*AD9*AF9*30.5*24)-BN9)/$Y9 -> #REF! | BI9: =+AP9+AQ9+AR9 -> 151865.11 | BJ9: =+BI9-BK9 -> #REF! | BK9: =IF(H9="Bundled",MIN(Y9*#REF!*(1+#REF!),BI9),AR9) -> #REF! | BL9: =IF($AG9>0,$AG9*#REF!*#REF!*(1+#REF!*(20/#REF!)/732),#REF!*Z9) -> #REF! | BM9: =IF($AG9>0,$AG9*#REF!*#REF!*(1+#REF!*(20/#REF!)/732),+#REF!*(Z9+X9)) -> #REF! | BN9: =IF(H9="Bundled",#REF!*Y9,#REF!*Y9*0.85) -> #REF! | BO9: =+BE9*Y9 -> #REF! | BP9: =+#REF!*Y9 -> #REF! | BQ9: =+BJ9-BP9 -> #REF! | BR9: =+BK9-BL9 -> #REF! | BS9: =+BQ9+BR9 -> #REF! | BT9: =+Y9 -> #REF! | BU9: =+BE9 -> #REF! | BV9: =IF(H9="Bundled",BN9-BL9,AR9-BL9) -> #REF! | BW9: =IF(H9="Bundled",+(BG9-#REF!)*Y9,(AP9+AQ9)-Y9*#REF!) -> #REF! | BX9: =+BV9+BW9 -> #REF! | BY9: =+BV9/$BT9 -> #REF! | BZ9: =+BW9/$BT9 -> #REF! | CA9: =+BX9/$BT9 -> #REF! | CB9: Shouldn’t MRC be 50,662? ARC is 38,58,750 for 7 racks and 396,900 for addl space reservation.
A10: L5 | B10: L5A-05-09 & L5A-05-10 | C10: DENSO INTERNATIONAL INDIA PVT LTD | D10: YES | G10: Rated | H10: Bundled | I10: Rack | J10: Uncaged | K10: =IF(I10="Rack","No of Racks",(IF(I10="Space","Sq Ft","U Space"))) -> No of Racks | L10: 2 | M10: 2 | N10: =L10-M10 -> 0 | O10: 2 | Q10: =((860000+550000+200000)/3)/12 -> 44722.222 | R10: =G10 -> Rated | S10: KVA | T10: 9 | U10: 12.72 | V10: =T10-U10 -> -3.72 | X10: =IF(V10<=0,0,(IF(R10="Rated",(V10+W10)*#REF!,(V10+W10)))) -> 0 | Y10: =IF(R10="Rated",T10*#REF!,T10) -> #REF! | Z10: 1.74 | AA10: =IF((V10*-1)>0, (V10*-1), 0) -> 3.72 | AB10: =90000/12 -> 7500 | AC10: =H10 -> Bundled | AI10: =IF(AH10="No of Seats","No of Seats",(IF(AH10="Space","Sq Ft",""))) | AL10: =AJ10-AK10 -> 0 | AP10: =Q10*O10 -> 89444.444 | AQ10: =AB10*AA10 -> 27900 | AR10: =AG10*AF10*AD10 -> 0 | AS10: =AO10*AM10 -> 0 | AT10: =(20000+200000+50000+5000)/12 -> 22916.667 | AU10: =SUBTOTAL(9,AP10:AT10) -> 140261.11 | AW10: Renewal | BC10: =IF(I10="Rack",AU10/L10,0)+IF(I10="U Space",AU10*40/L10,0)+IF(I10="Space",AU10*30/L10,0) -> 70130.556 | BD10: =+AU10/Y10 -> #REF! | BE10: =+($AP10+$AQ10+$AR10-BL10)/$Y10 -> #REF! | BF10: =+($AP10+$AQ10+$AR10-BM10)/$Y10 -> #REF! | BG10: =+($AP10+$AQ10+IF(H10="Bundled",0,Y10*0.85*AD10*AF10*30.5*24)-BN10)/$Y10 -> #REF! | BI10: =+AP10+AQ10+AR10 -> 117344.44 | BJ10: =+BI10-BK10 -> #REF! | BK10: =IF(H10="Bundled",MIN(Y10*#REF!*(1+#REF!),BI10),AR10) -> #REF! | BL10: =IF($AG10>0,$AG10*#REF!*#REF!*(1+#REF!*(20/#REF!)/732),#REF!*Z10) -> #REF! | BM10: =IF($AG10>0,$AG10*#REF!*#REF!*(1+#REF!*(20/#REF!)/732),+#REF!*(Z10+X10)) -> #REF! | BN10: =IF(H10="Bundled",#REF!*Y10,#REF!*Y10*0.85) -> #REF! | BO10: =+BE10*Y10 -> #REF! | BP10: =+#REF!*Y10 -> #REF! | BQ10: =+BJ10-BP10 -> #REF! | BR10: =+BK10-BL10 -> #REF! | BS10: =+BQ10+BR10 -> #REF! | BT10: =+Y10 -> #REF! | BU10: =+BE10 -> #REF! | BV10: =IF(H10="Bundled",BN10-BL10,AR10-BL10) -> #REF! | BW10: =IF(H10="Bundled",+(BG10-#REF!)*Y10,(AP10+AQ10)-Y10*#REF!) -> #REF! | BX10: =+BV10+BW10 -> #REF! | BY10: =+BV10/$BT10 -> #REF! | BZ10: =+BW10/$BT10 -> #REF! | CA10: =+BX10/$BT10 -> #REF!
A11: L5 | B11: L5A-05-08 | C11: CATO | D11: NO | G11: Subscribed | H11: Bundled | I11: Rack | J11: Uncaged | K11: =IF(I11="Rack","No of Racks",(IF(I11="Space","Sq Ft","U Space"))) -> No of Racks | L11: 1 | M11: 1 | N11: =L11-M11 -> 0 | O11: 1 | Q11: =((860000+550000+200000)/3)/12 -> 44722.222 | S11: KVA | T11: 4 | U11: =Z11 -> 0.7172619 | V11: =T11-U11 -> 3.2827381 | X11: =IF(V11<=0,0,(IF(R11="Rated",(V11+W11)*#REF!,(V11+W11)))) -> 3.2827381 | Y11: =IF(R11="Rated",T11*#REF!,T11) -> 4 | Z11: =AG11/28/24 -> 0.7172619 | AA11: =IF((V11*-1)>0, (V11*-1), 0) -> 0 | AB11: =90000/12 -> 7500 | AC11: =H11 -> Bundled | AG11: 482 | AI11: =IF(AH11="No of Seats","No of Seats",(IF(AH11="Space","Sq Ft",""))) | AL11: =AJ11-AK11 -> 0 | AP11: =Q11*O11 -> 44722.222 | AQ11: =AB11*AA11 -> 0 | AR11: =AG11*AF11*AD11 -> 0 | AS11: =AO11*AM11 -> 0 | AT11: =(20000+200000+50000+5000)/12 -> 22916.667 | AU11: =SUBTOTAL(9,AP11:AT11) -> 67638.889 | AW11: Renewal | BC11: =IF(I11="Rack",AU11/L11,0)+IF(I11="U Space",AU11*40/L11,0)+IF(I11="Space",AU11*30/L11,0) -> 67638.889 | BD11: =+AU11/Y11 -> 16909.722 | BE11: =+($AP11+$AQ11+$AR11-BL11)/$Y11 -> #REF! | BF11: =+($AP11+$AQ11+$AR11-BM11)/$Y11 -> #REF! | BG11: =+($AP11+$AQ11+IF(H11="Bundled",0,Y11*0.85*AD11*AF11*30.5*24)-BN11)/$Y11 -> #REF! | BI11: =+AP11+AQ11+AR11 -> 44722.222 | BJ11: =+BI11-BK11 -> #REF! | BK11: =IF(H11="Bundled",MIN(Y11*#REF!*(1+#REF!),BI11),AR11) -> #REF! | BL11: =IF($AG11>0,$AG11*#REF!*#REF!*(1+#REF!*(20/#REF!)/732),#REF!*Z11) -> #REF! | BM11: =IF($AG11>0,$AG11*#REF!*#REF!*(1+#REF!*(20/#REF!)/732),+#REF!*(Z11+X11)) -> #REF! | BN11: =IF(H11="Bundled",#REF!*Y11,#REF!*Y11*0.85) -> #REF! | BO11: =+BE11*Y11 -> #REF! | BP11: =+#REF!*Y11 -> #REF! | BQ11: =+BJ11-BP11 -> #REF! | BR11: =+BK11-BL11 -> #REF! | BS11: =+BQ11+BR11 -> #REF! | BT11: =+Y11 -> 4 | BU11: =+BE11 -> #REF! | BV11: =IF(H11="Bundled",BN11-BL11,AR11-BL11) -> #REF! | BW11: =IF(H11="Bundled",+(BG11-#REF!)*Y11,(AP11+AQ11)-Y11*#REF!) -> #REF! | BX11: =+BV11+BW11 -> #REF! | BY11: =+BV11/$BT11 -> #REF! | BZ11: =+BW11/$BT11 -> #REF! | CA11: =+BX11/$BT11 -> #REF!
A12: L5 | B12: L5A-06-01, L5A-06-02, L5A-06-03, L5A-07-01 & L5A-07-02 | C12: NIVA BUPA HEALTH INSURANCE COMPANY LIMITED | D12: MANAGE SERVICES | E12: 1 | G12: Subscribed | H12: Metered | I12: Rack | J12: Uncaged | K12: =IF(I12="Rack","No of Racks",(IF(I12="Space","Sq Ft","U Space"))) -> No of Racks | L12: 5 | M12: 5 | N12: =L12-M12 -> 0 | O12: 5 | Q12: =297500/12 -> 24791.667 | R12: =G12 -> Subscribed | S12: KW | T12: 17.5 | U12: =Z12 -> 16.045491 | V12: =T12-U12 -> 1.4545089 | X12: =IF(V12<=0,0,(IF(R12="Rated",(V12+W12)*#REF!,(V12+W12)))) -> 1.4545089 | Y12: =IF(R12="Rated",T12*#REF!,T12) -> 17.5 | Z12: =AG12/28/24 -> 16.045491 | AA12: =IF((V12*-1)>0, (V12*-1), 0) -> 0 | AB12: =85000/12 -> 7083.3333 | AC12: =H12 -> Metered | AD12: 1 | AE12: Fixed | AF12: 19.5 | AG12: 10782.57 | AH12: No of Seats | AI12: =IF(AH12="No of Seats","No of Seats",(IF(AH12="Space","Sq Ft",""))) -> No of Seats | AJ12: 1 | AK12: 1 | AL12: =AJ12-AK12 -> 0 | AM12: 1 | AO12: =96307/12 -> 8025.5833 | AP12: =Q12*O12 -> 123958.33 | AQ12: =AB12*AA12 -> 0 | AR12: =AG12*AF12*AD12 -> 210260.11 | AS12: =AO12*AM12 -> 8025.5833 | AT12: =(96307+74906)/12 -> 14267.75 | AU12: =SUBTOTAL(9,AP12:AT12) -> 356511.78 | AW12: Renewal | BC12: =IF(I12="Rack",AU12/L12,0)+IF(I12="U Space",AU12*40/L12,0)+IF(I12="Space",AU12*30/L12,0) -> 71302.356 | BD12: =+AU12/Y12 -> 20372.102 | BE12: =+($AP12+$AQ12+$AR12-BL12)/$Y12 -> #REF! | BF12: =+($AP12+$AQ12+$AR12-BM12)/$Y12 -> #REF! | BG12: =+($AP12+$AQ12+IF(H12="Bundled",0,Y12*0.85*AD12*AF12*30.5*24)-BN12)/$Y12 -> #REF! | BI12: =+AP12+AQ12+AR12 -> 334218.45 | BJ12: =+BI12-BK12 -> 123958.33 | BK12: =IF(H12="Bundled",MIN(Y12*#REF!*(1+#REF!),BI12),AR12) -> 210260.11 | BL12: =IF($AG12>0,$AG12*#REF!*#REF!*(1+#REF!*(20/#REF!)/732),#REF!*Z12) -> #REF! | BM12: =IF($AG12>0,$AG12*#REF!*#REF!*(1+#REF!*(20/#REF!)/732),+#REF!*(Z12+X12)) -> #REF! | BN12: =IF(H12="Bundled",#REF!*Y12,#REF!*Y12*0.85) -> #REF! | BO12: =+BE12*Y12 -> #REF! | BP12: =+#REF!*Y12 -> #REF! | BQ12: =+BJ12-BP12 -> #REF! | BR12: =+BK12-BL12 -> #REF! | BS12: =+BQ12+BR12 -> #REF! | BT12: =+Y12 -> 17.5 | BU12: =+BE12 -> #REF! | BV12: =IF(H12="Bundled",BN12-BL12,AR12-BL12) -> #REF! | BW12: =IF(H12="Bundled",+(BG12-#REF!)*Y12,(AP12+AQ12)-Y12*#REF!) -> #REF! | BX12: =+BV12+BW12 -> #REF! | BY12: =+BV12/$BT12 -> #REF! | BZ12: =+BW12/$BT12 -> #REF! | CA12: =+BX12/$BT12 -> #REF!
A13: L5 | B13: Server Hall 5A | C13: BENNETT, COLEMAN & CO. LTD | D13: YES | G13: Subscribed | H13: Metered | I13: Space | J13: Caged | K13: Sq Ft | L13: 416 | M13: 416 | N13: =L13-M13 -> 0 | O13: 19 | Q13: =((4778000+330000)/20)/12 -> 21283.333 | R13: =G13 -> Subscribed | S13: KW | T13: 56 | U13: =Z13 -> 45.66747 | V13: =T13-U13 -> 10.33253 | X13: =IF(V13<=0,0,(IF(R13="Rated",(V13+W13)*#REF!,(V13+W13)))) -> 10.33253 | Y13: =IF(R13="Rated",T13*#REF!,T13) -> 56 | Z13: =AG13/28/24 -> 45.66747 | AA13: =IF((V13*-1)>0, (V13*-1), 0) -> 0 | AB13: =70000/12 -> 5833.3333 | AC13: =H13 -> Metered | AD13: 1 | AE13: Fixed | AF13: 16.5 | AG13: 30688.54 | AI13: =IF(AH13="No of Seats","No of Seats",(IF(AH13="Space","Sq Ft",""))) | AL13: =AJ13-AK13 -> 0 | AP13: =Q13*O13 -> 404383.33 | AQ13: =AB13*AA13 -> 0 | AR13: =AG13*AF13*AD13 -> 506360.91 | AS13: =AO13*AM13 -> 0 | AT13: =(175000+700000)/12 -> 72916.667 | AU13: =SUBTOTAL(9,AP13:AT13) -> 983660.91 | AW13: Renewal | BC13: =IF(I13="Rack",AU13/L13,0)+IF(I13="U Space",AU13*40/L13,0)+IF(I13="Space",AU13*30/L13,0) -> 70937.085 | BD13: =+AU13/Y13 -> 17565.373 | BE13: =+($AP13+$AQ13+$AR13-BL13)/$Y13 -> #REF! | BF13: =+($AP13+$AQ13+$AR13-BM13)/$Y13 -> #REF! | BG13: =+($AP13+$AQ13+IF(H13="Bundled",0,Y13*0.85*AD13*AF13*30.5*24)-BN13)/$Y13 -> #REF! | BI13: =+AP13+AQ13+AR13 -> 910744.24 | BJ13: =+BI13-BK13 -> 404383.33 | BK13: =IF(H13="Bundled",MIN(Y13*#REF!*(1+#REF!),BI13),AR13) -> 506360.91 | BL13: =IF($AG13>0,$AG13*#REF!*#REF!*(1+#REF!*(20/#REF!)/732),#REF!*Z13) -> #REF! | BM13: =IF($AG13>0,$AG13*#REF!*#REF!*(1+#REF!*(20/#REF!)/732),+#REF!*(Z13+X13)) -> #REF! | BN13: =IF(H13="Bundled",#REF!*Y13,#REF!*Y13*0.85) -> #REF! | BO13: =+BE13*Y13 -> #REF! | BP13: =+#REF!*Y13 -> #REF! | BQ13: =+BJ13-BP13 -> #REF! | BR13: =+BK13-BL13 -> #REF! | BS13: =+BQ13+BR13 -> #REF! | BT13: =+Y13 -> 56 | BU13: =+BE13 -> #REF! | BV13: =IF(H13="Bundled",BN13-BL13,AR13-BL13) -> #REF! | BW13: =IF(H13="Bundled",+(BG13-#REF!)*Y13,(AP13+AQ13)-Y13*#REF!) -> #REF! | BX13: =+BV13+BW13 -> #REF! | BY13: =+BV13/$BT13 -> #REF! | BZ13: =+BW13/$BT13 -> #REF! | CA13: =+BX13/$BT13 -> #REF! | CB13: not able to trace in inventory file.
A14: L5 | B14: Server Hall 5A | C14: THE JAMMU & KASHMIR BANK LTD | D14: NO/RFP | E14: 52 | G14: Subscribed | H14: Metered | I14: Space | J14: Caged | K14: =IF(I14="Rack","No of Racks",(IF(I14="Space","Sq Ft","U Space"))) -> Sq Ft | L14: 998 | M14: 998 | N14: =L14-M14 -> 0 | O14: 998 | Q14: =(7527733.92/998)/12 -> 628.5683 | R14: =G14 -> Subscribed | S14: KW | T14: 100 | U14: =Z14 -> 107.67182 | V14: =T14-U14 -> -7.6718155 | X14: =IF(V14<=0,0,(IF(R14="Rated",(V14+W14)*#REF!,(V14+W14)))) -> 0 | Y14: =IF(R14="Rated",T14*#REF!,T14) -> 100 | Z14: =AG14/28/24 -> 107.67182 | AA14: =IF((V14*-1)>0, (V14*-1), 0) -> 7.6718155 | AB14: 0 | AC14: =H14 -> Metered | AD14: 1 | AE14: Fixed | AF14: 12.48 | AG14: 72355.46 | AI14: =IF(AH14="No of Seats","No of Seats",(IF(AH14="Space","Sq Ft",""))) | AJ14: 52 | AK14: 52 | AL14: =AJ14-AK14 -> 0 | AM14: 52 | AO14: =((1895859.28+162489.68+189571.29+355473.61+118491)/12)/21 -> 10801.13 | AP14: =Q14*O14 -> 627311.16 | AQ14: =AB14*AA14 -> 0 | AR14: =AG14*AF14*AD14 -> 902996.14 | AS14: =AO14 -> 10801.13 | AT14: =161135/12 -> 13427.917 | AU14: =SUBTOTAL(9,AP14:AT14) -> 1554536.3 | AW14: 721000893, 721000761, 721001050 | BC14: =IF(I14="Rack",AU14/L14,0)+IF(I14="U Space",AU14*40/L14,0)+IF(I14="Space",AU14*30/L14,0) -> 46729.55 | BD14: =+AU14/Y14 -> 15545.363 | BE14: =+($AP14+$AQ14+$AR14-BL14)/$Y14 -> #REF! | BF14: =+($AP14+$AQ14+$AR14-BM14)/$Y14 -> #REF! | BG14: =+($AP14+$AQ14+IF(H14="Bundled",0,Y14*0.85*AD14*AF14*30.5*24)-BN14)/$Y14 -> #REF! | BI14: =+AP14+AQ14+AR14 -> 1530307.3 | BJ14: =+BI14-BK14 -> 627311.16 | BK14: =IF(H14="Bundled",MIN(Y14*#REF!*(1+#REF!),BI14),AR14) -> 902996.14 | BL14: =IF($AG14>0,$AG14*#REF!*#REF!*(1+#REF!*(20/#REF!)/732),#REF!*Z14) -> #REF! | BM14: =IF($AG14>0,$AG14*#REF!*#REF!*(1+#REF!*(20/#REF!)/732),+#REF!*(Z14+X14)) -> #REF! | BN14: =IF(H14="Bundled",#REF!*Y14,#REF!*Y14*0.85) -> #REF! | BO14: =+BE14*Y14 -> #REF! | BP14: =+#REF!*Y14 -> #REF! | BQ14: =+BJ14-BP14 -> #REF! | BR14: =+BK14-BL14 -> #REF! | BS14: =+BQ14+BR14 -> #REF! | BT14: =+Y14 -> 100 | BU14: =+BE14 -> #REF! | BV14: =IF(H14="Bundled",BN14-BL14,AR14-BL14) -> #REF! | BW14: =IF(H14="Bundled",+(BG14-#REF!)*Y14,(AP14+AQ14)-Y14*#REF!) -> #REF! | BX14: =+BV14+BW14 -> #REF! | BY14: =+BV14/$BT14 -> #REF! | BZ14: =+BW14/$BT14 -> #REF! | CA14: =+BX14/$BT14 -> #REF!
A15: L5 | B15: Server Hall 5A | C15: THE JAMMU & KASHMIR BANK LTD | D15: NO/RFP | G15: Subscribed | H15: Metered | I15: Space | J15: Caged | K15: =IF(I15="Rack","No of Racks",(IF(I15="Space","Sq Ft","U Space"))) -> Sq Ft | L15: 216 | M15: 216 | N15: 0 | O15: 216 | R15: =G15 -> Subscribed | S15: KW | T15: 30 | U15: =Z15 -> 6.4434524 | Y15: =IF(R15="Rated",T15*#REF!,T15) -> 30 | Z15: =AG15/28/24 -> 6.4434524 | AG15: 4330 | BL15: =IF($AG15>0,$AG15*#REF!*#REF!*(1+#REF!*(20/#REF!)/732),#REF!*Z15) -> #REF! | BN15: =IF(H15="Bundled",#REF!*Y15,#REF!*Y15*0.85) -> #REF! | BT15: =+Y15 -> 30
A16: L5 | B16: L5A-03-11 | C16: GSTECH SOFTWARE SYSTEMS PVT.LTD. | D16: NO | G16: Subscribed | H16: Metered | I16: Rack | J16: Uncaged | K16: =IF(I16="Rack","No of Racks",(IF(I16="Space","Sq Ft","U Space"))) -> No of Racks | L16: 1 | M16: 1 | N16: =L16-M16 -> 0 | O16: 1 | Q16: =270000/12 -> 22500 | R16: =G16 -> Subscribed | S16: KW | T16: 2.5 | U16: =Z16 -> 1.5044643 | V16: =T16-U16 -> 0.99553571 | X16: =IF(V16<=0,0,(IF(R16="Rated",(V16+W16)*#REF!,(V16+W16)))) -> 0.99553571 | Y16: =IF(R16="Rated",T16*#REF!,T16) -> 2.5 | Z16: =AG16/28/24 -> 1.5044643 | AA16: =IF((V16*-1)>0, (V16*-1), 0) -> 0 | AB16: =95000/12 -> 7916.6667 | AC16: =H16 -> Metered | AD16: 1 | AE16: Fixed | AF16: 17 | AG16: 1011 | AI16: =IF(AH16="No of Seats","No of Seats",(IF(AH16="Space","Sq Ft",""))) | AL16: =AJ16-AK16 -> 0 | AP16: =Q16*O16 -> 22500 | AQ16: =AB16*AA16 -> 0 | AR16: =AG16*AF16*AD16 -> 17187 | AS16: =AO16*AM16 -> 0 | AT16: =95051/12 -> 7920.9167 | AU16: =SUBTOTAL(9,AP16:AT16) -> 47607.917 | AW16: Renewal | BC16: =IF(I16="Rack",AU16/L16,0)+IF(I16="U Space",AU16*40/L16,0)+IF(I16="Space",AU16*30/L16,0) -> 47607.917 | BD16: =+AU16/Y16 -> 19043.167 | BE16: =+($AP16+$AQ16+$AR16-BL16)/$Y16 -> #REF! | BF16: =+($AP16+$AQ16+$AR16-BM16)/$Y16 -> #REF! | BG16: =+($AP16+$AQ16+IF(H16="Bundled",0,Y16*0.85*AD16*AF16*30.5*24)-BN16)/$Y16 -> #REF! | BI16: =+AP16+AQ16+AR16 -> 39687 | BJ16: =+BI16-BK16 -> 22500 | BK16: =IF(H16="Bundled",MIN(Y16*#REF!*(1+#REF!),BI16),AR16) -> 17187 | BL16: =IF($AG16>0,$AG16*#REF!*#REF!*(1+#REF!*(20/#REF!)/732),#REF!*Z16) -> #REF! | BM16: =IF($AG16>0,$AG16*#REF!*#REF!*(1+#REF!*(20/#REF!)/732),+#REF!*(Z16+X16)) -> #REF! | BN16: =IF(H16="Bundled",#REF!*Y16,#REF!*Y16*0.85) -> #REF! | BO16: =+BE16*Y16 -> #REF! | BP16: =+#REF!*Y16 -> #REF! | BQ16: =+BJ16-BP16 -> #REF! | BR16: =+BK16-BL16 -> #REF! | BS16: =+BQ16+BR16 -> #REF! | BT16: =+Y16 -> 2.5 | BU16: =+BE16 -> #REF! | BV16: =IF(H16="Bundled",BN16-BL16,AR16-BL16) -> #REF! | BW16: =IF(H16="Bundled",+(BG16-#REF!)*Y16,(AP16+AQ16)-Y16*#REF!) -> #REF! | BX16: =+BV16+BW16 -> #REF! | BY16: =+BV16/$BT16 -> #REF! | BZ16: =+BW16/$BT16 -> #REF! | CA16: =+BX16/$BT16 -> #REF! | CB16: not able to match with PO. PO ARC value shows 305,000. Also, this client is not found in the Inventory report. Is it still live?
A17: L5 | B17: Server Hall 5A L5A-01-08 | C17: ULTRANET SERVICES PVT LTD | D17: YES | G17: Rated | H17: Bundled | I17: U space | J17: Uncaged | K17: =IF(I17="Rack","No of Racks",(IF(I17="Space","Sq Ft","U Space"))) -> U Space | L17: 4 | M17: 4 | N17: =L17-M17 -> 0 | O17: 4 | Q17: =(160000/4)/12 -> 3333.3333 | R17: =G17 -> Rated | S17: KVA | T17: 1 | U17: 0.27 | V17: =T17-U17 -> 0.73 | X17: =IF(V17<=0,0,(IF(R17="Rated",(V17+W17)*#REF!,(V17+W17)))) -> #REF! | Y17: =IF(R17="Rated",T17*#REF!,T17) -> #REF! | Z17: 0.8 | AA17: =IF((V17*-1)>0, (V17*-1), 0) -> 0 | AB17: =100000/12 -> 8333.3333 | AC17: =H17 -> Bundled | AI17: =IF(AH17="No of Seats","No of Seats",(IF(AH17="Space","Sq Ft",""))) | AL17: =AJ17-AK17 -> 0 | AP17: =Q17*O17 -> 13333.333 | AQ17: =AB17*AA17 -> 0 | AR17: =AG17*AF17*AD17 -> 0 | AS17: =AO17*AM17 -> 0 | AT17: =(15000+50000+60000)/12 -> 10416.667 | AU17: =SUBTOTAL(9,AP17:AT17) -> 23750 | AW17: Renewal | BC17: =IF(I17="Rack",AU17/L17,0)+IF(I17="U Space",AU17*40/L17,0)+IF(I17="Space",AU17*30/L17,0) -> 237500 | BD17: =+AU17/Y17 -> #REF! | BE17: =+($AP17+$AQ17+$AR17-BL17)/$Y17 -> #REF! | BF17: =+($AP17+$AQ17+$AR17-BM17)/$Y17 -> #REF! | BG17: =+($AP17+$AQ17+IF(H17="Bundled",0,Y17*0.85*AD17*AF17*30.5*24)-BN17)/$Y17 -> #REF! | BI17: =+AP17+AQ17+AR17 -> 13333.333 | BJ17: =+BI17-BK17 -> #REF! | BK17: =IF(H17="Bundled",MIN(Y17*#REF!*(1+#REF!),BI17),AR17) -> #REF! | BL17: =IF($AG17>0,$AG17*#REF!*#REF!*(1+#REF!*(20/#REF!)/732),#REF!*Z17) -> #REF! | BM17: =IF($AG17>0,$AG17*#REF!*#REF!*(1+#REF!*(20/#REF!)/732),+#REF!*(Z17+X17)) -> #REF! | BN17: =IF(H17="Bundled",#REF!*Y17,#REF!*Y17*0.85) -> #REF! | BO17: =+BE17*Y17 -> #REF! | BP17: =+#REF!*Y17 -> #REF! | BQ17: =+BJ17-BP17 -> #REF! | BR17: =+BK17-BL17 -> #REF! | BS17: =+BQ17+BR17 -> #REF! | BT17: =+Y17 -> #REF! | BU17: =+BE17 -> #REF! | BV17: =IF(H17="Bundled",BN17-BL17,AR17-BL17) -> #REF! | BW17: =IF(H17="Bundled",+(BG17-#REF!)*Y17,(AP17+AQ17)-Y17*#REF!) -> #REF! | BX17: =+BV17+BW17 -> #REF! | BY17: =+BV17/$BT17 -> #REF! | BZ17: =+BW17/$BT17 -> #REF! | CA17: =+BX17/$BT17 -> #REF!
A18: L5 | C18: SPIDER LINK ( 4U and 6U TO 7U) | D18: NO | G18: Rated | H18: Bundled | I18: U space | J18: Uncaged | K18: =IF(I18="Rack","No of Racks",(IF(I18="Space","Sq Ft","U Space"))) -> U Space | L18: 3 | M18: 3 | N18: 0 | O18: 3 | Q18: =(30000/1)/12 -> 2500 | R18: =G18 -> Rated | S18: KVA | T18: 0.75 | U18: 1.68 | V18: =T18-U18 -> -0.93 | X18: =IF(V18<=0,0,(IF(R18="Rated",(V18+W18)*#REF!,(V18+W18)))) -> 0 | Y18: =IF(R18="Rated",T18*#REF!,T18) -> #REF! | AA18: =IF((V18*-1)>0, (V18*-1), 0) -> 0.93 | AC18: =H18 -> Bundled | BM18: =IF($AG18>0,$AG18*#REF!*#REF!*(1+#REF!*(20/#REF!)/732),+#REF!*(Z18+X18)) -> #REF! | BN18: =IF(H18="Bundled",#REF!*Y18,#REF!*Y18*0.85) -> #REF! | BT18: =+Y18 -> #REF!
A19: L5 | C19: BIG Data Broadband | D19: NO | G19: Rated | H19: Bundled | I19: U space | J19: Uncaged | K19: =IF(I19="Rack","No of Racks",(IF(I19="Space","Sq Ft","U Space"))) -> U Space | L19: 1 | M19: 1 | N19: 0 | O19: 1 | Q19: =(103500/3)/12 -> 2875 | R19: =G19 -> Rated | S19: KVA | T19: 0.25 | U19: 0.27 | V19: =T19-U19 -> -0.02 | X19: =IF(V19<=0,0,(IF(R19="Rated",(V19+W19)*#REF!,(V19+W19)))) -> 0 | Y19: =IF(R19="Rated",T19*#REF!,T19) -> #REF! | AA19: =IF((V19*-1)>0, (V19*-1), 0) -> 0.02 | AC19: =H19 -> Bundled | BM19: =IF($AG19>0,$AG19*#REF!*#REF!*(1+#REF!*(20/#REF!)/732),+#REF!*(Z19+X19)) -> #REF! | BN19: =IF(H19="Bundled",#REF!*Y19,#REF!*Y19*0.85) -> #REF! | BP19: =+#REF!*Y19 -> #REF! | BT19: =+Y19 -> #REF!
A20: L5 | C20: MYLINK SERVICES PVT LTD ( 20U) (22U) | D20: NO | G20: Rated | H20: Bundled | I20: U space | J20: Uncaged | K20: =IF(I20="Rack","No of Racks",(IF(I20="Space","Sq Ft","U Space"))) -> U Space | L20: 2 | M20: 2 | N20: =L20-M20 -> 0 | O20: 2 | Q20: =33700/12 -> 2808.3333 | R20: =G20 -> Rated | S20: KVA | T20: 0.5 | U20: 0.27 | V20: =T20-U20 -> 0.23 | X20: =IF(V20<=0,0,(IF(R20="Rated",(V20+W20)*#REF!,(V20+W20)))) -> #REF! | Y20: =IF(R20="Rated",T20*#REF!,T20) -> #REF! | AA20: =IF((V20*-1)>0, (V20*-1), 0) -> 0 | AB20: =110000/12 -> 9166.6667 | AC20: =H20 -> Bundled | AI20: =IF(AH20="No of Seats","No of Seats",(IF(AH20="Space","Sq Ft",""))) | AL20: =AJ20-AK20 -> 0 | AP20: =Q20*O20 -> 5616.6667 | AQ20: =AB20*AA20 -> 0 | AR20: =AG20*AF20*AD20 -> 0 | AS20: =AO20*AM20 -> 0 | AT20: =(60000)/12 -> 5000 | AU20: =SUBTOTAL(9,AP20:AT20) -> 10616.667 | AW20: 121000929 | BC20: =IF(I20="Rack",AU20/L20,0)+IF(I20="U Space",AU20*40/L20,0)+IF(I20="Space",AU20*30/L20,0) -> 212333.33 | BD20: =+AU20/Y20 -> #REF! | BE20: =+($AP20+$AQ20+$AR20-BL20)/$Y20 -> #REF! | BF20: =+($AP20+$AQ20+$AR20-BM20)/$Y20 -> #REF! | BG20: =+($AP20+$AQ20+IF(H20="Bundled",0,Y20*0.85*AD20*AF20*30.5*24)-BN20)/$Y20 -> #REF! | BI20: =+AP20+AQ20+AR20 -> 5616.6667 | BJ20: =+BI20-BK20 -> #REF! | BK20: =IF(H20="Bundled",MIN(Y20*#REF!*(1+#REF!),BI20),AR20) -> #REF! | BL20: =IF($AG20>0,$AG20*#REF!*#REF!*(1+#REF!*(20/#REF!)/732),#REF!*Z20) -> #REF! | BM20: =IF($AG20>0,$AG20*#REF!*#REF!*(1+#REF!*(20/#REF!)/732),+#REF!*(Z20+X20)) -> #REF! | BN20: =IF(H20="Bundled",#REF!*Y20,#REF!*Y20*0.85) -> #REF! | BO20: =+BE20*Y20 -> #REF! | BP20: =+#REF!*Y20 -> #REF! | BQ20: =+BJ20-BP20 -> #REF! | BR20: =+BK20-BL20 -> #REF! | BS20: =+BQ20+BR20 -> #REF! | BT20: =+Y20 -> #REF! | BU20: =+BE20 -> #REF! | BV20: =IF(H20="Bundled",BN20-BL20,AR20-BL20) -> #REF! | BW20: =IF(H20="Bundled",+(BG20-#REF!)*Y20,(AP20+AQ20)-Y20*#REF!) -> #REF! | BX20: =+BV20+BW20 -> #REF! | BY20: =+BV20/$BT20 -> #REF! | BZ20: =+BW20/$BT20 -> #REF! | CA20: =+BX20/$BT20 -> #REF!
A21: L5 | B21: Server Hall 5A L5A-01-06 | C21: OZONETEL COMMUNICATIONS PRIVATE LIMITED | D21: YES | G21: Rated | H21: Bundled | I21: U space | J21: Uncaged | K21: =IF(I21="Rack","No of Racks",(IF(I21="Space","Sq Ft","U Space"))) -> U Space | L21: 4 | M21: 4 | N21: =L21-M21 -> 0 | O21: 4 | Q21: =(154000/4)/12 -> 3208.3333 | R21: =G21 -> Rated | S21: KVA | T21: 1 | U21: 0.69 | V21: =T21-U21 -> 0.31 | X21: =IF(V21<=0,0,(IF(R21="Rated",(V21+W21)*#REF!,(V21+W21)))) -> #REF! | Y21: =IF(R21="Rated",T21*#REF!,T21) -> #REF! | Z21: 0.89 | AA21: =IF((V21*-1)>0, (V21*-1), 0) -> 0 | AB21: 0 | AC21: =H21 -> Bundled | AI21: =IF(AH21="No of Seats","No of Seats",(IF(AH21="Space","Sq Ft",""))) | AL21: =AJ21-AK21 -> 0 | AP21: =Q21*O21 -> 12833.333 | AQ21: =AB21*AA21 -> 0 | AR21: =AG21*AF21*AD21 -> 0 | AS21: =AO21*AM21 -> 0 | AT21: =100000/12 -> 8333.3333 | AU21: =SUBTOTAL(9,AP21:AT21) -> 21166.667 | BC21: =IF(I21="Rack",AU21/L21,0)+IF(I21="U Space",AU21*40/L21,0)+IF(I21="Space",AU21*30/L21,0) -> 211666.67 | BD21: =+AU21/Y21 -> #REF! | BE21: =+($AP21+$AQ21+$AR21-BL21)/$Y21 -> #REF! | BF21: =+($AP21+$AQ21+$AR21-BM21)/$Y21 -> #REF! | BG21: =+($AP21+$AQ21+IF(H21="Bundled",0,Y21*0.85*AD21*AF21*30.5*24)-BN21)/$Y21 -> #REF! | BI21: =+AP21+AQ21+AR21 -> 12833.333 | BJ21: =+BI21-BK21 -> #REF! | BK21: =IF(H21="Bundled",MIN(Y21*#REF!*(1+#REF!),BI21),AR21) -> #REF! | BL21: =IF($AG21>0,$AG21*#REF!*#REF!*(1+#REF!*(20/#REF!)/732),#REF!*Z21) -> #REF! | BM21: =IF($AG21>0,$AG21*#REF!*#REF!*(1+#REF!*(20/#REF!)/732),+#REF!*(Z21+X21)) -> #REF! | BN21: =IF(H21="Bundled",#REF!*Y21,#REF!*Y21*0.85) -> #REF! | BO21: =+BE21*Y21 -> #REF! | BP21: =+#REF!*Y21 -> #REF! | BQ21: =+BJ21-BP21 -> #REF! | BR21: =+BK21-BL21 -> #REF! | BS21: =+BQ21+BR21 -> #REF! | BT21: =+Y21 -> #REF! | BU21: =+BE21 -> #REF! | BV21: =IF(H21="Bundled",BN21-BL21,AR21-BL21) -> #REF! | BW21: =IF(H21="Bundled",+(BG21-#REF!)*Y21,(AP21+AQ21)-Y21*#REF!) -> #REF! | BX21: =+BV21+BW21 -> #REF! | BY21: =+BV21/$BT21 -> #REF! | BZ21: =+BW21/$BT21 -> #REF! | CA21: =+BX21/$BT21 -> #REF!
A22: L5 | C22: DBYTE FACILITY NETWORK PVT. LTD. (Space 32U - 35U) | D22: NO | G22: Rated | H22: Bundled | I22: U space | J22: Uncaged | K22: =IF(I22="Rack","No of Racks",(IF(I22="Space","Sq Ft","U Space"))) -> U Space | L22: 4 | M22: 4 | N22: 0 | O22: 4 | R22: Rated | S22: KVA | T22: 1 | U22: 0.33 | V22: =T22-U22 -> 0.67 | X22: =IF(V22<=0,0,(IF(R22="Rated",(V22+W22)*#REF!,(V22+W22)))) -> #REF! | Y22: =IF(R22="Rated",T22*#REF!,T22) -> #REF! | AA22: =IF((V22*-1)>0, (V22*-1), 0) -> 0 | AC22: =H22 -> Bundled
A23: L5 | C23: NETPLUS | D23: YES | G23: Rated | H23: Bundled | I23: U space | J23: Uncaged | K23: =IF(I23="Rack","No of Racks",(IF(I23="Space","Sq Ft","U Space"))) -> U Space | L23: 10 | M23: 10 | N23: 0 | O23: 10 | R23: =G23 -> Rated | S23: KVA | T23: 1.3 | U23: 1.26 | V23: =T23-U23 -> 0.04 | X23: =IF(V23<=0,0,(IF(R23="Rated",(V23+W23)*#REF!,(V23+W23)))) -> #REF! | Y23: =IF(R23="Rated",T23*#REF!,T23) -> #REF! | AA23: =IF((V23*-1)>0, (V23*-1), 0) -> 0 | AC23: =H23 -> Bundled | AI23: =IF(AH23="No of Seats","No of Seats",(IF(AH23="Space","Sq Ft",""))) | AL23: =AJ23-AK23 -> 0 | AP23: =Q23*O23 -> 0 | AQ23: =AB23*AA23 -> 0 | AR23: =AG23*AF23*AD23 -> 0 | AS23: =AO23*AM23 -> 0 | AU23: =SUBTOTAL(9,AP23:AT23) -> 0 | BC23: =IF(I23="Rack",AU23/L23,0)+IF(I23="U Space",AU23*40/L23,0)+IF(I23="Space",AU23*30/L23,0) -> 0 | BD23: =+AU23/Y23 -> #REF! | BE23: =+($AP23+$AQ23+$AR23-BL23)/$Y23 -> #REF! | BF23: =+($AP23+$AQ23+$AR23-BM23)/$Y23 -> #REF! | BG23: =+($AP23+$AQ23+IF(H23="Bundled",0,Y23*0.85*AD23*AF23*30.5*24)-BN23)/$Y23 -> #REF! | BI23: =+AP23+AQ23+AR23 -> 0 | BJ23: =+BI23-BK23 -> #REF! | BK23: =IF(H23="Bundled",MIN(Y23*#REF!*(1+#REF!),BI23),AR23) -> #REF! | BL23: =IF($AG23>0,$AG23*#REF!*#REF!*(1+#REF!*(20/#REF!)/732),#REF!*Z23) -> #REF! | BM23: =IF($AG23>0,$AG23*#REF!*#REF!*(1+#REF!*(20/#REF!)/732),+#REF!*(Z23+X23)) -> #REF! | BN23: =IF(H23="Bundled",#REF!*Y23,#REF!*Y23*0.85) -> #REF! | BO23: =+BE23*Y23 -> #REF! | BP23: =+#REF!*Y23 -> #REF! | BQ23: =+BJ23-BP23 -> #REF! | BR23: =+BK23-BL23 -> #REF! | BS23: =+BQ23+BR23 -> #REF! | BT23: =+Y23 -> #REF! | BU23: =+BE23 -> #REF! | BV23: =IF(H23="Bundled",BN23-BL23,AR23-BL23) -> #REF! | BW23: =IF(H23="Bundled",+(BG23-#REF!)*Y23,(AP23+AQ23)-Y23*#REF!) -> #REF! | BX23: =+BV23+BW23 -> #REF! | BY23: =+BV23/$BT23 -> #REF! | BZ23: =+BW23/$BT23 -> #REF! | CA23: =+BX23/$BT23 -> #REF!
A24: L5 | C24: Greenmax Technologies Ltd 15U | D24: NO | G24: Rated | H24: Bundled | I24: U space | J24: Uncaged | K24: =IF(I24="Rack","No of Racks",(IF(I24="Space","Sq Ft","U Space"))) -> U Space | L24: 1 | M24: 1 | N24: 0 | O24: 1 | R24: Rated | S24: KVA | T24: 0.25 | U24: 0.27 | V24: =T24-U24 -> -0.02 | X24: =IF(V24<=0,0,(IF(R24="Rated",(V24+W24)*#REF!,(V24+W24)))) -> 0 | Y24: =IF(R24="Rated",T24*#REF!,T24) -> #REF! | AA24: =IF((V24*-1)>0, (V24*-1), 0) -> 0.02 | AC24: =H24 -> Bundled
A25: L5 | C25: GIGATEL SOLUTIONS PRIVATE LIMITED | D25: NO | G25: Rated | H25: Bundled | I25: U space | J25: Uncaged | K25: =IF(I25="Rack","No of Racks",(IF(I25="Space","Sq Ft","U Space"))) -> U Space | L25: 1 | M25: 1 | N25: =L25-M25 -> 0 | O25: 1 | Q25: =30000/12 -> 2500 | R25: =G25 -> Rated | S25: KVA | T25: 0.25 | U25: 0.07 | V25: =T25-U25 -> 0.18 | X25: =IF(V25<=0,0,(IF(R25="Rated",(V25+W25)*#REF!,(V25+W25)))) -> #REF! | Y25: =IF(R25="Rated",T25*#REF!,T25) -> #REF! | AA25: =IF((V25*-1)>0, (V25*-1), 0) -> 0 | AB25: =100000/12 -> 8333.3333 | AC25: =H25 -> Bundled | AI25: =IF(AH25="No of Seats","No of Seats",(IF(AH25="Space","Sq Ft",""))) | AL25: =AJ25-AK25 -> 0 | AP25: =Q25*O25 -> 2500 | AQ25: =AB25*AA25 -> 0 | AR25: =AG25*AF25*AD25 -> 0 | AS25: =AO25*AM25 -> 0 | AT25: =10000/12 -> 833.33333 | AU25: =SUBTOTAL(9,AP25:AT25) -> 3333.3333 | AW25: 721006234 | BC25: =IF(I25="Rack",AU25/L25,0)+IF(I25="U Space",AU25*40/L25,0)+IF(I25="Space",AU25*30/L25,0) -> 133333.33 | BD25: =+AU25/Y25 -> #REF! | BE25: =+($AP25+$AQ25+$AR25-BL25)/$Y25 -> #REF! | BF25: =+($AP25+$AQ25+$AR25-BM25)/$Y25 -> #REF! | BG25: =+($AP25+$AQ25+IF(H25="Bundled",0,Y25*0.85*AD25*AF25*30.5*24)-BN25)/$Y25 -> #REF! | BI25: =+AP25+AQ25+AR25 -> 2500 | BJ25: =+BI25-BK25 -> #REF! | BK25: =IF(H25="Bundled",MIN(Y25*#REF!*(1+#REF!),BI25),AR25) -> #REF! | BL25: =IF($AG25>0,$AG25*#REF!*#REF!*(1+#REF!*(20/#REF!)/732),#REF!*Z25) -> #REF! | BM25: =IF($AG25>0,$AG25*#REF!*#REF!*(1+#REF!*(20/#REF!)/732),+#REF!*(Z25+X25)) -> #REF! | BN25: =IF(H25="Bundled",#REF!*Y25,#REF!*Y25*0.85) -> #REF! | BO25: =+BE25*Y25 -> #REF! | BP25: =+#REF!*Y25 -> #REF! | BQ25: =+BJ25-BP25 -> #REF! | BR25: =+BK25-BL25 -> #REF! | BS25: =+BQ25+BR25 -> #REF! | BT25: =+Y25 -> #REF! | BU25: =+BE25 -> #REF! | BV25: =IF(H25="Bundled",BN25-BL25,AR25-BL25) -> #REF! | BW25: =IF(H25="Bundled",+(BG25-#REF!)*Y25,(AP25+AQ25)-Y25*#REF!) -> #REF! | BX25: =+BV25+BW25 -> #REF! | BY25: =+BV25/$BT25 -> #REF! | BZ25: =+BW25/$BT25 -> #REF! | CA25: =+BX25/$BT25 -> #REF!
A26: L5 | C26: Geocity Network/ Bhartiya Net | D26: YES | G26: Rated | H26: Bundled | I26: U space | J26: Uncaged | K26: =IF(I26="Rack","No of Racks",(IF(I26="Space","Sq Ft","U Space"))) -> U Space | L26: 3 | M26: 3 | N26: =L26-M26 -> 0 | O26: 3 | Q26: =30000/12 -> 2500 | R26: =G26 -> Rated | S26: KVA | T26: 0.75 | U26: 0.28 | V26: =T26-U26 -> 0.47 | X26: =IF(V26<=0,0,(IF(R26="Rated",(V26+W26)*#REF!,(V26+W26)))) -> #REF! | Y26: =IF(R26="Rated",T26*#REF!,T26) -> #REF! | AA26: =IF((V26*-1)>0, (V26*-1), 0) -> 0 | AB26: =90000/12 -> 7500 | AC26: =H26 -> Bundled | AI26: =IF(AH26="No of Seats","No of Seats",(IF(AH26="Space","Sq Ft",""))) | AL26: =AJ26-AK26 -> 0 | AP26: =Q26*O26 -> 7500 | AQ26: =AB26*AA26 -> 0 | AR26: =AG26*AF26*AD26 -> 0 | AS26: =AO26*AM26 -> 0 | AT26: =0/12 -> 0 | AU26: =SUBTOTAL(9,AP26:AT26) -> 7500 | BC26: =IF(I26="Rack",AU26/L26,0)+IF(I26="U Space",AU26*40/L26,0)+IF(I26="Space",AU26*30/L26,0) -> 100000 | BD26: =+AU26/Y26 -> #REF! | BE26: =+($AP26+$AQ26+$AR26-BL26)/$Y26 -> #REF! | BF26: =+($AP26+$AQ26+$AR26-BM26)/$Y26 -> #REF! | BG26: =+($AP26+$AQ26+IF(H26="Bundled",0,Y26*0.85*AD26*AF26*30.5*24)-BN26)/$Y26 -> #REF! | BI26: =+AP26+AQ26+AR26 -> 7500 | BJ26: =+BI26-BK26 -> #REF! | BK26: =IF(H26="Bundled",MIN(Y26*#REF!*(1+#REF!),BI26),AR26) -> #REF! | BL26: =IF($AG26>0,$AG26*#REF!*#REF!*(1+#REF!*(20/#REF!)/732),#REF!*Z26) -> #REF! | BM26: =IF($AG26>0,$AG26*#REF!*#REF!*(1+#REF!*(20/#REF!)/732),+#REF!*(Z26+X26)) -> #REF! | BN26: =IF(H26="Bundled",#REF!*Y26,#REF!*Y26*0.85) -> #REF! | BO26: =+BE26*Y26 -> #REF! | BP26: =+#REF!*Y26 -> #REF! | BQ26: =+BJ26-BP26 -> #REF! | BR26: =+BK26-BL26 -> #REF! | BS26: =+BQ26+BR26 -> #REF! | BT26: =+Y26 -> #REF! | BU26: =+BE26 -> #REF! | BV26: =IF(H26="Bundled",BN26-BL26,AR26-BL26) -> #REF! | BW26: =IF(H26="Bundled",+(BG26-#REF!)*Y26,(AP26+AQ26)-Y26*#REF!) -> #REF! | BX26: =+BV26+BW26 -> #REF! | BY26: =+BV26/$BT26 -> #REF! | BZ26: =+BW26/$BT26 -> #REF! | CA26: =+BX26/$BT26 -> #REF!
A27: L5 | C27: ATRIA CONVERGENCE TECHNOLOGIES LTD/ ACT | D27: YES | G27: Rated | H27: Bundled | I27: U space | J27: Uncaged | K27: =IF(I27="Rack","No of Racks",(IF(I27="Space","Sq Ft","U Space"))) -> U Space | L27: 1 | M27: 1 | N27: =L27-M27 -> 0 | O27: 1 | Q27: =34500/12 -> 2875 | R27: =G27 -> Rated | S27: KVA | T27: 0.25 | U27: 0.33 | V27: =T27-U27 -> -0.08 | X27: =IF(V27<=0,0,(IF(R27="Rated",(V27+W27)*#REF!,(V27+W27)))) -> 0 | Y27: =IF(R27="Rated",T27*#REF!,T27) -> #REF! | AA27: =IF((V27*-1)>0, (V27*-1), 0) -> 0.08 | AB27: =90000/12 -> 7500 | AC27: =H27 -> Bundled | AI27: =IF(AH27="No of Seats","No of Seats",(IF(AH27="Space","Sq Ft",""))) | AL27: =AJ27-AK27 -> 0 | AP27: =Q27*O27 -> 2875 | AQ27: =AB27*AA27 -> 600 | AR27: =AG27*AF27*AD27 -> 0 | AS27: =AO27*AM27 -> 0 | AT27: =0/12 -> 0 | AU27: =SUBTOTAL(9,AP27:AT27) -> 3475 | BC27: =IF(I27="Rack",AU27/L27,0)+IF(I27="U Space",AU27*40/L27,0)+IF(I27="Space",AU27*30/L27,0) -> 139000 | BD27: =+AU27/Y27 -> #REF! | BE27: =+($AP27+$AQ27+$AR27-BL27)/$Y27 -> #REF! | BF27: =+($AP27+$AQ27+$AR27-BM27)/$Y27 -> #REF! | BG27: =+($AP27+$AQ27+IF(H27="Bundled",0,Y27*0.85*AD27*AF27*30.5*24)-BN27)/$Y27 -> #REF! | BI27: =+AP27+AQ27+AR27 -> 3475 | BJ27: =+BI27-BK27 -> #REF! | BK27: =IF(H27="Bundled",MIN(Y27*#REF!*(1+#REF!),BI27),AR27) -> #REF! | BL27: =IF($AG27>0,$AG27*#REF!*#REF!*(1+#REF!*(20/#REF!)/732),#REF!*Z27) -> #REF! | BM27: =IF($AG27>0,$AG27*#REF!*#REF!*(1+#REF!*(20/#REF!)/732),+#REF!*(Z27+X27)) -> #REF! | BN27: =IF(H27="Bundled",#REF!*Y27,#REF!*Y27*0.85) -> #REF! | BO27: =+BE27*Y27 -> #REF! | BP27: =+#REF!*Y27 -> #REF! | BQ27: =+BJ27-BP27 -> #REF! | BR27: =+BK27-BL27 -> #REF! | BS27: =+BQ27+BR27 -> #REF! | BT27: =+Y27 -> #REF! | BU27: =+BE27 -> #REF! | BV27: =IF(H27="Bundled",BN27-BL27,AR27-BL27) -> #REF! | BW27: =IF(H27="Bundled",+(BG27-#REF!)*Y27,(AP27+AQ27)-Y27*#REF!) -> #REF! | BX27: =+BV27+BW27 -> #REF! | BY27: =+BV27/$BT27 -> #REF! | BZ27: =+BW27/$BT27 -> #REF! | CA27: =+BX27/$BT27 -> #REF!
A28: L5 | B28: Server Hall 5A L5A-02-01 | C28: SITI BROADBAND SERVICES PVT LTD | D28: NO | G28: Rated | H28: Bundled | I28: U space | J28: Uncaged | K28: =IF(I28="Rack","No of Racks",(IF(I28="Space","Sq Ft","U Space"))) -> U Space | L28: 4 | M28: 4 | N28: =L28-M28 -> 0 | O28: 4 | Q28: =(140000/4)/12 -> 2916.6667 | R28: =G28 -> Rated | S28: KVA | T28: 1 | U28: 0.26 | V28: =T28-U28 -> 0.74 | X28: =IF(V28<=0,0,(IF(R28="Rated",(V28+W28)*#REF!,(V28+W28)))) -> #REF! | Y28: =IF(R28="Rated",T28*#REF!,T28) -> #REF! | Z28: 0.68 | AA28: =IF((V28*-1)>0, (V28*-1), 0) -> 0 | AB28: =90000/12 -> 7500 | AC28: =H28 -> Bundled | AI28: =IF(AH28="No of Seats","No of Seats",(IF(AH28="Space","Sq Ft",""))) | AL28: =AJ28-AK28 -> 0 | AP28: =Q28*O28 -> 11666.667 | AQ28: =AB28*AA28 -> 0 | AR28: =AG28*AF28*AD28 -> 0 | AS28: =AO28*AM28 -> 0 | AT28: =150000/12 -> 12500 | AU28: =SUBTOTAL(9,AP28:AT28) -> 24166.667 | BC28: =IF(I28="Rack",AU28/L28,0)+IF(I28="U Space",AU28*40/L28,0)+IF(I28="Space",AU28*30/L28,0) -> 241666.67 | BD28: =+AU28/Y28 -> #REF! | BE28: =+($AP28+$AQ28+$AR28-BL28)/$Y28 -> #REF! | BF28: =+($AP28+$AQ28+$AR28-BM28)/$Y28 -> #REF! | BG28: =+($AP28+$AQ28+IF(H28="Bundled",0,Y28*0.85*AD28*AF28*30.5*24)-BN28)/$Y28 -> #REF! | BI28: =+AP28+AQ28+AR28 -> 11666.667 | BJ28: =+BI28-BK28 -> #REF! | BK28: =IF(H28="Bundled",MIN(Y28*#REF!*(1+#REF!),BI28),AR28) -> #REF! | BL28: =IF($AG28>0,$AG28*#REF!*#REF!*(1+#REF!*(20/#REF!)/732),#REF!*Z28) -> #REF! | BM28: =IF($AG28>0,$AG28*#REF!*#REF!*(1+#REF!*(20/#REF!)/732),+#REF!*(Z28+X28)) -> #REF! | BN28: =IF(H28="Bundled",#REF!*Y28,#REF!*Y28*0.85) -> #REF! | BO28: =+BE28*Y28 -> #REF! | BP28: =+#REF!*Y28 -> #REF! | BQ28: =+BJ28-BP28 -> #REF! | BR28: =+BK28-BL28 -> #REF! | BS28: =+BQ28+BR28 -> #REF! | BT28: =+Y28 -> #REF! | BU28: =+BE28 -> #REF! | BV28: =IF(H28="Bundled",BN28-BL28,AR28-BL28) -> #REF! | BW28: =IF(H28="Bundled",+(BG28-#REF!)*Y28,(AP28+AQ28)-Y28*#REF!) -> #REF! | BX28: =+BV28+BW28 -> #REF! | BY28: =+BV28/$BT28 -> #REF! | BZ28: =+BW28/$BT28 -> #REF! | CA28: =+BX28/$BT28 -> #REF!
A29: L5 | C29: Hathway Cable and Datacom Limited | D29: YES | G29: Rated | H29: Bundled | I29: U space | J29: Uncaged | K29: =IF(I29="Rack","No of Racks",(IF(I29="Space","Sq Ft","U Space"))) -> U Space | L29: 6 | M29: 6 | N29: =L29-M29 -> 0 | O29: 6 | Q29: =(35000)/12 -> 2916.6667 | R29: =G29 -> Rated | S29: KVA | T29: 1.5 | U29: 0.17 | V29: =T29-U29 -> 1.33 | X29: =IF(V29<=0,0,(IF(R29="Rated",(V29+W29)*#REF!,(V29+W29)))) -> #REF! | Y29: =IF(R29="Rated",T29*#REF!,T29) -> #REF! | AA29: =IF((V29*-1)>0, (V29*-1), 0) -> 0 | AB29: =80000/12 -> 6666.6667 | AC29: =H29 -> Bundled | AI29: =IF(AH29="No of Seats","No of Seats",(IF(AH29="Space","Sq Ft",""))) | AL29: =AJ29-AK29 -> 0 | AP29: =Q29*O29 -> 17500 | AQ29: =AB29*AA29 -> 0 | AR29: =AG29*AF29*AD29 -> 0 | AS29: =AO29*AM29 -> 0 | AT29: =800000/12 -> 66666.667 | AU29: =SUBTOTAL(9,AP29:AT29) -> 84166.667 | AW29: 121001073 & 121001074 | BC29: =IF(I29="Rack",AU29/L29,0)+IF(I29="U Space",AU29*40/L29,0)+IF(I29="Space",AU29*30/L29,0) -> 561111.11 | BD29: =+AU29/Y29 -> #REF! | BE29: =+($AP29+$AQ29+$AR29-BL29)/$Y29 -> #REF! | BF29: =+($AP29+$AQ29+$AR29-BM29)/$Y29 -> #REF! | BG29: =+($AP29+$AQ29+IF(H29="Bundled",0,Y29*0.85*AD29*AF29*30.5*24)-BN29)/$Y29 -> #REF! | BI29: =+AP29+AQ29+AR29 -> 17500 | BJ29: =+BI29-BK29 -> #REF! | BK29: =IF(H29="Bundled",MIN(Y29*#REF!*(1+#REF!),BI29),AR29) -> #REF! | BL29: =IF($AG29>0,$AG29*#REF!*#REF!*(1+#REF!*(20/#REF!)/732),#REF!*Z29) -> #REF! | BM29: =IF($AG29>0,$AG29*#REF!*#REF!*(1+#REF!*(20/#REF!)/732),+#REF!*(Z29+X29)) -> #REF! | BN29: =IF(H29="Bundled",#REF!*Y29,#REF!*Y29*0.85) -> #REF! | BO29: =+BE29*Y29 -> #REF! | BP29: =+#REF!*Y29 -> #REF! | BQ29: =+BJ29-BP29 -> #REF! | BR29: =+BK29-BL29 -> #REF! | BS29: =+BQ29+BR29 -> #REF! | BT29: =+Y29 -> #REF! | BU29: =+BE29 -> #REF! | BV29: =IF(H29="Bundled",BN29-BL29,AR29-BL29) -> #REF! | BW29: =IF(H29="Bundled",+(BG29-#REF!)*Y29,(AP29+AQ29)-Y29*#REF!) -> #REF! | BX29: =+BV29+BW29 -> #REF! | BY29: =+BV29/$BT29 -> #REF! | BZ29: =+BW29/$BT29 -> #REF! | CA29: =+BX29/$BT29 -> #REF!
A30: L5 | C30: UMBRELLA CABLE SYSTEMS PRIVATE LIMITED 14-15U | D30: NO | G30: Rated | H30: Bundled | I30: U space | J30: Uncaged | K30: =IF(I30="Rack","No of Racks",(IF(I30="Space","Sq Ft","U Space"))) -> U Space | L30: 2 | M30: 2 | N30: =L30-M30 -> 0 | O30: 2 | R30: Rated | S30: KVA | T30: 0.5 | U30: 1.1 | V30: =T30-U30 -> -0.6 | X30: =IF(V30<=0,0,(IF(R30="Rated",(V30+W30)*#REF!,(V30+W30)))) -> 0 | Y30: =IF(R30="Rated",T30*#REF!,T30) -> #REF! | AA30: =IF((V30*-1)>0, (V30*-1), 0) -> 0.6 | AC30: =H30 -> Bundled
A31: L5 | C31: GLOBE CAPITAL MARKET LIMITED | D31: YES | G31: Rated | H31: Bundled | I31: U space | J31: Uncaged | K31: =IF(I31="Rack","No of Racks",(IF(I31="Space","Sq Ft","U Space"))) -> U Space | L31: 6 | M31: 6 | N31: =L31-M31 -> 0 | O31: 6 | Q31: =(25200)/12 -> 2100 | R31: =G31 -> Rated | S31: KVA | T31: 1.5 | U31: 1.84 | V31: =T31-U31 -> -0.34 | X31: =IF(V31<=0,0,(IF(R31="Rated",(V31+W31)*#REF!,(V31+W31)))) -> 0 | Y31: =IF(R31="Rated",T31*#REF!,T31) -> #REF! | AA31: =IF((V31*-1)>0, (V31*-1), 0) -> 0.34 | AB31: =100000/12 -> 8333.3333 | AC31: =H31 -> Bundled | AI31: =IF(AH31="No of Seats","No of Seats",(IF(AH31="Space","Sq Ft",""))) | AL31: =AJ31-AK31 -> 0 | AP31: =Q31*O31 -> 12600 | AQ31: =AB31*AA31 -> 2833.3333 | AR31: =AG31*AF31*AD31 -> 0 | AS31: =AO31*AM31 -> 0 | AT31: =(276480+10000)/12 -> 23873.333 | AU31: =SUBTOTAL(9,AP31:AT31) -> 39306.667 | AW31: Renewal | BC31: =IF(I31="Rack",AU31/L31,0)+IF(I31="U Space",AU31*40/L31,0)+IF(I31="Space",AU31*30/L31,0) -> 262044.44 | BD31: =+AU31/Y31 -> #REF! | BE31: =+($AP31+$AQ31+$AR31-BL31)/$Y31 -> #REF! | BF31: =+($AP31+$AQ31+$AR31-BM31)/$Y31 -> #REF! | BG31: =+($AP31+$AQ31+IF(H31="Bundled",0,Y31*0.85*AD31*AF31*30.5*24)-BN31)/$Y31 -> #REF! | BI31: =+AP31+AQ31+AR31 -> 15433.333 | BJ31: =+BI31-BK31 -> #REF! | BK31: =IF(H31="Bundled",MIN(Y31*#REF!*(1+#REF!),BI31),AR31) -> #REF! | BL31: =IF($AG31>0,$AG31*#REF!*#REF!*(1+#REF!*(20/#REF!)/732),#REF!*Z31) -> #REF! | BM31: =IF($AG31>0,$AG31*#REF!*#REF!*(1+#REF!*(20/#REF!)/732),+#REF!*(Z31+X31)) -> #REF! | BN31: =IF(H31="Bundled",#REF!*Y31,#REF!*Y31*0.85) -> #REF! | BO31: =+BE31*Y31 -> #REF! | BP31: =+#REF!*Y31 -> #REF! | BQ31: =+BJ31-BP31 -> #REF! | BR31: =+BK31-BL31 -> #REF! | BS31: =+BQ31+BR31 -> #REF! | BT31: =+Y31 -> #REF! | BU31: =+BE31 -> #REF! | BV31: =IF(H31="Bundled",BN31-BL31,AR31-BL31) -> #REF! | BW31: =IF(H31="Bundled",+(BG31-#REF!)*Y31,(AP31+AQ31)-Y31*#REF!) -> #REF! | BX31: =+BV31+BW31 -> #REF! | BY31: =+BV31/$BT31 -> #REF! | BZ31: =+BW31/$BT31 -> #REF! | CA31: =+BX31/$BT31 -> #REF!
C32: EXTREME CABLES AND BROADBAND (08U-09U) | D32: NO | F32: 45898 | G32: Rated | H32: Bundled | I32: U space | J32: Uncaged | K32: =IF(I32="Rack","No of Racks",(IF(I32="Space","Sq Ft","U Space"))) -> U Space | L32: 2 | M32: 2 | N32: 0 | O32: 2 | R32: Rated | S32: KVA | T32: 0.5 | U32: 0.11 | V32: =T32-U32 -> 0.39 | X32: =IF(V32<=0,0,(IF(R32="Rated",(V32+W32)*#REF!,(V32+W32)))) -> #REF! | Y32: =IF(R32="Rated",T32*#REF!,T32) -> #REF! | AA32: =IF((V32*-1)>0, (V32*-1), 0) -> 0 | AC32: =H32 -> Bundled | AL32: =AJ32-AK32 -> 0
A33: L5 | C33: Sphier Infotech Private Limited | D33: YES | G33: Rated | H33: Bundled | I33: U space | J33: Uncaged | K33: =IF(I33="Rack","No of Racks",(IF(I33="Space","Sq Ft","U Space"))) -> U Space | L33: 1 | M33: 1 | N33: =L33-M33 -> 0 | O33: 1 | Q33: =(35000)/12 -> 2916.6667 | R33: =G33 -> Rated | S33: KVA | T33: 0.25 | U33: 0.17 | V33: =T33-U33 -> 0.08 | X33: =IF(V33<=0,0,(IF(R33="Rated",(V33+W33)*#REF!,(V33+W33)))) -> #REF! | Y33: =IF(R33="Rated",T33*#REF!,T33) -> #REF! | AA33: =IF((V33*-1)>0, (V33*-1), 0) -> 0 | AB33: =90000/12 -> 7500 | AC33: =H33 -> Bundled | AI33: =IF(AH33="No of Seats","No of Seats",(IF(AH33="Space","Sq Ft",""))) | AL33: =AJ33-AK33 -> 0 | AP33: =Q33*O33 -> 2916.6667 | AQ33: =AB33*AA33 -> 0 | AR33: =AG33*AF33*AD33 -> 0 | AS33: =AO33*AM33 -> 0 | AT33: =(20000)/12 -> 1666.6667 | AU33: =SUBTOTAL(9,AP33:AT33) -> 4583.3333 | BC33: =IF(I33="Rack",AU33/L33,0)+IF(I33="U Space",AU33*40/L33,0)+IF(I33="Space",AU33*30/L33,0) -> 183333.33 | BD33: =+AU33/Y33 -> #REF! | BE33: =+($AP33+$AQ33+$AR33-BL33)/$Y33 -> #REF! | BF33: =+($AP33+$AQ33+$AR33-BM33)/$Y33 -> #REF! | BG33: =+($AP33+$AQ33+IF(H33="Bundled",0,Y33*0.85*AD33*AF33*30.5*24)-BN33)/$Y33 -> #REF! | BI33: =+AP33+AQ33+AR33 -> 2916.6667 | BJ33: =+BI33-BK33 -> #REF! | BK33: =IF(H33="Bundled",MIN(Y33*#REF!*(1+#REF!),BI33),AR33) -> #REF! | BL33: =IF($AG33>0,$AG33*#REF!*#REF!*(1+#REF!*(20/#REF!)/732),#REF!*Z33) -> #REF! | BM33: =IF($AG33>0,$AG33*#REF!*#REF!*(1+#REF!*(20/#REF!)/732),+#REF!*(Z33+X33)) -> #REF! | BN33: =IF(H33="Bundled",#REF!*Y33,#REF!*Y33*0.85) -> #REF! | BO33: =+BE33*Y33 -> #REF! | BP33: =+#REF!*Y33 -> #REF! | BQ33: =+BJ33-BP33 -> #REF! | BR33: =+BK33-BL33 -> #REF! | BS33: =+BQ33+BR33 -> #REF! | BT33: =+Y33 -> #REF! | BU33: =+BE33 -> #REF! | BV33: =IF(H33="Bundled",BN33-BL33,AR33-BL33) -> #REF! | BW33: =IF(H33="Bundled",+(BG33-#REF!)*Y33,(AP33+AQ33)-Y33*#REF!) -> #REF! | BX33: =+BV33+BW33 -> #REF! | BY33: =+BV33/$BT33 -> #REF! | BZ33: =+BW33/$BT33 -> #REF! | CA33: =+BX33/$BT33 -> #REF!
A34: L5 | B34: Server Hall 5A L5A-04-11 | C34: SMC INSURANCE BROKERS PVT LTD | D34: NO | G34: Rated | H34: Bundled | I34: U space | J34: Uncaged | K34: =IF(I34="Rack","No of Racks",(IF(I34="Space","Sq Ft","U Space"))) -> U Space | L34: 21 | M34: 21 | N34: =L34-M34 -> 0 | O34: 21 | Q34: =(315000)/21/12 -> 1250 | R34: =G34 -> Rated | S34: KVA | T34: 3 | U34: 6.52 | V34: =T34-U34 -> -3.52 | X34: =IF(V34<=0,0,(IF(R34="Rated",(V34+W34)*#REF!,(V34+W34)))) -> 0 | Y34: =IF(R34="Rated",T34*#REF!,T34) -> #REF! | Z34: 2.03 | AA34: =IF((V34*-1)>0, (V34*-1), 0) -> 3.52 | AB34: =110000/12 -> 9166.6667 | AC34: =H34 -> Bundled | AI34: =IF(AH34="No of Seats","No of Seats",(IF(AH34="Space","Sq Ft",""))) | AL34: =AJ34-AK34 -> 0 | AP34: =Q34*O34 -> 26250 | AQ34: =AB34*AA34 -> 32266.667 | AR34: =AG34*AF34*AD34 -> 0 | AS34: =AO34*AM34 -> 0 | AT34: 0 | AU34: =SUBTOTAL(9,AP34:AT34) -> 58516.667 | BC34: =IF(I34="Rack",AU34/L34,0)+IF(I34="U Space",AU34*40/L34,0)+IF(I34="Space",AU34*30/L34,0) -> 111460.32 | BD34: =+AU34/Y34 -> #REF! | BE34: =+($AP34+$AQ34+$AR34-BL34)/$Y34 -> #REF! | BF34: =+($AP34+$AQ34+$AR34-BM34)/$Y34 -> #REF! | BG34: =+($AP34+$AQ34+IF(H34="Bundled",0,Y34*0.85*AD34*AF34*30.5*24)-BN34)/$Y34 -> #REF! | BI34: =+AP34+AQ34+AR34 -> 58516.667 | BJ34: =+BI34-BK34 -> #REF! | BK34: =IF(H34="Bundled",MIN(Y34*#REF!*(1+#REF!),BI34),AR34) -> #REF! | BL34: =IF($AG34>0,$AG34*#REF!*#REF!*(1+#REF!*(20/#REF!)/732),#REF!*Z34) -> #REF! | BM34: =IF($AG34>0,$AG34*#REF!*#REF!*(1+#REF!*(20/#REF!)/732),+#REF!*(Z34+X34)) -> #REF! | BN34: =IF(H34="Bundled",#REF!*Y34,#REF!*Y34*0.85) -> #REF! | BO34: =+BE34*Y34 -> #REF! | BP34: =+#REF!*Y34 -> #REF! | BQ34: =+BJ34-BP34 -> #REF! | BR34: =+BK34-BL34 -> #REF! | BS34: =+BQ34+BR34 -> #REF! | BT34: =+Y34 -> #REF! | BU34: =+BE34 -> #REF! | BV34: =IF(H34="Bundled",BN34-BL34,AR34-BL34) -> #REF! | BW34: =IF(H34="Bundled",+(BG34-#REF!)*Y34,(AP34+AQ34)-Y34*#REF!) -> #REF! | BX34: =+BV34+BW34 -> #REF! | BY34: =+BV34/$BT34 -> #REF! | BZ34: =+BW34/$BT34 -> #REF! | CA34: =+BX34/$BT34 -> #REF!
A35: L5 | C35: ACME DIGINET CORPORATION PVT LTD | D35: NO | G35: Rated | H35: Bundled | I35: U space | J35: Uncaged | K35: =IF(I35="Rack","No of Racks",(IF(I35="Space","Sq Ft","U Space"))) -> U Space | L35: 4 | M35: 4 | N35: =L35-M35 -> 0 | O35: 4 | R35: Rated | S35: KVA | T35: 1 | U35: 1.1 | V35: =T35-U35 -> -0.1 | AA35: =IF((V35*-1)>0, (V35*-1), 0) -> 0.1 | AC35: =H35 -> Bundled
A36: L5 | C36: Earth Communication | D36: YES | G36: Rated | H36: Bundled | I36: U space | J36: Uncaged | K36: =IF(I36="Rack","No of Racks",(IF(I36="Space","Sq Ft","U Space"))) -> U Space | L36: 11 | M36: 11 | N36: =L36-M36 -> 0 | O36: 11 | R36: =G36 -> Rated | S36: KVA | T36: 2 | U36: 0.67 | V36: =T36-U36 -> 1.33 | X36: =IF(V36<=0,0,(IF(R36="Rated",(V36+W36)*#REF!,(V36+W36)))) -> #REF! | Y36: =IF(R36="Rated",T36*#REF!,T36) -> #REF! | AA36: =IF((V36*-1)>0, (V36*-1), 0) -> 0 | AC36: =H36 -> Bundled | BN36: =IF(H36="Bundled",#REF!*Y36,#REF!*Y36*0.85) -> #REF! | BT36: =+Y36 -> #REF!
A37: L5 | B37: L5A-06-09 | C37: LITE BITE FOODS PVT LTD | D37: NO | G37: Rated | H37: Metered | I37: Rack | J37: Uncaged | K37: =IF(I37="Rack","No of Racks",(IF(I37="Space","Sq Ft","U Space"))) -> No of Racks | L37: 1 | M37: 1 | N37: =L37-M37 -> 0 | O37: 1 | Q37: =276228/12 -> 23019 | R37: =G37 -> Rated | S37: KVA | T37: 5 | U37: 5.23 | V37: =T37-U37 -> -0.23 | X37: =IF(V37<=0,0,(IF(R37="Rated",(V37+W37)*#REF!,(V37+W37)))) -> 0 | Y37: =IF(R37="Rated",T37*#REF!,T37) -> #REF! | Z37: =AG37/28/24 -> 2.0166071 | AA37: =IF((V37*-1)>0, (V37*-1), 0) -> 0.23 | AB37: 0 | AC37: =H37 -> Metered | AD37: 1 | AE37: Fixed | AF37: 15.5 | AG37: 1355.16 | AI37: =IF(AH37="No of Seats","No of Seats",(IF(AH37="Space","Sq Ft",""))) | AL37: =AJ37-AK37 -> 0 | AP37: =Q37*O37 -> 23019 | AQ37: =AB37*AA37 -> 0 | AR37: =AG37*AF37*AD37 -> 21004.98 | AS37: =AO37*AM37 -> 0 | AT37: =(30000)/12 -> 2500 | AU37: =SUBTOTAL(9,AP37:AT37) -> 46523.98 | AW37: 721006343 | BC37: =IF(I37="Rack",AU37/L37,0)+IF(I37="U Space",AU37*40/L37,0)+IF(I37="Space",AU37*30/L37,0) -> 46523.98 | BD37: =+AU37/Y37 -> #REF! | BE37: =+($AP37+$AQ37+$AR37-BL37)/$Y37 -> #REF! | BF37: =+($AP37+$AQ37+$AR37-BM37)/$Y37 -> #REF! | BG37: =+($AP37+$AQ37+IF(H37="Bundled",0,Y37*0.85*AD37*AF37*30.5*24)-BN37)/$Y37 -> #REF! | BI37: =+AP37+AQ37+AR37 -> 44023.98 | BJ37: =+BI37-BK37 -> 23019 | BK37: =IF(H37="Bundled",MIN(Y37*#REF!*(1+#REF!),BI37),AR37) -> 21004.98 | BL37: =IF($AG37>0,$AG37*#REF!*#REF!*(1+#REF!*(20/#REF!)/732),#REF!*Z37) -> #REF! | BM37: =IF($AG37>0,$AG37*#REF!*#REF!*(1+#REF!*(20/#REF!)/732),+#REF!*(Z37+X37)) -> #REF! | BN37: =IF(H37="Bundled",#REF!*Y37,#REF!*Y37*0.85) -> #REF! | BO37: =+BE37*Y37 -> #REF! | BP37: =+#REF!*Y37 -> #REF! | BQ37: =+BJ37-BP37 -> #REF! | BR37: =+BK37-BL37 -> #REF! | BS37: =+BQ37+BR37 -> #REF! | BT37: =+Y37 -> #REF! | BU37: =+BE37 -> #REF! | BV37: =IF(H37="Bundled",BN37-BL37,AR37-BL37) -> #REF! | BW37: =IF(H37="Bundled",+(BG37-#REF!)*Y37,(AP37+AQ37)-Y37*#REF!) -> #REF! | BX37: =+BV37+BW37 -> #REF! | BY37: =+BV37/$BT37 -> #REF! | BZ37: =+BW37/$BT37 -> #REF! | CA37: =+BX37/$BT37 -> #REF!
A38: L5 | B38: L5A-07-10 | C38: TELANGANA STATE COOPERATIVE APEX BANK LTD | D38: NO | G38: Rated | H38: Bundled | I38: Rack | J38: Uncaged | K38: =IF(I38="Rack","No of Racks",(IF(I38="Space","Sq Ft","U Space"))) -> No of Racks | L38: 1 | M38: 1 | N38: =L38-M38 -> 0 | O38: 1 | Q38: =480000/12 -> 40000 | R38: =G38 -> Rated | S38: KVA | T38: 6 | U38: 19.35 | V38: =T38-U38 -> -13.35 | X38: =IF(V38<=0,0,(IF(R38="Rated",(V38+W38)*#REF!,(V38+W38)))) -> 0 | Y38: =IF(R38="Rated",T38*#REF!,T38) -> #REF! | Z38: 2.87 | AA38: =IF((V38*-1)>0, (V38*-1), 0) -> 13.35 | AB38: =90000/12 -> 7500 | AC38: =H38 -> Bundled | AI38: =IF(AH38="No of Seats","No of Seats",(IF(AH38="Space","Sq Ft",""))) | AL38: =AJ38-AK38 -> 0 | AP38: =Q38*O38 -> 40000 | AQ38: =AB38*AA38 -> 100125 | AR38: =AG38*AF38*AD38 -> 0 | AS38: =AO38*AM38 -> 0 | AT38: 0 | AU38: =SUBTOTAL(9,AP38:AT38) -> 140125 | BC38: =IF(I38="Rack",AU38/L38,0)+IF(I38="U Space",AU38*40/L38,0)+IF(I38="Space",AU38*30/L38,0) -> 140125 | BD38: =+AU38/Y38 -> #REF! | BE38: =+($AP38+$AQ38+$AR38-BL38)/$Y38 -> #REF! | BF38: =+($AP38+$AQ38+$AR38-BM38)/$Y38 -> #REF! | BG38: =+($AP38+$AQ38+IF(H38="Bundled",0,Y38*0.85*AD38*AF38*30.5*24)-BN38)/$Y38 -> #REF! | BI38: =+AP38+AQ38+AR38 -> 140125 | BJ38: =+BI38-BK38 -> #REF! | BK38: =IF(H38="Bundled",MIN(Y38*#REF!*(1+#REF!),BI38),AR38) -> #REF! | BL38: =IF($AG38>0,$AG38*#REF!*#REF!*(1+#REF!*(20/#REF!)/732),#REF!*Z38) -> #REF! | BM38: =IF($AG38>0,$AG38*#REF!*#REF!*(1+#REF!*(20/#REF!)/732),+#REF!*(Z38+X38)) -> #REF! | BN38: =IF(H38="Bundled",#REF!*Y38,#REF!*Y38*0.85) -> #REF! | BO38: =+BE38*Y38 -> #REF! | BP38: =+#REF!*Y38 -> #REF! | BQ38: =+BJ38-BP38 -> #REF! | BR38: =+BK38-BL38 -> #REF! | BS38: =+BQ38+BR38 -> #REF! | BT38: =+Y38 -> #REF! | BU38: =+BE38 -> #REF! | BV38: =IF(H38="Bundled",BN38-BL38,AR38-BL38) -> #REF! | BW38: =IF(H38="Bundled",+(BG38-#REF!)*Y38,(AP38+AQ38)-Y38*#REF!) -> #REF! | BX38: =+BV38+BW38 -> #REF! | BY38: =+BV38/$BT38 -> #REF! | BZ38: =+BW38/$BT38 -> #REF! | CA38: =+BX38/$BT38 -> #REF!
A39: L5 | B39: L5A-07-08 & L5A-07-09 | C39: PIONEER ELABS LIMITED | D39: NO | G39: Rated | H39: Bundled | I39: Rack | J39: Uncaged | K39: =IF(I39="Rack","No of Racks",(IF(I39="Space","Sq Ft","U Space"))) -> No of Racks | L39: 2 | M39: 2 | N39: 0 | O39: 2 | R39: =G39 -> Rated | S39: KVA | T39: 6 | U39: 3.19 | V39: =T39-U39 -> 2.81 | X39: =IF(V39<=0,0,(IF(R39="Rated",(V39+W39)*#REF!,(V39+W39)))) -> #REF! | Y39: =IF(R39="Rated",T39*#REF!,T39) -> #REF! | Z39: 77 | AA39: =IF((V39*-1)>0, (V39*-1), 0) -> 0 | AB39: =90000/12 -> 7500 | AC39: =H39 -> Bundled | AI39: =IF(AH39="No of Seats","No of Seats",(IF(AH39="Space","Sq Ft",""))) | AL39: =AJ39-AK39 -> 0 | AP39: =Q39*O39 -> 0 | AQ39: =AB39*AA39 -> 0 | AR39: =AG39*AF39*AD39 -> 0 | AS39: =AO39*AM39 -> 0 | AT39: 0 | AU39: =SUBTOTAL(9,AP39:AT39) -> 0 | BC39: =IF(I39="Rack",AU39/L39,0)+IF(I39="U Space",AU39*40/L39,0)+IF(I39="Space",AU39*30/L39,0) -> 0 | BD39: =+AU39/Y39 -> #REF! | BE39: =+($AP39+$AQ39+$AR39-BL39)/$Y39 -> #REF! | BF39: =+($AP39+$AQ39+$AR39-BM39)/$Y39 -> #REF! | BG39: =+($AP39+$AQ39+IF(H39="Bundled",0,Y39*0.85*AD39*AF39*30.5*24)-BN39)/$Y39 -> #REF! | BI39: =+AP39+AQ39+AR39 -> 0 | BJ39: =+BI39-BK39 -> #REF! | BK39: =IF(H39="Bundled",MIN(Y39*#REF!*(1+#REF!),BI39),AR39) -> #REF! | BL39: =IF($AG39>0,$AG39*#REF!*#REF!*(1+#REF!*(20/#REF!)/732),#REF!*Z39) -> #REF! | BM39: =IF($AG39>0,$AG39*#REF!*#REF!*(1+#REF!*(20/#REF!)/732),+#REF!*(Z39+X39)) -> #REF! | BN39: =IF(H39="Bundled",#REF!*Y39,#REF!*Y39*0.85) -> #REF! | BO39: =+BE39*Y39 -> #REF! | BP39: =+#REF!*Y39 -> #REF! | BQ39: =+BJ39-BP39 -> #REF! | BR39: =+BK39-BL39 -> #REF! | BS39: =+BQ39+BR39 -> #REF! | BT39: =+Y39 -> #REF! | BU39: =+BE39 -> #REF! | BV39: =IF(H39="Bundled",BN39-BL39,AR39-BL39) -> #REF! | BW39: =IF(H39="Bundled",+(BG39-#REF!)*Y39,(AP39+AQ39)-Y39*#REF!) -> #REF! | BX39: =+BV39+BW39 -> #REF! | BY39: =+BV39/$BT39 -> #REF! | BZ39: =+BW39/$BT39 -> #REF! | CA39: =+BX39/$BT39 -> #REF!
A40: L5 | B40: L5A-04-08 & L5A-04-09 | C40: FASTLY INDIA PRIVATE LIMITED | D40: YES | G40: Subscribed | H40: Bundled | I40: Rack | J40: Uncaged | K40: =IF(I40="Rack","No of Racks",(IF(I40="Space","Sq Ft","U Space"))) -> No of Racks | L40: 2 | M40: 2 | N40: =L40-M40 -> 0 | O40: 2 | Q40: =123982 -> 123982 | R40: =G40 -> Subscribed | S40: KVA | T40: 14 | U40: =Z40/0.9 -> 14.471842 | V40: =T40-U40 -> -0.47184193 | X40: =IF(V40<=0,0,(IF(R40="Rated",(V40+W40)*#REF!,(V40+W40)))) -> 0 | Y40: =IF(R40="Rated",T40*#REF!,T40) -> 14 | Z40: =AG40/28/24 -> 13.024658 | AA40: =IF((V40*-1)>0, (V40*-1), 0) -> 0.47184193 | AB40: =17711 -> 17711 | AC40: =H40 -> Bundled | AD40: 1 | AE40: Fixed | AF40: 0 | AG40: 8752.57 | AL40: =AJ40-AK40 -> 0 | AP40: =Q40*O40 -> 247964 | AQ40: =AB40*AA40 -> 8356.7924 | AR40: =AG40*AF40*AD40 -> 0 | AS40: =AO40*AM40 -> 0 | AT40: 0 | AU40: =SUBTOTAL(9,AP40:AT40) -> 256320.79 | AW40: 721007392 | BC40: =IF(I40="Rack",AU40/L40,0)+IF(I40="U Space",AU40*40/L40,0)+IF(I40="Space",AU40*30/L40,0) -> 128160.4 | BD40: =+AU40/Y40 -> 18308.628 | BE40: =+($AP40+$AQ40+$AR40-BL40)/$Y40 -> #REF! | BF40: =+($AP40+$AQ40+$AR40-BM40)/$Y40 -> #REF! | BG40: =+($AP40+$AQ40+IF(H40="Bundled",0,Y40*0.85*AD40*AF40*30.5*24)-BN40)/$Y40 -> #REF! | BI40: =+AP40+AQ40+AR40 -> 256320.79 | BJ40: =+BI40-BK40 -> #REF! | BK40: =IF(H40="Bundled",MIN(Y40*#REF!*(1+#REF!),BI40),AR40) -> #REF! | BL40: =IF($AG40>0,$AG40*#REF!*#REF!*(1+#REF!*(20/#REF!)/732),#REF!*Z40) -> #REF! | BM40: =IF($AG40>0,$AG40*#REF!*#REF!*(1+#REF!*(20/#REF!)/732),+#REF!*(Z40+X40)) -> #REF! | BN40: =IF(H40="Bundled",#REF!*Y40,#REF!*Y40*0.85) -> #REF! | BO40: =+BE40*Y40 -> #REF! | BP40: =+#REF!*Y40 -> #REF! | BQ40: =+BJ40-BP40 -> #REF! | BR40: =+BK40-BL40 -> #REF! | BS40: =+BQ40+BR40 -> #REF! | BT40: =+Y40 -> 14 | BU40: =+BE40 -> #REF! | BV40: =IF(H40="Bundled",BN40-BL40,AR40-BL40) -> #REF! | BW40: =IF(H40="Bundled",+(BG40-#REF!)*Y40,(AP40+AQ40)-Y40*#REF!) -> #REF! | BX40: =+BV40+BW40 -> #REF! | BY40: =+BV40/$BT40 -> #REF! | BZ40: =+BW40/$BT40 -> #REF! | CA40: =+BX40/$BT40 -> #REF!
A41: L5 | B41: L5A-06-11 | C41: EXTREME INFOCOM PVT LTD | D41: NO | G41: Rated | H41: Bundled | I41: Rack | J41: Uncaged | K41: =IF(I41="Rack","No of Racks",(IF(I41="Space","Sq Ft","U Space"))) -> No of Racks | L41: 1 | M41: 1 | N41: =L41-M41 -> 0 | O41: 1 | Q41: =(160000)/12 -> 13333.333 | R41: =G41 -> Rated | S41: KVA | T41: 2 | U41: 2.5 | V41: =T41-U41 -> -0.5 | X41: =IF(V41<=0,0,(IF(R41="Rated",(V41+W41)*#REF!,(V41+W41)))) -> 0 | Y41: =IF(R41="Rated",T41*#REF!,T41) -> #REF! | Z41: 2.17 | AA41: =IF((V41*-1)>0, (V41*-1), 0) -> 0.5 | AB41: =125000/12 -> 10416.667 | AC41: =H41 -> Bundled | AL41: =AJ41-AK41 -> 0 | AP41: =Q41*O41 -> 13333.333 | AQ41: =AB41*AA41 -> 5208.3333 | AR41: =AG41*AF41*AD41 -> 0 | AS41: =AO41*AM41 -> 0 | AT41: =(30000)/12 -> 2500 | AU41: =SUBTOTAL(9,AP41:AT41) -> 21041.667 | AW41: 121000056 | BC41: =IF(I41="Rack",AU41/L41,0)+IF(I41="U Space",AU41*40/L41,0)+IF(I41="Space",AU41*30/L41,0) -> 21041.667 | BD41: =+AU41/Y41 -> #REF! | BE41: =+($AP41+$AQ41+$AR41-BL41)/$Y41 -> #REF! | BF41: =+($AP41+$AQ41+$AR41-BM41)/$Y41 -> #REF! | BG41: =+($AP41+$AQ41+IF(H41="Bundled",0,Y41*0.85*AD41*AF41*30.5*24)-BN41)/$Y41 -> #REF! | BI41: =+AP41+AQ41+AR41 -> 18541.667 | BJ41: =+BI41-BK41 -> #REF! | BK41: =IF(H41="Bundled",MIN(Y41*#REF!*(1+#REF!),BI41),AR41) -> #REF! | BL41: =IF($AG41>0,$AG41*#REF!*#REF!*(1+#REF!*(20/#REF!)/732),#REF!*Z41) -> #REF! | BM41: =IF($AG41>0,$AG41*#REF!*#REF!*(1+#REF!*(20/#REF!)/732),+#REF!*(Z41+X41)) -> #REF! | BN41: =IF(H41="Bundled",#REF!*Y41,#REF!*Y41*0.85) -> #REF! | BO41: =+BE41*Y41 -> #REF! | BP41: =+#REF!*Y41 -> #REF! | BQ41: =+BJ41-BP41 -> #REF! | BR41: =+BK41-BL41 -> #REF! | BS41: =+BQ41+BR41 -> #REF! | BT41: =+Y41 -> #REF! | BU41: =+BE41 -> #REF! | BV41: =IF(H41="Bundled",BN41-BL41,AR41-BL41) -> #REF! | BW41: =IF(H41="Bundled",+(BG41-#REF!)*Y41,(AP41+AQ41)-Y41*#REF!) -> #REF! | BX41: =+BV41+BW41 -> #REF! | BY41: =+BV41/$BT41 -> #REF! | BZ41: =+BW41/$BT41 -> #REF! | CA41: =+BX41/$BT41 -> #REF!
A42: L5 | B42: L5A-06-04 | C42: D.S. Tech Cyber/ FASUTONETTO SERVICES PRIVATE LIMITED | D42: NO | G42: Subscribed | H42: Metered | I42: Rack | J42: Uncaged | K42: =IF(I42="Rack","No of Racks",(IF(I42="Space","Sq Ft","U Space"))) -> No of Racks | L42: 1 | M42: 1 | N42: =L42-M42 -> 0 | O42: 1 | Q42: =(340000)/12 -> 28333.333 | R42: =G42 -> Subscribed | S42: KW | T42: 3 | U42: =Z42 -> 1.0084226 | V42: =T42-U42 -> 1.9915774 | X42: =IF(V42<=0,0,(IF(R42="Rated",(V42+W42)*#REF!,(V42+W42)))) -> 1.9915774 | Y42: =IF(R42="Rated",T42*#REF!,T42) -> 3 | Z42: =AG42/28/24 -> 1.0084226 | AA42: =IF((V42*-1)>0, (V42*-1), 0) -> 0 | AB42: =80000/12 -> 6666.6667 | AC42: =H42 -> Metered | AD42: 1 | AE42: Fixed | AF42: 18 | AG42: 677.66 | AL42: =AJ42-AK42 -> 0 | AP42: =Q42*O42 -> 28333.333 | AQ42: =AB42*AA42 -> 0 | AR42: =AG42*AF42*AD42 -> 12197.88 | AS42: =AO42*AM42 -> 0 | AT42: =360000/12 -> 30000 | AU42: =SUBTOTAL(9,AP42:AT42) -> 70531.213 | AW42: 121000302 | BC42: =IF(I42="Rack",AU42/L42,0)+IF(I42="U Space",AU42*40/L42,0)+IF(I42="Space",AU42*30/L42,0) -> 70531.213 | BD42: =+AU42/Y42 -> 23510.404 | BE42: =+($AP42+$AQ42+$AR42-BL42)/$Y42 -> #REF! | BF42: =+($AP42+$AQ42+$AR42-BM42)/$Y42 -> #REF! | BG42: =+($AP42+$AQ42+IF(H42="Bundled",0,Y42*0.85*AD42*AF42*30.5*24)-BN42)/$Y42 -> #REF! | BI42: =+AP42+AQ42+AR42 -> 40531.213 | BJ42: =+BI42-BK42 -> 28333.333 | BK42: =IF(H42="Bundled",MIN(Y42*#REF!*(1+#REF!),BI42),AR42) -> 12197.88 | BL42: =IF($AG42>0,$AG42*#REF!*#REF!*(1+#REF!*(20/#REF!)/732),#REF!*Z42) -> #REF! | BM42: =IF($AG42>0,$AG42*#REF!*#REF!*(1+#REF!*(20/#REF!)/732),+#REF!*(Z42+X42)) -> #REF! | BN42: =IF(H42="Bundled",#REF!*Y42,#REF!*Y42*0.85) -> #REF! | BO42: =+BE42*Y42 -> #REF! | BP42: =+#REF!*Y42 -> #REF! | BQ42: =+BJ42-BP42 -> #REF! | BR42: =+BK42-BL42 -> #REF! | BS42: =+BQ42+BR42 -> #REF! | BT42: =+Y42 -> 3 | BU42: =+BE42 -> #REF! | BV42: =IF(H42="Bundled",BN42-BL42,AR42-BL42) -> #REF! | BW42: =IF(H42="Bundled",+(BG42-#REF!)*Y42,(AP42+AQ42)-Y42*#REF!) -> #REF! | BX42: =+BV42+BW42 -> #REF! | BY42: =+BV42/$BT42 -> #REF! | BZ42: =+BW42/$BT42 -> #REF! | CA42: =+BX42/$BT42 -> #REF!
A43: L5 | B43: L5A-01-07 | C43: SOFTECH INFOSOL PVT LTD | D43: YES | G43: Rated | H43: Bundled | I43: U space | J43: Uncaged | K43: =IF(I43="Rack","No of Racks",(IF(I43="Space","Sq Ft","U Space"))) -> U Space | L43: 21 | M43: 21 | N43: =L43-M43 -> 0 | O43: 21 | Q43: =(400000)/12 -> 33333.333 | R43: =G43 -> Rated | S43: KVA | T43: 1.5 | U43: 5.33 | V43: =T43-U43 -> -3.83 | X43: =IF(V43<=0,0,(IF(R43="Rated",(V43+W43)*#REF!,(V43+W43)))) -> 0 | Y43: =IF(R43="Rated",T43*#REF!,T43) -> #REF! | Z43: 3.38 | AA43: =IF((V43*-1)>0, (V43*-1), 0) -> 3.83 | AB43: =80000/12 -> 6666.6667 | AC43: =H43 -> Bundled | AL43: =AJ43-AK43 -> 0 | AP43: =Q43*O43 -> 700000 | AQ43: =AB43*AA43 -> 25533.333 | AR43: =AG43*AF43*AD43 -> 0 | AS43: =AO43*AM43 -> 0 | AT43: =(40000+5000)/12 -> 3750 | AU43: =SUBTOTAL(9,AP43:AT43) -> 729283.33 | AW43: 121000827 | BC43: =IF(I43="Rack",AU43/L43,0)+IF(I43="U Space",AU43*40/L43,0)+IF(I43="Space",AU43*30/L43,0) -> 1389111.1 | BD43: =+AU43/Y43 -> #REF! | BE43: =+($AP43+$AQ43+$AR43-BL43)/$Y43 -> #REF! | BF43: =+($AP43+$AQ43+$AR43-BM43)/$Y43 -> #REF! | BG43: =+($AP43+$AQ43+IF(H43="Bundled",0,Y43*0.85*AD43*AF43*30.5*24)-BN43)/$Y43 -> #REF! | BI43: =+AP43+AQ43+AR43 -> 725533.33 | BJ43: =+BI43-BK43 -> #REF! | BK43: =IF(H43="Bundled",MIN(Y43*#REF!*(1+#REF!),BI43),AR43) -> #REF! | BL43: =IF($AG43>0,$AG43*#REF!*#REF!*(1+#REF!*(20/#REF!)/732),#REF!*Z43) -> #REF! | BM43: =IF($AG43>0,$AG43*#REF!*#REF!*(1+#REF!*(20/#REF!)/732),+#REF!*(Z43+X43)) -> #REF! | BN43: =IF(H43="Bundled",#REF!*Y43,#REF!*Y43*0.85) -> #REF! | BO43: =+BE43*Y43 -> #REF! | BP43: =+#REF!*Y43 -> #REF! | BQ43: =+BJ43-BP43 -> #REF! | BR43: =+BK43-BL43 -> #REF! | BS43: =+BQ43+BR43 -> #REF! | BT43: =+Y43 -> #REF! | BU43: =+BE43 -> #REF! | BV43: =IF(H43="Bundled",BN43-BL43,AR43-BL43) -> #REF! | BW43: =IF(H43="Bundled",+(BG43-#REF!)*Y43,(AP43+AQ43)-Y43*#REF!) -> #REF! | BX43: =+BV43+BW43 -> #REF! | BY43: =+BV43/$BT43 -> #REF! | BZ43: =+BW43/$BT43 -> #REF! | CA43: =+BX43/$BT43 -> #REF!
C44: FALCONET INTERNET PRIVATE LIMITED(11U) | D44: NO | G44: Rated | H44: Bundled | I44: U space | J44: Uncaged | K44: =IF(I44="Rack","No of Racks",(IF(I44="Space","Sq Ft","U Space"))) -> U Space | L44: 1 | M44: 1 | N44: =L44-M44 -> 0 | O44: 1 | R44: =G44 -> Rated | S44: KVA | T44: 0.25 | U44: 0.27 | V44: =T44-U44 -> -0.02 | X44: =IF(V44<=0,0,(IF(R44="Rated",(V44+W44)*#REF!,(V44+W44)))) -> 0 | Y44: =IF(R44="Rated",T44*#REF!,T44) -> #REF! | AA44: =IF((V44*-1)>0, (V44*-1), 0) -> 0.02 | AC44: =H44 -> Bundled | BN44: =IF(H44="Bundled",#REF!*Y44,#REF!*Y44*0.85) -> #REF! | BT44: =+Y44 -> #REF!
C45: BLAZENET LIMITED(8U-9U) | D45: NO | G45: Rated | H45: Bundled | I45: U space | J45: Uncaged | K45: =IF(I45="Rack","No of Racks",(IF(I45="Space","Sq Ft","U Space"))) -> U Space | L45: 2 | M45: 2 | N45: =L45-M45 -> 0 | O45: 2 | R45: =G45 -> Rated | S45: KVA | T45: 0.5 | U45: 0.44 | V45: =T45-U45 -> 0.06 | X45: =IF(V45<=0,0,(IF(R45="Rated",(V45+W45)*#REF!,(V45+W45)))) -> #REF! | Y45: =IF(R45="Rated",T45*#REF!,T45) -> #REF! | AA45: =IF((V45*-1)>0, (V45*-1), 0) -> 0 | AC45: =H45 -> Bundled | BN45: =IF(H45="Bundled",#REF!*Y45,#REF!*Y45*0.85) -> #REF! | BT45: =+Y45 -> #REF!
C46: LALAT COMMUNICATIONS(6U) | D46: NO | G46: Rated | H46: Bundled | I46: U space | J46: Uncaged | K46: =IF(I46="Rack","No of Racks",(IF(I46="Space","Sq Ft","U Space"))) -> U Space | L46: 1 | M46: 1 | N46: =L46-M46 -> 0 | O46: 1 | R46: =G46 -> Rated | S46: KVA | T46: 0.5 | U46: 0.19 | V46: =T46-U46 -> 0.31 | X46: =IF(V46<=0,0,(IF(R46="Rated",(V46+W46)*#REF!,(V46+W46)))) -> #REF! | Y46: =IF(R46="Rated",T46*#REF!,T46) -> #REF! | AA46: =IF((V46*-1)>0, (V46*-1), 0) -> 0 | AC46: =H46 -> Bundled | BN46: =IF(H46="Bundled",#REF!*Y46,#REF!*Y46*0.85) -> #REF! | BT46: =+Y46 -> #REF!
C47: My Next Film (2U-3U) | D47: NO | G47: Rated | H47: Bundled | I47: U space | J47: Uncaged | K47: =IF(I47="Rack","No of Racks",(IF(I47="Space","Sq Ft","U Space"))) -> U Space | L47: 2 | M47: 2 | N47: =L47-M47 -> 0 | O47: 2 | R47: =G47 -> Rated | S47: KVA | T47: 0.25 | U47: 1.04 | V47: =T47-U47 -> -0.79 | X47: =IF(V47<=0,0,(IF(R47="Rated",(V47+W47)*#REF!,(V47+W47)))) -> 0 | Y47: =IF(R47="Rated",T47*#REF!,T47) -> #REF! | AA47: =IF((V47*-1)>0, (V47*-1), 0) -> 0.79 | AC47: =H47 -> Bundled | BN47: =IF(H47="Bundled",#REF!*Y47,#REF!*Y47*0.85) -> #REF! | BT47: =+Y47 -> #REF!
A48: L5 | B48: L5A-04-10 | C48: KDDI INDIA-CONNECTIVITY | D48: YES | G48: Rated | H48: Bundled | I48: Rack | J48: Uncaged | K48: =IF(I48="Rack","No of Racks",(IF(I48="Space","Sq Ft","U Space"))) -> No of Racks | L48: 1 | M48: 1 | N48: =L48-M48 -> 0 | O48: 1 | Q48: =672600/12 -> 56050 | R48: =G48 -> Rated | S48: KVA | T48: 5 | U48: 7.64 | V48: =T48-U48 -> -2.64 | X48: =IF(V48<=0,0,(IF(R48="Rated",(V48+W48)*#REF!,(V48+W48)))) -> 0 | Y48: =IF(R48="Rated",T48*#REF!,T48) -> #REF! | Z48: 1.32 | AA48: =IF((V48*-1)>0, (V48*-1), 0) -> 2.64 | AB48: =110000/12 -> 9166.6667 | AC48: =H48 -> Bundled | AL48: =AJ48-AK48 -> 0 | AP48: =Q48*O48 -> 56050 | AQ48: =AB48*AA48 -> 24200 | AR48: =AG48*AF48*AD48 -> 0 | AS48: =AO48*AM48 -> 0 | AT48: 0 | AU48: =SUBTOTAL(9,AP48:AT48) -> 80250 | AW48: 121001543 | BC48: =IF(I48="Rack",AU48/L48,0)+IF(I48="U Space",AU48*40/L48,0)+IF(I48="Space",AU48*30/L48,0) -> 80250 | BD48: =+AU48/Y48 -> #REF! | BE48: =+($AP48+$AQ48+$AR48-BL48)/$Y48 -> #REF! | BF48: =+($AP48+$AQ48+$AR48-BM48)/$Y48 -> #REF! | BG48: =+($AP48+$AQ48+IF(H48="Bundled",0,Y48*0.85*AD48*AF48*30.5*24)-BN48)/$Y48 -> #REF! | BI48: =+AP48+AQ48+AR48 -> 80250 | BJ48: =+BI48-BK48 -> #REF! | BK48: =IF(H48="Bundled",MIN(Y48*#REF!*(1+#REF!),BI48),AR48) -> #REF! | BL48: =IF($AG48>0,$AG48*#REF!*#REF!*(1+#REF!*(20/#REF!)/732),#REF!*Z48) -> #REF! | BM48: =IF($AG48>0,$AG48*#REF!*#REF!*(1+#REF!*(20/#REF!)/732),+#REF!*(Z48+X48)) -> #REF! | BN48: =IF(H48="Bundled",#REF!*Y48,#REF!*Y48*0.85) -> #REF! | BO48: =+BE48*Y48 -> #REF! | BP48: =+#REF!*Y48 -> #REF! | BQ48: =+BJ48-BP48 -> #REF! | BR48: =+BK48-BL48 -> #REF! | BS48: =+BQ48+BR48 -> #REF! | BT48: =+Y48 -> #REF! | BU48: =+BE48 -> #REF! | BV48: =IF(H48="Bundled",BN48-BL48,AR48-BL48) -> #REF! | BW48: =IF(H48="Bundled",+(BG48-#REF!)*Y48,(AP48+AQ48)-Y48*#REF!) -> #REF! | BX48: =+BV48+BW48 -> #REF! | BY48: =+BV48/$BT48 -> #REF! | BZ48: =+BW48/$BT48 -> #REF! | CA48: =+BX48/$BT48 -> #REF!
A49: L5 | B49: L5A-01-03 | C49: MUNJAL AUTO INDUSTRIES LTD - SOLUTIONS | D49: NO | G49: Rated | H49: Bundled | I49: Rack | J49: Uncaged | K49: =IF(I49="Rack","No of Racks",(IF(I49="Space","Sq Ft","U Space"))) -> No of Racks | L49: 1 | M49: 1 | N49: =L49-M49 -> 0 | O49: 1 | Q49: =768700/12 -> 64058.333 | R49: =G49 -> Rated | S49: KVA | T49: 7 | U49: 7.32 | V49: =T49-U49 -> -0.32 | X49: =IF(V49<=0,0,(IF(R49="Rated",(V49+W49)*#REF!,(V49+W49)))) -> 0 | Y49: =IF(R49="Rated",T49*#REF!,T49) -> #REF! | Z49: 1.69 | AA49: =IF((V49*-1)>0, (V49*-1), 0) -> 0.32 | AB49: =90000/12 -> 7500 | AC49: =H49 -> Bundled | AL49: =AJ49-AK49 -> 0 | AP49: =Q49*O49 -> 64058.333 | AQ49: =AB49*AA49 -> 2400 | AR49: =AG49*AF49*AD49 -> 0 | AS49: =AO49*AM49 -> 0 | AT49: 0 | AU49: =SUBTOTAL(9,AP49:AT49) -> 66458.333 | BC49: =IF(I49="Rack",AU49/L49,0)+IF(I49="U Space",AU49*40/L49,0)+IF(I49="Space",AU49*30/L49,0) -> 66458.333 | BD49: =+AU49/Y49 -> #REF! | BE49: =+($AP49+$AQ49+$AR49-BL49)/$Y49 -> #REF! | BF49: =+($AP49+$AQ49+$AR49-BM49)/$Y49 -> #REF! | BG49: =+($AP49+$AQ49+IF(H49="Bundled",0,Y49*0.85*AD49*AF49*30.5*24)-BN49)/$Y49 -> #REF! | BI49: =+AP49+AQ49+AR49 -> 66458.333 | BJ49: =+BI49-BK49 -> #REF! | BK49: =IF(H49="Bundled",MIN(Y49*#REF!*(1+#REF!),BI49),AR49) -> #REF! | BL49: =IF($AG49>0,$AG49*#REF!*#REF!*(1+#REF!*(20/#REF!)/732),#REF!*Z49) -> #REF! | BM49: =IF($AG49>0,$AG49*#REF!*#REF!*(1+#REF!*(20/#REF!)/732),+#REF!*(Z49+X49)) -> #REF! | BN49: =IF(H49="Bundled",#REF!*Y49,#REF!*Y49*0.85) -> #REF! | BO49: =+BE49*Y49 -> #REF! | BP49: =+#REF!*Y49 -> #REF! | BQ49: =+BJ49-BP49 -> #REF! | BR49: =+BK49-BL49 -> #REF! | BS49: =+BQ49+BR49 -> #REF! | BT49: =+Y49 -> #REF! | BU49: =+BE49 -> #REF! | BV49: =IF(H49="Bundled",BN49-BL49,AR49-BL49) -> #REF! | BW49: =IF(H49="Bundled",+(BG49-#REF!)*Y49,(AP49+AQ49)-Y49*#REF!) -> #REF! | BX49: =+BV49+BW49 -> #REF! | BY49: =+BV49/$BT49 -> #REF! | BZ49: =+BW49/$BT49 -> #REF! | CA49: =+BX49/$BT49 -> #REF!
B50: L5B-01-09 | C50: NXTRA DATA LIMITED | D50: NO | G50: Rated | H50: Bundled | I50: Rack | J50: Uncaged | K50: =IF(I50="Rack","No of Racks",(IF(I50="Space","Sq Ft","U Space"))) -> No of Racks | L50: 1 | M50: 1 | N50: =L50-M50 -> 0 | O50: 1 | R50: =G50 -> Rated | S50: KVA | T50: 3 | V50: =T50-U50 -> 3 | X50: =IF(V50<=0,0,(IF(R50="Rated",(V50+W50)*#REF!,(V50+W50)))) -> #REF! | Y50: =IF(R50="Rated",T50*#REF!,T50) -> #REF! | Z50: =AG50/28/24 -> 0.74702381 | AC50: =H50 -> Bundled | AG50: 502 | BN50: =IF(H50="Bundled",#REF!*Y50,#REF!*Y50*0.85) -> #REF! | BT50: =+Y50 -> #REF!
A51: L5 | B51: L5B-02-01, L5B-02-02, L5B-03-01, L5B-03-02 & L5B-03-03 | C51: TATA Fiber Play BROADBAND PRIVATE LIMITED | D51: YES | E51: 1 | G51: Subscribed | H51: Metered | I51: Rack | J51: Uncaged | K51: =IF(I51="Rack","No of Racks",(IF(I51="Space","Sq Ft","U Space"))) -> No of Racks | L51: 5 | M51: 5 | N51: =L51-M51 -> 0 | O51: 5 | Q51: =240000/12 -> 20000 | R51: =G51 -> Subscribed | S51: KW | T51: 15 | U51: =Z51 -> 8.3554613 | V51: =T51-U51 -> 6.6445387 | X51: =IF(V51<=0,0,(IF(R51="Rated",(V51+W51)*#REF!,(V51+W51)))) -> 6.6445387 | Y51: =IF(R51="Rated",T51*#REF!,T51) -> 15 | Z51: =AG51/28/24 -> 8.3554613 | AA51: =IF((V51*-1)>0, (V51*-1), 0) -> 0 | AB51: =90000/12 -> 7500 | AC51: =H51 -> Metered | AD51: 1 | AE51: Fixed | AF51: =10.5*1.7 -> 17.85 | AG51: 5614.87 | AH51: No of Seats | AI51: No of Seats | AJ51: 1 | AK51: 1 | AL51: =AJ51-AK51 -> 0 | AM51: 1 | AP51: =Q51*O51 -> 100000 | AQ51: =AB51*AA51 -> 0 | AR51: =AG51*AF51*AD51 -> 100225.43 | AS51: =AO51*AM51 -> 0 | AT51: 0 | AU51: =SUBTOTAL(9,AP51:AT51) -> 200225.43 | BC51: =IF(I51="Rack",AU51/L51,0)+IF(I51="U Space",AU51*40/L51,0)+IF(I51="Space",AU51*30/L51,0) -> 40045.086 | BD51: =+AU51/Y51 -> 13348.362 | BE51: =+($AP51+$AQ51+$AR51-BL51)/$Y51 -> #REF! | BF51: =+($AP51+$AQ51+$AR51-BM51)/$Y51 -> #REF! | BG51: =+($AP51+$AQ51+IF(H51="Bundled",0,Y51*0.85*AD51*AF51*30.5*24)-BN51)/$Y51 -> #REF! | BI51: =+AP51+AQ51+AR51 -> 200225.43 | BJ51: =+BI51-BK51 -> 100000 | BK51: =IF(H51="Bundled",MIN(Y51*#REF!*(1+#REF!),BI51),AR51) -> 100225.43 | BL51: =IF($AG51>0,$AG51*#REF!*#REF!*(1+#REF!*(20/#REF!)/732),#REF!*Z51) -> #REF! | BM51: =IF($AG51>0,$AG51*#REF!*#REF!*(1+#REF!*(20/#REF!)/732),+#REF!*(Z51+X51)) -> #REF! | BN51: =IF(H51="Bundled",#REF!*Y51,#REF!*Y51*0.85) -> #REF! | BO51: =+BE51*Y51 -> #REF! | BP51: =+#REF!*Y51 -> #REF! | BQ51: =+BJ51-BP51 -> #REF! | BR51: =+BK51-BL51 -> #REF! | BS51: =+BQ51+BR51 -> #REF! | BT51: =+Y51 -> 15 | BU51: =+BE51 -> #REF! | BV51: =IF(H51="Bundled",BN51-BL51,AR51-BL51) -> #REF! | BW51: =IF(H51="Bundled",+(BG51-#REF!)*Y51,(AP51+AQ51)-Y51*#REF!) -> #REF! | BX51: =+BV51+BW51 -> #REF! | BY51: =+BV51/$BT51 -> #REF! | BZ51: =+BW51/$BT51 -> #REF! | CA51: =+BX51/$BT51 -> #REF!
A52: L5 | B52: L5B-01-07, L5B-01-05 & L5B-06 | C52: DEHRADUN E NET SOLUTIONS (P) LTD. | D52: YES | G52: Subscribed | H52: Metered | I52: Rack | J52: Uncaged | K52: =IF(I52="Rack","No of Racks",(IF(I52="Space","Sq Ft","U Space"))) -> No of Racks | L52: 3 | M52: 3 | N52: =L52-M52 -> 0 | O52: 3 | Q52: =(442500)/12 -> 36875 | R52: =G52 -> Subscribed | S52: KW | T52: 6 | U52: =Z52 -> 3.5534673 | V52: =T52-U52 -> 2.4465327 | X52: =IF(V52<=0,0,(IF(R52="Rated",(V52+W52)*#REF!,(V52+W52)))) -> 2.4465327 | Y52: =IF(R52="Rated",T52*#REF!,T52) -> 6 | Z52: =AG52/28/24 -> 3.5534673 | AA52: =IF((V52*-1)>0, (V52*-1), 0) -> 0 | AB52: =90000/12 -> 7500 | AC52: =H52 -> Metered | AG52: 2387.93 | AI52: =IF(AH52="No of Seats","No of Seats",(IF(AH52="Space","Sq Ft",""))) | AL52: =AJ52-AK52 -> 0 | AP52: =Q52*O52 -> 110625 | AQ52: =AB52*AA52 -> 0 | AR52: =AG52*AF52*AD52 -> 0 | AS52: =AO52*AM52 -> 0 | AU52: =SUBTOTAL(9,AP52:AT52) -> 110625 | AW52: 721003988 | BC52: =IF(I52="Rack",AU52/L52,0)+IF(I52="U Space",AU52*40/L52,0)+IF(I52="Space",AU52*30/L52,0) -> 36875 | BD52: =+AU52/Y52 -> 18437.5 | BE52: =+($AP52+$AQ52+$AR52-BL52)/$Y52 -> #REF! | BF52: =+($AP52+$AQ52+$AR52-BM52)/$Y52 -> #REF! | BG52: =+($AP52+$AQ52+IF(H52="Bundled",0,Y52*0.85*AD52*AF52*30.5*24)-BN52)/$Y52 -> #REF! | BI52: =+AP52+AQ52+AR52 -> 110625 | BJ52: =+BI52-BK52 -> 110625 | BK52: =IF(H52="Bundled",MIN(Y52*#REF!*(1+#REF!),BI52),AR52) -> 0 | BL52: =IF($AG52>0,$AG52*#REF!*#REF!*(1+#REF!*(20/#REF!)/732),#REF!*Z52) -> #REF! | BM52: =IF($AG52>0,$AG52*#REF!*#REF!*(1+#REF!*(20/#REF!)/732),+#REF!*(Z52+X52)) -> #REF! | BN52: =IF(H52="Bundled",#REF!*Y52,#REF!*Y52*0.85) -> #REF! | BO52: =+BE52*Y52 -> #REF! | BP52: =+#REF!*Y52 -> #REF! | BQ52: =+BJ52-BP52 -> #REF! | BR52: =+BK52-BL52 -> #REF! | BS52: =+BQ52+BR52 -> #REF! | BT52: =+Y52 -> 6 | BU52: =+BE52 -> #REF! | BV52: =IF(H52="Bundled",BN52-BL52,AR52-BL52) -> #REF! | BW52: =IF(H52="Bundled",+(BG52-#REF!)*Y52,(AP52+AQ52)-Y52*#REF!) -> #REF! | BX52: =+BV52+BW52 -> #REF! | BY52: =+BV52/$BT52 -> #REF! | BZ52: =+BW52/$BT52 -> #REF! | CA52: =+BX52/$BT52 -> #REF!
A53: L5 | B53: L5B-01-11 & L5B-01-12 | C53: UPPCL (UP Power Corp Ltd) | D53: MANAGE SERVICES | G53: Rated | H53: Bundled | I53: Rack | J53: Uncaged | K53: =IF(I53="Rack","No of Racks",(IF(I53="Space","Sq Ft","U Space"))) -> No of Racks | L53: 2 | M53: 2 | N53: =L53-M53 -> 0 | O53: 2 | Q53: =(0)/12 -> 0 | R53: =G53 -> Rated | S53: KVA | T53: 6 | U53: 17.52 | V53: =T53-U53 -> -11.52 | X53: =IF(V53<=0,0,(IF(R53="Rated",(V53+W53)*#REF!,(V53+W53)))) -> 0 | Y53: =IF(R53="Rated",T53*#REF!,T53) -> #REF! | Z53: 5.2 | AA53: =IF((V53*-1)>0, (V53*-1), 0) -> 11.52 | AB53: 0 | AC53: =H53 -> Bundled | AI53: =IF(AH53="No of Seats","No of Seats",(IF(AH53="Space","Sq Ft",""))) | AL53: =AJ53-AK53 -> 0 | AP53: =Q53*O53 -> 0 | AQ53: =AB53*AA53 -> 0 | AR53: =AG53*AF53*AD53 -> 0 | AS53: =AO53*AM53 -> 0 | AU53: =SUBTOTAL(9,AP53:AT53) -> 0 | AW53: NA | BC53: =IF(I53="Rack",AU53/L53,0)+IF(I53="U Space",AU53*40/L53,0)+IF(I53="Space",AU53*30/L53,0) -> 0 | BD53: =+AU53/Y53 -> #REF! | BE53: =+($AP53+$AQ53+$AR53-BL53)/$Y53 -> #REF! | BF53: =+($AP53+$AQ53+$AR53-BM53)/$Y53 -> #REF! | BG53: =+($AP53+$AQ53+IF(H53="Bundled",0,Y53*0.85*AD53*AF53*30.5*24)-BN53)/$Y53 -> #REF! | BI53: =+AP53+AQ53+AR53 -> 0 | BJ53: =+BI53-BK53 -> #REF! | BK53: =IF(H53="Bundled",MIN(Y53*#REF!*(1+#REF!),BI53),AR53) -> #REF! | BL53: =IF($AG53>0,$AG53*#REF!*#REF!*(1+#REF!*(20/#REF!)/732),#REF!*Z53) -> #REF! | BM53: =IF($AG53>0,$AG53*#REF!*#REF!*(1+#REF!*(20/#REF!)/732),+#REF!*(Z53+X53)) -> #REF! | BN53: =IF(H53="Bundled",#REF!*Y53,#REF!*Y53*0.85) -> #REF! | BO53: =+BE53*Y53 -> #REF! | BP53: =+#REF!*Y53 -> #REF! | BQ53: =+BJ53-BP53 -> #REF! | BR53: =+BK53-BL53 -> #REF! | BS53: =+BQ53+BR53 -> #REF! | BT53: =+Y53 -> #REF! | BU53: =+BE53 -> #REF! | BV53: =IF(H53="Bundled",BN53-BL53,AR53-BL53) -> #REF! | BW53: =IF(H53="Bundled",+(BG53-#REF!)*Y53,(AP53+AQ53)-Y53*#REF!) -> #REF! | BX53: =+BV53+BW53 -> #REF! | BY53: =+BV53/$BT53 -> #REF! | BZ53: =+BW53/$BT53 -> #REF! | CA53: =+BX53/$BT53 -> #REF!
A54: L5 | B54: L5B-01-10, L5B-01-15, L5B-01-16 & L5B-01-17 | C54: FUSIONNET WEB SERVICES PVT LTD | D54: YES | G54: Subscribed | H54: Metered | I54: Rack | J54: Uncaged | K54: =IF(I54="Rack","No of Racks",(IF(I54="Space","Sq Ft","U Space"))) -> No of Racks | L54: 4 | M54: 4 | N54: =L54-M54 -> 0 | O54: 4 | Q54: =(210000/12) -> 17500 | R54: =G54 -> Subscribed | S54: KW | T54: 12 | U54: =Z54 -> 14.085685 | V54: =T54-U54 -> -2.0856845 | X54: =IF(V54<=0,0,(IF(R54="Rated",(V54+W54)*#REF!,(V54+W54)))) -> 0 | Y54: =IF(R54="Rated",T54*#REF!,T54) -> 12 | Z54: =AG54/28/24 -> 14.085685 | AA54: =IF((V54*-1)>0, (V54*-1), 0) -> 2.0856845 | AB54: 0 | AC54: =H54 -> Metered | AD54: 1 | AE54: Fixed | AF54: 16.4 | AG54: 9465.58 | AI54: =IF(AH54="No of Seats","No of Seats",(IF(AH54="Space","Sq Ft",""))) | AL54: =AJ54-AK54 -> 0 | AP54: =Q54*O54 -> 70000 | AQ54: =AB54*AA54 -> 0 | AR54: =AG54*AF54*AD54 -> 155235.51 | AS54: =AO54*AM54 -> 0 | AT54: =(251000+34400)/12 -> 23783.333 | AU54: =SUBTOTAL(9,AP54:AT54) -> 249018.85 | AW54: Renewal | BC54: =IF(I54="Rack",AU54/L54,0)+IF(I54="U Space",AU54*40/L54,0)+IF(I54="Space",AU54*30/L54,0) -> 62254.711 | BD54: =+AU54/Y54 -> 20751.57 | BE54: =+($AP54+$AQ54+$AR54-BL54)/$Y54 -> #REF! | BF54: =+($AP54+$AQ54+$AR54-BM54)/$Y54 -> #REF! | BG54: =+($AP54+$AQ54+IF(H54="Bundled",0,Y54*0.85*AD54*AF54*30.5*24)-BN54)/$Y54 -> #REF! | BI54: =+AP54+AQ54+AR54 -> 225235.51 | BJ54: =+BI54-BK54 -> 70000 | BK54: =IF(H54="Bundled",MIN(Y54*#REF!*(1+#REF!),BI54),AR54) -> 155235.51 | BL54: =IF($AG54>0,$AG54*#REF!*#REF!*(1+#REF!*(20/#REF!)/732),#REF!*Z54) -> #REF! | BM54: =IF($AG54>0,$AG54*#REF!*#REF!*(1+#REF!*(20/#REF!)/732),+#REF!*(Z54+X54)) -> #REF! | BN54: =IF(H54="Bundled",#REF!*Y54,#REF!*Y54*0.85) -> #REF! | BO54: =+BE54*Y54 -> #REF! | BP54: =+#REF!*Y54 -> #REF! | BQ54: =+BJ54-BP54 -> #REF! | BR54: =+BK54-BL54 -> #REF! | BS54: =+BQ54+BR54 -> #REF! | BT54: =+Y54 -> 12 | BU54: =+BE54 -> #REF! | BV54: =IF(H54="Bundled",BN54-BL54,AR54-BL54) -> #REF! | BW54: =IF(H54="Bundled",+(BG54-#REF!)*Y54,(AP54+AQ54)-Y54*#REF!) -> #REF! | BX54: =+BV54+BW54 -> #REF! | BY54: =+BV54/$BT54 -> #REF! | BZ54: =+BW54/$BT54 -> #REF! | CA54: =+BX54/$BT54 -> #REF! | CB54: not able to trace PO/match price with PO
A55: L5 | B55: Server Hall 5B | C55: HT MEDIA LTD | D55: YES | G55: Subscribed | H55: Metered | I55: Space | J55: Caged | K55: =IF(I55="Rack","No of Racks",(IF(I55="Space","Sq Ft","U Space"))) -> Sq Ft | L55: 160 | M55: 160 | N55: =L55-M55 -> 0 | O55: 7 | Q55: =(227557+281631)/12 -> 42432.333 | R55: =G55 -> Subscribed | S55: KW | T55: 24.5 | U55: =Z55 -> 19.003571 | V55: =T55-U55 -> 5.4964286 | X55: =IF(V55<=0,0,(IF(R55="Rated",(V55+W55)*#REF!,(V55+W55)))) -> 5.4964286 | Y55: =IF(R55="Rated",T55*#REF!,T55) -> 24.5 | Z55: =AG55/28/24 -> 19.003571 | AA55: =IF((V55*-1)>0, (V55*-1), 0) -> 0 | AB55: =72000/12 -> 6000 | AC55: =H55 -> Metered | AD55: 1 | AE55: Fixed | AF55: 16.2 | AG55: 12770.4 | AI55: =IF(AH55="No of Seats","No of Seats",(IF(AH55="Space","Sq Ft",""))) | AL55: =AJ55-AK55 -> 0 | AP55: =Q55*O55 -> 297026.33 | AQ55: =AB55*AA55 -> 0 | AR55: =AG55*AF55*AD55 -> 206880.48 | AS55: =AO55*AM55 -> 0 | AT55: =(4358+75000)/12 -> 6613.1667 | AU55: =SUBTOTAL(9,AP55:AT55) -> 510519.98 | AW55: Renewal | BC55: =IF(I55="Rack",AU55/L55,0)+IF(I55="U Space",AU55*40/L55,0)+IF(I55="Space",AU55*30/L55,0) -> 95722.496 | BD55: =+AU55/Y55 -> 20837.55 | BE55: =+($AP55+$AQ55+$AR55-BL55)/$Y55 -> #REF! | BF55: =+($AP55+$AQ55+$AR55-BM55)/$Y55 -> #REF! | BG55: =+($AP55+$AQ55+IF(H55="Bundled",0,Y55*0.85*AD55*AF55*30.5*24)-BN55)/$Y55 -> #REF! | BI55: =+AP55+AQ55+AR55 -> 503906.81 | BJ55: =+BI55-BK55 -> 297026.33 | BK55: =IF(H55="Bundled",MIN(Y55*#REF!*(1+#REF!),BI55),AR55) -> 206880.48 | BL55: =IF($AG55>0,$AG55*#REF!*#REF!*(1+#REF!*(20/#REF!)/732),#REF!*Z55) -> #REF! | BM55: =IF($AG55>0,$AG55*#REF!*#REF!*(1+#REF!*(20/#REF!)/732),+#REF!*(Z55+X55)) -> #REF! | BN55: =IF(H55="Bundled",#REF!*Y55,#REF!*Y55*0.85) -> #REF! | BO55: =+BE55*Y55 -> #REF! | BP55: =+#REF!*Y55 -> #REF! | BQ55: =+BJ55-BP55 -> #REF! | BR55: =+BK55-BL55 -> #REF! | BS55: =+BQ55+BR55 -> #REF! | BT55: =+Y55 -> 24.5 | BU55: =+BE55 -> #REF! | BV55: =IF(H55="Bundled",BN55-BL55,AR55-BL55) -> #REF! | BW55: =IF(H55="Bundled",+(BG55-#REF!)*Y55,(AP55+AQ55)-Y55*#REF!) -> #REF! | BX55: =+BV55+BW55 -> #REF! | BY55: =+BV55/$BT55 -> #REF! | BZ55: =+BW55/$BT55 -> #REF! | CA55: =+BX55/$BT55 -> #REF! | CB55: Have updated new renewed rates. Also number of racks billed Is now 11. Pls confirm this.
A56: L5 | B56: Server Hall 5B | C56: Sify NOC | D56: YES | G56: Rated | H56: Bundled | I56: Space | J56: Caged | K56: Sq Ft | L56: 224 | M56: 224 | N56: =L56-M56 -> 0 | O56: 0 | Q56: =(0)/12 -> 0 | R56: =G56 -> Rated | S56: KVA | T56: 24 | U56: 22.99 | V56: =T56-U56 -> 1.01 | X56: =IF(V56<=0,0,(IF(R56="Rated",(V56+W56)*#REF!,(V56+W56)))) -> #REF! | Y56: =IF(R56="Rated",T56*#REF!,T56) -> #REF! | Z56: 10.36 | AA56: =IF((V56*-1)>0, (V56*-1), 0) -> 0 | AB56: 0 | AC56: =H56 -> Bundled | AI56: =IF(AH56="No of Seats","No of Seats",(IF(AH56="Space","Sq Ft",""))) | AL56: =AJ56-AK56 -> 0 | AP56: =Q56*O56 -> 0 | AQ56: =AB56*AA56 -> 0 | AR56: =AG56*AF56*AD56 -> 0 | AS56: =AO56*AM56 -> 0 | AU56: =SUBTOTAL(9,AP56:AT56) -> 0 | AW56: NA | BC56: =IF(I56="Rack",AU56/L56,0)+IF(I56="U Space",AU56*40/L56,0)+IF(I56="Space",AU56*30/L56,0) -> 0 | BD56: =+AU56/Y56 -> #REF! | BE56: =+($AP56+$AQ56+$AR56-BL56)/$Y56 -> #REF! | BF56: =+($AP56+$AQ56+$AR56-BM56)/$Y56 -> #REF! | BG56: =+($AP56+$AQ56+IF(H56="Bundled",0,Y56*0.85*AD56*AF56*30.5*24)-BN56)/$Y56 -> #REF! | BI56: =+AP56+AQ56+AR56 -> 0 | BJ56: =+BI56-BK56 -> #REF! | BK56: =IF(H56="Bundled",MIN(Y56*#REF!*(1+#REF!),BI56),AR56) -> #REF! | BL56: =IF($AG56>0,$AG56*#REF!*#REF!*(1+#REF!*(20/#REF!)/732),#REF!*Z56) -> #REF! | BM56: =IF($AG56>0,$AG56*#REF!*#REF!*(1+#REF!*(20/#REF!)/732),+#REF!*(Z56+X56)) -> #REF! | BN56: =IF(H56="Bundled",#REF!*Y56,#REF!*Y56*0.85) -> #REF! | BO56: =+BE56*Y56 -> #REF! | BP56: =+#REF!*Y56 -> #REF! | BQ56: =+BJ56-BP56 -> #REF! | BR56: =+BK56-BL56 -> #REF! | BS56: =+BQ56+BR56 -> #REF! | BT56: =+Y56 -> #REF! | BU56: =+BE56 -> #REF! | BV56: =IF(H56="Bundled",BN56-BL56,AR56-BL56) -> #REF! | BW56: =IF(H56="Bundled",+(BG56-#REF!)*Y56,(AP56+AQ56)-Y56*#REF!) -> #REF! | BX56: =+BV56+BW56 -> #REF! | BY56: =+BV56/$BT56 -> #REF! | BZ56: =+BW56/$BT56 -> #REF! | CA56: =+BX56/$BT56 -> #REF!
A57: L5 | B57: Server Hall 5B | C57: HEALTH INSURANCE TPA OF INDIA LTD | D57: YES | G57: Rated | H57: Bundled | I57: Space | J57: Caged | K57: Sq Ft | L57: 224 | M57: 224 | N57: 0 | O57: 8 | Q57: =(5718251+249311)/8/12 -> 62162.104 | R57: =G57 -> Rated | S57: KVA | T57: =7.5*7 -> 52.5 | U57: 42.48 | V57: =T57-U57 -> 10.02 | X57: =IF(V57<=0,0,(IF(R57="Rated",(V57+W57)*#REF!,(V57+W57)))) -> #REF! | Y57: =IF(R57="Rated",T57*#REF!,T57) -> #REF! | Z57: 18.11 | AA57: =IF((V57*-1)>0, (V57*-1), 0) -> 0 | AB57: =90000/12 -> 7500 | AC57: =H57 -> Bundled | AI57: =IF(AH57="No of Seats","No of Seats",(IF(AH57="Space","Sq Ft",""))) | AL57: =AJ57-AK57 -> 0 | AO57: =15000/12 -> 1250 | AP57: =Q57*O57 -> 497296.83 | AQ57: =AB57*AA57 -> 0 | AR57: =AG57*AF57*AD57 -> 0 | AS57: =AO57*AM57 -> 0 | AU57: =SUBTOTAL(9,AP57:AT57) -> 497296.83 | AW57: 721002051 | BC57: =IF(I57="Rack",AU57/L57,0)+IF(I57="U Space",AU57*40/L57,0)+IF(I57="Space",AU57*30/L57,0) -> 66602.254 | BD57: =+AU57/Y57 -> #REF! | BE57: =+($AP57+$AQ57+$AR57-BL57)/$Y57 -> #REF! | BF57: =+($AP57+$AQ57+$AR57-BM57)/$Y57 -> #REF! | BG57: =+($AP57+$AQ57+IF(H57="Bundled",0,Y57*0.85*AD57*AF57*30.5*24)-BN57)/$Y57 -> #REF! | BI57: =+AP57+AQ57+AR57 -> 497296.83 | BJ57: =+BI57-BK57 -> #REF! | BK57: =IF(H57="Bundled",MIN(Y57*#REF!*(1+#REF!),BI57),AR57) -> #REF! | BL57: =IF($AG57>0,$AG57*#REF!*#REF!*(1+#REF!*(20/#REF!)/732),#REF!*Z57) -> #REF! | BM57: =IF($AG57>0,$AG57*#REF!*#REF!*(1+#REF!*(20/#REF!)/732),+#REF!*(Z57+X57)) -> #REF! | BN57: =IF(H57="Bundled",#REF!*Y57,#REF!*Y57*0.85) -> #REF! | BO57: =+BE57*Y57 -> #REF! | BP57: =+#REF!*Y57 -> #REF! | BQ57: =+BJ57-BP57 -> #REF! | BR57: =+BK57-BL57 -> #REF! | BS57: =+BQ57+BR57 -> #REF! | BT57: =+Y57 -> #REF! | BU57: =+BE57 -> #REF! | BV57: =IF(H57="Bundled",BN57-BL57,AR57-BL57) -> #REF! | BW57: =IF(H57="Bundled",+(BG57-#REF!)*Y57,(AP57+AQ57)-Y57*#REF!) -> #REF! | BX57: =+BV57+BW57 -> #REF! | BY57: =+BV57/$BT57 -> #REF! | BZ57: =+BW57/$BT57 -> #REF! | CA57: =+BX57/$BT57 -> #REF! | CB57: Updated to yr 3 rates from yr 2 rates. Pls confirm.
A58: L5 | B58: Server Hall 5B | C58: MAX LIFE INSURANCE PVT LTD | D58: YES | E58: 5 | G58: Subscribed | H58: Metered | I58: Space | J58: Caged | K58: Sq Ft | L58: 704 | M58: 704 | N58: =L58-M58 -> 0 | O58: 34 | Q58: =(5850000/32)/12 -> 15234.375 | R58: =G58 -> Subscribed | S58: KW | T58: 75 | U58: =Z58 -> 67.006726 | V58: =T58-U58 -> 7.9932738 | X58: =IF(V58<=0,0,(IF(R58="Rated",(V58+W58)*#REF!,(V58+W58)))) -> 7.9932738 | Y58: =IF(R58="Rated",T58*#REF!,T58) -> 75 | Z58: =AG58/28/24 -> 67.006726 | AA58: =IF((V58*-1)>0, (V58*-1), 0) -> 0 | AB58: =65000/12 -> 5416.6667 | AC58: =H58 -> Metered | AD58: 1 | AE58: Fixed | AF58: 15 | AG58: 45028.52 | AH58: No of Seats | AI58: =IF(AH58="No of Seats","No of Seats",(IF(AH58="Space","Sq Ft",""))) -> No of Seats | AJ58: 5 | AK58: 5 | AL58: =AJ58-AK58 -> 0 | AM58: 5 | AO58: =71000/12 -> 5916.6667 | AP58: =Q58*O58 -> 517968.75 | AQ58: =AB58*AA58 -> 0 | AR58: =AG58*AF58*AD58 -> 675427.8 | AS58: =AO58*AM58 -> 29583.333 | AT58: =(64000+63415+30003)/12 -> 13118.167 | AU58: =SUBTOTAL(9,AP58:AT58) -> 1236098 | AW58: 721004019, 731002977 | BC58: =IF(I58="Rack",AU58/L58,0)+IF(I58="U Space",AU58*40/L58,0)+IF(I58="Space",AU58*30/L58,0) -> 52674.633 | BD58: =+AU58/Y58 -> 16481.307 | BE58: =+($AP58+$AQ58+$AR58-BL58)/$Y58 -> #REF! | BF58: =+($AP58+$AQ58+$AR58-BM58)/$Y58 -> #REF! | BG58: =+($AP58+$AQ58+IF(H58="Bundled",0,Y58*0.85*AD58*AF58*30.5*24)-BN58)/$Y58 -> #REF! | BI58: =+AP58+AQ58+AR58 -> 1193396.5 | BJ58: =+BI58-BK58 -> 517968.75 | BK58: =IF(H58="Bundled",MIN(Y58*#REF!*(1+#REF!),BI58),AR58) -> 675427.8 | BL58: =IF($AG58>0,$AG58*#REF!*#REF!*(1+#REF!*(20/#REF!)/732),#REF!*Z58) -> #REF! | BM58: =IF($AG58>0,$AG58*#REF!*#REF!*(1+#REF!*(20/#REF!)/732),+#REF!*(Z58+X58)) -> #REF! | BN58: =IF(H58="Bundled",#REF!*Y58,#REF!*Y58*0.85) -> #REF! | BO58: =+BE58*Y58 -> #REF! | BP58: =+#REF!*Y58 -> #REF! | BQ58: =+BJ58-BP58 -> #REF! | BR58: =+BK58-BL58 -> #REF! | BS58: =+BQ58+BR58 -> #REF! | BT58: =+Y58 -> 75 | BU58: =+BE58 -> #REF! | BV58: =IF(H58="Bundled",BN58-BL58,AR58-BL58) -> #REF! | BW58: =IF(H58="Bundled",+(BG58-#REF!)*Y58,(AP58+AQ58)-Y58*#REF!) -> #REF! | BX58: =+BV58+BW58 -> #REF! | BY58: =+BV58/$BT58 -> #REF! | BZ58: =+BW58/$BT58 -> #REF! | CA58: =+BX58/$BT58 -> #REF!
A59: L5 | B59: Server Hall 5B | C59: AMAZON DATA SERVICES INDIA PVT LTD-HOSTING | D59: YES | G59: Subscribed | H59: Metered | I59: Space | J59: Caged | K59: Sq Ft | L59: 288 | M59: 288 | N59: =L59-M59 -> 0 | O59: 288 | Q59: =(164001+27333+21866)/6 -> 35533.333 | R59: =G59 -> Subscribed | S59: KW | T59: 36 | U59: =Z59 -> 2.5998512 | V59: =T59-U59 -> 33.400149 | X59: =IF(V59<=0,0,(IF(R59="Rated",(V59+W59)*#REF!,(V59+W59)))) -> 33.400149 | Y59: =IF(R59="Rated",T59*#REF!,T59) -> 36 | Z59: =AG59/28/24 -> 2.5998512 | AA59: =IF((V59*-1)>0, (V59*-1), 0) -> 0 | AB59: 0 | AC59: =H59 -> Metered | AD59: 1.7 | AE59: Variable | AF59: 9.3 | AG59: 1747.1 | AI59: =IF(AH59="No of Seats","No of Seats",(IF(AH59="Space","Sq Ft",""))) | AL59: =AJ59-AK59 -> 0 | AP59: =Q59*O59 -> 10233600 | AQ59: =AB59*AA59 -> 0 | AR59: =AG59*AF59*AD59 -> 27621.651 | AS59: =AO59*AM59 -> 0 | AT59: 20883 | AU59: =SUBTOTAL(9,AP59:AT59) -> 10282105 | AW59: 721002808 & 711067576 | BC59: =IF(I59="Rack",AU59/L59,0)+IF(I59="U Space",AU59*40/L59,0)+IF(I59="Space",AU59*30/L59,0) -> 1071052.6 | BD59: =+AU59/Y59 -> 285614.02 | BE59: =+($AP59+$AQ59+$AR59-BL59)/$Y59 -> #REF! | BF59: =+($AP59+$AQ59+$AR59-BM59)/$Y59 -> #REF! | BG59: =+($AP59+$AQ59+IF(H59="Bundled",0,Y59*0.85*AD59*AF59*30.5*24)-BN59)/$Y59 -> #REF! | BI59: =+AP59+AQ59+AR59 -> 10261222 | BJ59: =+BI59-BK59 -> 10233600 | BK59: =IF(H59="Bundled",MIN(Y59*#REF!*(1+#REF!),BI59),AR59) -> 27621.651 | BL59: =IF($AG59>0,$AG59*#REF!*#REF!*(1+#REF!*(20/#REF!)/732),#REF!*Z59) -> #REF! | BM59: =IF($AG59>0,$AG59*#REF!*#REF!*(1+#REF!*(20/#REF!)/732),+#REF!*(Z59+X59)) -> #REF! | BN59: =IF(H59="Bundled",#REF!*Y59,#REF!*Y59*0.85) -> #REF! | BO59: =+BE59*Y59 -> #REF! | BP59: =+#REF!*Y59 -> #REF! | BQ59: =+BJ59-BP59 -> #REF! | BR59: =+BK59-BL59 -> #REF! | BS59: =+BQ59+BR59 -> #REF! | BT59: =+Y59 -> 36 | BU59: =+BE59 -> #REF! | BV59: =IF(H59="Bundled",BN59-BL59,AR59-BL59) -> #REF! | BW59: =IF(H59="Bundled",+(BG59-#REF!)*Y59,(AP59+AQ59)-Y59*#REF!) -> #REF! | BX59: =+BV59+BW59 -> #REF! | BY59: =+BV59/$BT59 -> #REF! | BZ59: =+BW59/$BT59 -> #REF! | CA59: =+BX59/$BT59 -> #REF!
A60: L5 | B60: Server Hall 5B | C60: GOOGLE INDIA PVT LTD(DEL-03 Google) | D60: YES | G60: Subscribed | H60: Metered | I60: Space | J60: Caged | K60: =IF(I60="Rack","No of Racks",(IF(I60="Space","Sq Ft","U Space"))) -> Sq Ft | L60: 1085 | M60: 1085 | N60: =L60-M60 -> 0 | O60: 1085 | Q60: =(1250000)/1085 -> 1152.0737 | R60: =G60 -> Subscribed | S60: KW | T60: 250 | U60: =Z60 -> 102.12548 | V60: =T60-U60 -> 147.87452 | X60: =IF(V60<=0,0,(IF(R60="Rated",(V60+W60)*#REF!,(V60+W60)))) -> 147.87452 | Y60: =IF(R60="Rated",T60*#REF!,T60) -> 250 | Z60: =AG60/28/24 -> 102.12548 | AA60: =IF((V60*-1)>0, (V60*-1), 0) -> 0 | AB60: =60000/12 -> 5000 | AC60: =H60 -> Metered | AD60: 1.7 | AE60: Variable | AF60: 10.88 | AG60: 68628.32 | AI60: =IF(AH60="No of Seats","No of Seats",(IF(AH60="Space","Sq Ft",""))) | AL60: =AJ60-AK60 -> 0 | AP60: =Q60*O60 -> 1250000 | AQ60: =AB60*AA60 -> 0 | AR60: =AG60*AF60*AD60 -> 1269349.4 | AS60: =AO60*AM60 -> 0 | AT60: =2500+1250+12500 -> 16250 | AU60: =SUBTOTAL(9,AP60:AT60) -> 2535599.4 | AW60: 721004425, 721004426, 721004427 & 711101631 | BC60: =IF(I60="Rack",AU60/L60,0)+IF(I60="U Space",AU60*40/L60,0)+IF(I60="Space",AU60*30/L60,0) -> 70108.739 | BD60: =+AU60/Y60 -> 10142.398 | BE60: =+($AP60+$AQ60+$AR60-BL60)/$Y60 -> #REF! | BF60: =+($AP60+$AQ60+$AR60-BM60)/$Y60 -> #REF! | BG60: =+($AP60+$AQ60+IF(H60="Bundled",0,Y60*0.85*AD60*AF60*30.5*24)-BN60)/$Y60 -> #REF! | BI60: =+AP60+AQ60+AR60 -> 2519349.4 | BJ60: =+BI60-BK60 -> 1250000 | BK60: =IF(H60="Bundled",MIN(Y60*#REF!*(1+#REF!),BI60),AR60) -> 1269349.4 | BL60: =IF($AG60>0,$AG60*#REF!*#REF!*(1+#REF!*(20/#REF!)/732),#REF!*Z60) -> #REF! | BM60: =IF($AG60>0,$AG60*#REF!*#REF!*(1+#REF!*(20/#REF!)/732),+#REF!*(Z60+X60)) -> #REF! | BN60: =IF(H60="Bundled",#REF!*Y60,#REF!*Y60*0.85) -> #REF! | BO60: =+BE60*Y60 -> #REF! | BP60: =+#REF!*Y60 -> #REF! | BQ60: =+BJ60-BP60 -> #REF! | BR60: =+BK60-BL60 -> #REF! | BS60: =+BQ60+BR60 -> #REF! | BT60: =+Y60 -> 250 | BU60: =+BE60 -> #REF! | BV60: =IF(H60="Bundled",BN60-BL60,AR60-BL60) -> #REF! | BW60: =IF(H60="Bundled",+(BG60-#REF!)*Y60,(AP60+AQ60)-Y60*#REF!) -> #REF! | BX60: =+BV60+BW60 -> #REF! | BY60: =+BV60/$BT60 -> #REF! | BZ60: =+BW60/$BT60 -> #REF! | CA60: =+BX60/$BT60 -> #REF!
A61: L5 | B61: L5B-01-14 | C61: FUSIONNET WEB SERVICES PVT LTD | D61: YES | G61: Subscribed | H61: Metered | I61: Rack | J61: UNcaged | K61: No of Racks | L61: 1 | M61: 1 | N61: =L61-M61 -> 0 | O61: 1 | S61: KW | T61: 3 | U61: =Z61 -> 2.4092262 | Z61: =AG61/28/24 -> 2.4092262 | AC61: =H61 -> Metered | AG61: 1619 | BL61: =IF($AG61>0,$AG61*#REF!*#REF!*(1+#REF!*(20/#REF!)/732),#REF!*Z61) -> #REF!
A62: L5 | B62: L5B-01-13 | C62: CYBER24 TECHNOLOGIES PRIVATE LIMITED | D62: NO | G62: Subscribed | H62: Metered | I62: Rack | J62: Uncaged | K62: No of Racks | L62: 1 | M62: 1 | N62: =L62-M62 -> 0 | O62: 1 | S62: KW | T62: 3 | U62: =Z62 -> 0.96279762 | Z62: =AG62/28/24 -> 0.96279762 | AC62: =H62 -> Metered | AG62: 647
A63: L5 | B63: L5A-02-10 | C63: SHIVTEL COMMUNICATIONS PRIVATE LIMITED | D63: YES | G63: Subscribed | H63: Metered | I63: Rack | J63: Uncaged | K63: No of Racks | L63: 1 | M63: 1 | N63: =L63-M63 -> 0 | O63: 1 | S63: KW | T63: 3 | U63: =Z63 -> 0.71325893 | Z63: =AG63/28/24 -> 0.71325893 | AC63: =H63 -> Metered | AG63: 479.31
A64: L5 | B64: L5B-01-08 | C64: Abhipra Capital Limited | D64: YES | G64: Subscribed | H64: Bundled | I64: Rack | J64: Uncaged | K64: =IF(I64="Rack","No of Racks",(IF(I64="Space","Sq Ft","U Space"))) -> No of Racks | L64: 1 | M64: 1 | N64: =L64-M64 -> 0 | O64: 1 | Q64: =188000/12 -> 15666.667 | R64: =G64 -> Subscribed | S64: KW | T64: 7.5 | U64: 7.23 | V64: =T64-U64 -> 0.27 | X64: =IF(V64<=0,0,(IF(R64="Rated",(V64+W64)*#REF!,(V64+W64)))) -> 0.27 | Y64: =IF(R64="Rated",T64*#REF!,T64) -> 7.5 | Z64: =AG64/28/24 -> 1.0627232 | AA64: =IF((V64*-1)>0, (V64*-1), 0) -> 0 | AB64: =75000/12 -> 6250 | AC64: =H64 -> Bundled | AD64: 1 | AE64: Fixed | AF64: 17 | AG64: 714.15 | AI64: =IF(AH64="No of Seats","No of Seats",(IF(AH64="Space","Sq Ft",""))) | AL64: =AJ64-AK64 -> 0 | AP64: =Q64*O64 -> 15666.667 | AQ64: =AB64*AA64 -> 0 | AR64: =AG64*AF64*AD64 -> 12140.55 | AS64: =AO64*AM64 -> 0 | AT64: =(190000+75000)/12 -> 22083.333 | AU64: =SUBTOTAL(9,AP64:AT64) -> 49890.55 | AW64: Renewal | AX64: 43831 | AY64: 1 | AZ64: 44196 | BC64: =IF(I64="Rack",AU64/L64,0)+IF(I64="U Space",AU64*40/L64,0)+IF(I64="Space",AU64*30/L64,0) -> 49890.55 | BD64: =+AU64/Y64 -> 6652.0733 | BE64: =+($AP64+$AQ64+$AR64-BL64)/$Y64 -> #REF! | BF64: =+($AP64+$AQ64+$AR64-BM64)/$Y64 -> #REF! | BG64: =+($AP64+$AQ64+IF(H64="Bundled",0,Y64*0.85*AD64*AF64*30.5*24)-BN64)/$Y64 -> #REF! | BI64: =+AP64+AQ64+AR64 -> 27807.217 | BJ64: =+BI64-BK64 -> #REF! | BK64: =IF(H64="Bundled",MIN(Y64*#REF!*(1+#REF!),BI64),AR64) -> #REF! | BL64: =IF($AG64>0,$AG64*#REF!*#REF!*(1+#REF!*(20/#REF!)/732),#REF!*Z64) -> #REF! | BM64: =IF($AG64>0,$AG64*#REF!*#REF!*(1+#REF!*(20/#REF!)/732),+#REF!*(Z64+X64)) -> #REF! | BN64: =IF(H64="Bundled",#REF!*Y64,#REF!*Y64*0.85) -> #REF! | BO64: =+BE64*Y64 -> #REF! | BP64: =+#REF!*Y64 -> #REF! | BQ64: =+BJ64-BP64 -> #REF! | BR64: =+BK64-BL64 -> #REF! | BS64: =+BQ64+BR64 -> #REF! | BT64: =+Y64 -> 7.5 | BU64: =+BE64 -> #REF! | BV64: =IF(H64="Bundled",BN64-BL64,AR64-BL64) -> #REF! | BW64: =IF(H64="Bundled",+(BG64-#REF!)*Y64,(AP64+AQ64)-Y64*#REF!) -> #REF! | BX64: =+BV64+BW64 -> #REF! | BY64: =+BV64/$BT64 -> #REF! | BZ64: =+BW64/$BT64 -> #REF! | CA64: =+BX64/$BT64 -> #REF!
A65: L5 | B65: L5B-02-03, L5B-02-04 , L5B-03-04 & L5B-03-05 | C65: AKAMAI INDIA NETWORKS PRIVATE LIMITED | D65: YES | G65: Subscribed | H65: Metered | I65: Rack | J65: Uncaged | K65: =IF(I65="Rack","No of Racks",(IF(I65="Space","Sq Ft","U Space"))) -> No of Racks | L65: 4 | M65: 4 | N65: =L65-M65 -> 0 | O65: 4 | R65: =G65 -> Subscribed | S65: KW | T65: 20 | U65: =Z65 -> 11.776339 | V65: =T65-U65 -> 8.2236607 | X65: =IF(V65<=0,0,(IF(R65="Rated",(V65+W65)*#REF!,(V65+W65)))) -> 8.2236607 | Y65: =IF(R65="Rated",T65*#REF!,T65) -> 20 | Z65: =AG65/28/24 -> 11.776339 | AC65: Metered | AG65: 7913.7 | BL65: =IF($AG65>0,$AG65*#REF!*#REF!*(1+#REF!*(20/#REF!)/732),#REF!*Z65) -> #REF! | BM65: =IF($AG65>0,$AG65*#REF!*#REF!*(1+#REF!*(20/#REF!)/732),+#REF!*(Z65+X65)) -> #REF! | BN65: =IF(H65="Bundled",#REF!*Y65,#REF!*Y65*0.85) -> #REF!
A66: L5 | B66: L5B-02-05, L5B-02-06 & L5B-03-06 | C66: AKAMAI INDIA NETWORKS PRIVATE LIMITED | D66: YES | G66: Subscribed | H66: Metered | I66: Rack | J66: Uncaged | K66: No of Racks | L66: 3 | M66: 0 | N66: =L66-M66 -> 3 | O66: 0 | R66: Subscribed | S66: KW | T66: 15 | U66: =Z66 -> 3.0089286 | V66: =T66-U66 -> 11.991071 | X66: =IF(V66<=0,0,(IF(R66="Rated",(V66+W66)*#REF!,(V66+W66)))) -> 11.991071 | Y66: =IF(R66="Rated",T66*#REF!,T66) -> 15 | Z66: =AG66/28/24 -> 3.0089286 | AC66: Metered | AG66: 2022
A67: L5 | B67: L5A-01-11 | C67: VELOCITY SIGNALS PRIVATE LIMITED | D67: YES | G67: Subscribed | H67: Metered | I67: Rack | J67: Uncaged | K67: =IF(I67="Rack","No of Racks",(IF(I67="Space","Sq Ft","U Space"))) -> No of Racks | L67: 1 | M67: 1 | N67: =L67-M67 -> 0 | O67: 1 | R67: =G67 -> Subscribed | S67: KW | T67: 3 | U67: =Z67 -> 0.20833333 | V67: =T67-U67 -> 2.7916667 | X67: =IF(V67<=0,0,(IF(R67="Rated",(V67+W67)*#REF!,(V67+W67)))) -> 2.7916667 | Y67: =IF(R67="Rated",T67*#REF!,T67) -> 3 | Z67: =AG67/28/24 -> 0.20833333 | AA67: =IF((V67*-1)>0, (V67*-1), 0) -> 0 | AC67: =H67 -> Metered | AD67: 1 | AE67: Fixed | AG67: 140 | AI67: =IF(AH67="No of Seats","No of Seats",(IF(AH67="Space","Sq Ft",""))) | AL67: =AJ67-AK67 -> 0 | AQ67: =AB67*AA67 -> 0 | AR67: =AG67*AF67*AD67 -> 0 | AS67: =AO67*AM67 -> 0 | AU67: =SUBTOTAL(9,AP67:AT67) -> 0 | BC67: =IF(I67="Rack",AU67/L67,0)+IF(I67="U Space",AU67*40/L67,0)+IF(I67="Space",AU67*30/L67,0) -> 0 | BD67: =+AU67/Y67 -> 0 | BE67: =+($AP67+$AQ67+$AR67-BL67)/$Y67 -> #REF! | BI67: =+AP67+AQ67+AR67 -> 0 | BJ67: =+BI67-BK67 -> 0 | BK67: =IF(H67="Bundled",MIN(Y67*#REF!*(1+#REF!),BI67),AR67) -> 0 | BL67: =IF($AG67>0,$AG67*#REF!*#REF!*(1+#REF!*(20/#REF!)/732),#REF!*Z67) -> #REF! | BO67: =+BE67*Y67 -> #REF! | BP67: =+#REF!*Y67 -> #REF! | BQ67: =+BJ67-BP67 -> #REF! | BR67: =+BK67-BL67 -> #REF! | BS67: =+BQ67+BR67 -> #REF! | BT67: =+Y67 -> 3 | BU67: =+BE67 -> #REF! | BV67: =IF(H67="Bundled",BN67-BL67,AR67-BL67) -> #REF! | BW67: =IF(H67="Bundled",+(BG67-#REF!)*Y67,(AP67+AQ67)-Y67*#REF!) -> #REF! | BX67: =+BV67+BW67 -> #REF! | BY67: =+BV67/$BT67 -> #REF! | BZ67: =+BW67/$BT67 -> #REF! | CA67: =+BX67/$BT67 -> #REF!
